Workbook

Sheet Cover
A1: ETERNAL LIMITED (formerly Zomato Ltd) | NSE: ETERNAL | BSE: 543320 | E1: =Data_Sources!$D$15&" | "&Data_Sources!$E$15&" | "&Data_Sources!$F$15 -> Eternal Q4FY26 shareholders' letter | Annexure A & B (reconciliation to reported P&L) | https://b.zmtcdn.com/investor-relations/Eternal_Shareholders_Letter_Q4FY26_Results.pdf
A3: MODEL SCOPE
A4: ="Historicals: FY2023A–FY2026A (audited consolidated results, Ind AS; FY23A–FY24A partly incomplete — see Checks). Forecast: FY2027E–FY2034E. Valuation date: FY2026A balance sheet; market price "&TEXT(Assumptions!B142,"0")&"." -> Historicals: FY2023A–FY2026A (audited consolidated results, Ind AS; FY23A–FY24A partly incomplete — see Checks). Forecast: FY2027E–FY2034E. Valuation date: FY2026A balance sheet; market price 281.
A5: All figures in INR crore unless stated. FY = year ending 31 March. Segment build uses company-disclosed NOV / Adjusted Revenue / Adjusted EBITDA.
A6: Adjusted EBITDA = EBITDA + share-based payment expense − rent paid on Ind AS 116 leases (company definition, Q4FY26 letter).
A7: Every input is tagged with its source in column P of Assumptions and logged on the Data_Sources tab. Items without a locatable source are marked MANUAL – OPEN (yellow) and counted on Checks!B5.
A9: KEY OUTPUTS | B9: Unit | C9: FY2026A | D9: FY2034E
A10: B2C Net Order Value (NOV) | B10: INR Cr | C10: ='Revenue Schedule'!F16 -> 95960 | D10: ='Revenue Schedule'!N16 -> 880924.33
A11: Adjusted Revenue | B11: INR Cr | C11: ='Revenue Schedule'!F27 -> 55903 | D11: ='Revenue Schedule'!N27 -> 722008.39
A12: Adjusted EBITDA | B12: INR Cr | C12: =IS!G48 -> 1189 | D12: =IS!O48 -> 54902.172
A13: Adjusted EBITDA margin (% of adj. revenue) | B13: % | C13: =IS!G49 -> 0.021268984 | D13: =IS!O49 -> 0.076040905
A14: Profit after tax (PAT) | B14: INR Cr | C14: =IS!G29 -> 366 | D14: =IS!O29 -> 29682.14
A15: Blinkit dark stores (EOY) | B15: # | C15: =Assumptions!G16 -> 2243 | D15: =Assumptions!O16 -> 13343
A17: INVESTMENT CONCLUSION
A18: DCF intrinsic value / share | B18: INR | C18: =DCF!B32 -> 96.751813
A19: SOTP value / share (FY2030E order value × peer EV/NOV, discounted at WACC; independent of the DCF) | B19: INR | C19: =SOTP!D17 -> 238.90427
A20: ="Probability-weighted expected value / share ("&TEXT(Scenarios!B39,"0%")&" bear / "&TEXT(Scenarios!C39,"0%")&" base / "&TEXT(Scenarios!D39,"0%")&" bull)" -> Probability-weighted expected value / share (30% bear / 45% base / 25% bull) | B20: INR | C20: =Scenarios!B41 -> 206.12669
A21: Current market price (24-Jul-2026) | B21: INR | C21: =Assumptions!B142 -> 281
A22: Expected return vs market price | B22: % | C22: =C20/C21-1 -> -0.26645307
A23: ="Probability-weighted IRR to a FY2030 exit vs the "&TEXT(Assumptions!B160,"0%")&" hurdle" -> Probability-weighted IRR to a FY2030 exit vs the 18% hurdle | B23: % | C23: =Dashboard!B28 -> -0.073362586
A24: RECOMMENDATION | C24: =Dashboard!B9 -> AVOID / SELL — negative expected return
A25: Full decision page on the Dashboard tab; the written case, kill criteria and open items are on Memo.
A26: ="Balance check (BS row 33) FY26A gap "&TEXT(BS!G33,"#,##0")&" Cr carried flat; max change in forecast imbalance "&TEXT(MAX(INDEX(ABS(BS!H34:O34),0)),"#,##0")&" Cr. Full integrity status on the Checks tab (open items counted in Checks!B5)." -> Balance check (BS row 33) FY26A gap 15 Cr carried flat; max change in forecast imbalance 0 Cr. Full integrity status on the Checks tab (open items counted in Checks!B5).
A28: TAB GUIDE
A29: Index — navigation, key outputs and the model flow diagram; start here
A30: Assumptions — every input, with the filing / call reference in the source column
A31: Revenue Schedule — NOV, adjusted revenue and Adjusted EBITDA for all five reporting segments
A32: IS / BS / CFS — statements, the bridge from Adjusted EBITDA to reported PAT, and the company's own cash and treasury bridge
A33: FA_Schedule / Lease_Schedule / WC_Schedule / Cost Schedule / ESOP Schedule / Other Income Schedule — supporting builds
A34: OpMetrics — operating KPIs, plus store-level unit economics and cohort payback for Blinkit (section D)
A35: Ratios — growth, margins, unit economics, ROIC against WACC, and valuation at the market price
A36: DCF — 8-year FCFF on a cash-rent basis, WACC build-up, terminal value and a ROIC-consistent terminal cross-check
A37: SOTP — FY2030E segment order value × peer-anchored EV/NOV multiples (Comparable peer table), discounted at WACC; DCF–SOTP gap shown openly
A38: Sensitivity — five tables flexing WACC, terminal growth, exit multiple and the operating drivers
A39: Scenarios — bear / base / bull on the four operating businesses, probability-weighted to an expected value
... A45: Beta Calc / ERP & Rf / Comparable / Data_Sources — reference tabs behind the cost of capital, the peer set and every sourced figure

Sheet Index
A1: ETERNAL LIMITED — MASTER FINANCIAL MODEL | F1: =Data_Sources!$D$15&" | "&Data_Sources!$E$15&" | "&Data_Sources!$F$15 -> Eternal Q4FY26 shareholders' letter | Annexure A & B (reconciliation to reported P&L) | https://b.zmtcdn.com/investor-relations/Eternal_Shareholders_Letter_Q4FY26_Results.pdf
A2: Food delivery (Zomato) · Quick commerce (Blinkit) · Going-out (District) · B2B supplies (Hyperpure) | NSE: ETERNAL | FY2025A–FY2026A actuals, FY2027E–FY2034E forecast
A4: KEY MODEL OUTPUTS | B4: Unit | C4: FY2026A | D4: FY2030E | E4: FY2034E
A5: B2C Net Order Value | B5: INR Cr | C5: ='Revenue Schedule'!F16 -> 95960 | D5: ='Revenue Schedule'!J16 -> 415920.28 | E5: ='Revenue Schedule'!N16 -> 880924.33
A6: Adjusted revenue | B6: INR Cr | C6: ='Revenue Schedule'!F27 -> 55903 | D6: ='Revenue Schedule'!J27 -> 328544.99 | E6: ='Revenue Schedule'!N27 -> 722008.39
A7: Adjusted EBITDA | B7: INR Cr | C7: =IS!G48 -> 1189 | D7: =IS!K48 -> 17501.415 | E7: =IS!O48 -> 54902.172
A8: Adjusted EBITDA margin (% of adj. revenue) | B8: % | C8: =IS!G49 -> 0.021268984 | D8: =IS!K49 -> 0.053269462 | E8: =IS!O49 -> 0.076040905
A9: Profit after tax | B9: INR Cr | C9: =IS!G29 -> 366 | D9: =IS!K29 -> -3202.4177 | E9: =IS!O29 -> 29682.14
A10: Blinkit dark stores (EOY) | B10: # | C10: =OpMetrics!G5 -> 2243 | D10: =OpMetrics!K5 -> 7243 | E10: =OpMetrics!O5 -> 13343
A11: Closing cash & treasury investments | B11: INR Cr | C11: =CFS!G32 -> 17972 | D11: =CFS!K32 -> -20244.157 | E11: =CFS!O32 -> 31344.97
A13: DCF intrinsic value / share | B13: INR | C13: =DCF!B32 -> 96.751813
A14: SOTP value / share (discounted to today) | B14: =SOTP!D17 -> 238.90427 | C14: =SOTP!D19 -> -0.14980687
A15: Scenario range (bear / base / bull) | B15: INR | C15: =Scenarios!B35 -> 66.2238 | D15: =Scenarios!C35 -> 178.67861 | E15: =Scenarios!D35 -> 423.4167
A16: Current market price | B16: INR | C16: =Assumptions!B142 -> 281
A17: Upside / (downside) on DCF | B17: % | C17: =DCF!B34 -> -0.6556875
A18: Probability-weighted expected value / share | B18: INR | C18: =Scenarios!B41 -> 206.12669
A19: Probability-weighted IRR to a FY2030 exit (hurdle 18%) | B19: % | C19: =Dashboard!B28 -> -0.073362586
A20: RECOMMENDATION | C20: =Dashboard!B9 -> AVOID / SELL — negative expected return
A22: SHEET NAVIGATION | C22: What it does | D22: Key contents
A23: ── FRONT MATTER
A24: Cover | B24: → | C24: Scope, definitions and the investment conclusion | D24: Model period, Adjusted EBITDA definition, headline valuation and recommendation, full tab guide
A25: ── FOUNDATION
A26: Assumptions | B26: → | C26: Every input in one place | D26: Segment drivers, corporate P&L drivers, capex, WACC, schedule drivers; source for each in column M
A27: Revenue Schedule | B27: → | C27: Bottom-up build of all five segments | D27: NOV, adjusted revenue, Adjusted EBITDA; Blinkit built from stores x NOV per store per day
A28: ── STATEMENTS & SCHEDULES
A29: IS | B29: → | C29: P&L and the bridge to reported PAT | D29: Segment roll-up, share-based payment and lease-rent bridge; tax from Tax_Schedule (loss carry-forward)
A30: FA_Schedule | B30: → | C30: Fixed assets and D&A | D30: PPE, right-of-use and intangible roll-forwards; total D&A; capex; capital-intensity analysis
A31: Lease_Schedule | B31: → | C31: Debt and lease liabilities | D31: Nil bank debt, lease liability roll-forward, finance costs, leverage, interest cover, rent analysis
A32: WC_Schedule | B32: → | C32: Working capital | D32: Receivable / inventory / payable days, balances, net WC, cash conversion cycle
A33: Cost Schedule | B33: → | C33: Reported expense waterfall | D33: COGS, delivery, employee, marketing, other; gross margin, contribution, operating leverage
A34: Other Income Schedule | B34: → | C34: Treasury and other income | D34: Yield applied to the opening treasury balance, so no circular reference
A35: ESOP Schedule | B35: → | C35: Share-based payment charge only | D35: Feeds the Adjusted EBITDA add-back on the IS and the dilution build
A36: BS | B36: → | C36: Condensed balance sheet | D36: Schedule-driven assets and liabilities; no balancing line; genuine balance check in row 33
A37: CFS | B37: → | C37: Cash / treasury bridge | D37: The company's own bridge format: EBITDA, treasury income, capex, working capital, closing cash
A38: ── ANALYSIS
A39: OpMetrics | B39: → | C39: Operating KPIs and unit economics | D39: Stores, NOV per store per day, orders, NAOV, transacting customers, take rates
A40: Ratios | B40: → | C40: Ratio dashboard | D40: Growth, margins, returns, capital intensity, valuation at the current market price
A41: ── VALUATION
A42: DCF | B42: → | C42: 8-year FCFF valuation | D42: WACC build-up, FCFF on a cash-rent basis, terminal value, intrinsic value per share
A43: Share Count & Dilution | B43: → | C43: Share count roll-forward and ESOP dilution
A44: SOTP | B44: → | C44: Sum-of-the-parts (independent) | D44: FY2030E order value × peer EV/NOV (Comparable rows 24–31); calibration to DCF switched off; gap to DCF at SOTP!D25
A45: Sensitivity | B45: → | C45: Five sensitivity tables | D45: WACC x terminal growth, exit multiple and operating-driver grids (see Sensitivity tab)
A46: Scenarios | B46: → | C46: Bear / base / bull | D46: Segment-level NOV CAGR and margin assumptions run to FY2030E
A47: ── INVESTMENT DECISION
A48: Dashboard | B48: → | C48: PM one-page decision sheet | D48: Recommendation, valuation range, IRR by scenario, margin of safety, position sizing, KPIs to monitor, catalysts, key risks
A49: Memo | B49: → | C49: Investment memo | D49: Thesis pillars, variant perception, what the market prices in, catalysts, kill criteria, moat, capital allocation, sizing
A50: Variant_View | B50: → | C50: Consensus vs my view | D50: Market-implied vs modelled on growth, margin, take rate, stores, ROIC, multiple and terminal growth; consensus column awaits broker data
A51: Reverse_DCF | B51: → | C51: What the market is pricing in | D51: Market-implied terminal growth, terminal EV/EBITDA and WACC, solved from today's price against the model's own cash flows
A52: Checks | B52: → | C52: Integrity and coherence control panel | D52: Balance-sheet and cash ties, error scan, valuation coherence, scenario discipline, register of unresolved assumptions
A53: ── REFERENCE
A54: Beta Calc | B54: → | C54: Systematic risk | D54: Beta input (placeholder, MANUAL – OPEN), Blume adjustment, peer betas (unsourced)
A55: ERP & Rf | B55: → | C55: WACC from first principles | D55: Rf, ERP, CAPM, capital structure, terminal capitalisation spread
A56: Comparable | B56: → | C56: Peer benchmarking and multiples table | D56: Swiggy, DoorDash, Delivery Hero, Meituan — latest full year; peer multiples table rows 24–31
A57: Data_Sources | B57: → | C57: Every historical input, cited | D57: Document, location, URL and target model cell for each figure
A59: MODEL FLOW
A60: Assumptions → Revenue Schedule → Cost Schedule (EBITDA is the waterfall output) → IS → Tax_Schedule → BS / CFS
A61: └─ FA_Schedule (D&A, capex) and Lease_Schedule (finance costs, cash rent) feed the IS
A62: └─ WC_Schedule feeds the CFS working-capital line and the balance sheet
A63: └─ Cost Schedule builds the reported expense waterfall; segment-margin EBITDA is kept as a comparison (IS row 59)
A64: └─ CFS → closing treasury → next year's other income (opening balance used, so no circular reference)
A65: └─ OpMetrics and Ratios read off the statements; Beta Calc → ERP & Rf → WACC feeds the DCF
A66: └─ DCF and SOTP value the business; Sensitivity and Scenarios stress it; Scenarios is probability-weighted to an expected value
A67: └─ Dashboard / Memo / Variant_View / Reverse_DCF turn the valuation into a decision; Checks gates the whole thing — read it first
A69: COLOUR CONVENTION
A70: Colour convention (applied literally across all calculation tabs): BLUE font = typed input / historical actual; BLACK = formula on the same sheet; GREEN = formula linking to another sheet; YELLOW fill = MANUAL – OPEN item or key judgement input awaiting a source.

Sheet Assumptions
A1: ASSUMPTIONS — all model inputs (blue = input, black = formula) | Q1: =Data_Sources!$D$26&" | "&Data_Sources!$E$26&" | "&Data_Sources!$F$26 -> Analyst estimate — not sourced from company disclosure | Judgement; sensitivity tested on the Sensitivity tab | n/a
A2: Item | B2: Unit | D2: FY2023A | E2: FY2024A | F2: FY2025A | G2: FY2026A | H2: FY2027E | I2: FY2028E | J2: FY2029E | K2: FY2030E | L2: FY2031E | M2: FY2032E | N2: FY2033E | O2: FY2034E | P2: Source / Rationale
D3: Actual | E3: Actual | F3: Actual | G3: Actual | H3: Forecast | I3: Forecast | J3: Forecast | K3: Forecast | L3: Forecast | M3: Forecast | N3: Forecast | O3: Forecast
A4: A. OPERATING ASSUMPTIONS — segment drivers, reported cost waterfall and corporate P&L
A6: FOOD DELIVERY (ZOMATO) | Q6: =Data_Sources!$D$20&" | "&Data_Sources!$E$20&" | "&Data_Sources!$F$20 -> Eternal Q4FY26 shareholders' letter | Q1 and Q7 of the Q&A | https://b.zmtcdn.com/investor-relations/Eternal_Shareholders_Letter_Q4FY26_Results.pdf
B7: % | P7: Mgmt: NOV growth to 18.8% YoY in Q4FY26, 'inching closer to our long-term expectation of 20%+' (Q4FY26 letter, Q1/Q7). Modelled at 20% in FY27& FY28 then fading to 13% as base because IBEF says CAGR till FY34 is 17-18% , and new players emerging in business like flipkart,ondc ,others.Mgt :margins have remained stable even as the order mix has shifted towards lower-value orders. Ultimately, we are optimizing for absolute Adjusted EBITDA (and not %), and the current tactics are working well to drive that ,future growth is the reduction of the minimum order value (MOV) for free delivery to INR 99 for Gold members(Q3,Q4FY25-26),still modelled at near inflation. | Q7: Mgmt: NOV growth to 18.8% YoY in Q4FY26, 'inching closer to our long-term expectation of 20%+' (Q4FY26 letter, Q1/Q7). Fading to 15% by FY34 because IBEF puts the industry CAGR to FY34 at 17-18% and new entrants (Flipkart, ONDC) are emerging. RETAINED AS A BENCHMARK ONLY: the build is driven by orders x NAOV, which implies c.18.4%. The gap between this row and row 7 is the gap between management's ambition and what the model actually assumes.
A8: Orders | B8: CR. | G8: ='Revenue Schedule'!F45 -> 97.93 | H8: =ROUND((G8*(1+H9)),1) -> 112.6 | I8: =ROUND((H8*(1+I9)),1) -> 129.5 | J8: =ROUND(I8*(1+J9),1) -> 148.9 | K8: =ROUND(J8*(1+K9),1) -> 171.2 | L8: =ROUND(K8*(1+L9),1) -> 195.2 | M8: =ROUND(L8*(1+M9),1) -> 222.5 | N8: =ROUND(M8*(1+N9),1) -> 253.7 | O8: =ROUND(N8*(1+O9),1) -> 289.2
A9: Orders growth | B9: % | G9: =IFERROR(G8/F8-1,"") | H9: 0.15 | I9: 0.15 | J9: 0.15 | K9: 0.15 | L9: 0.14 | M9: 0.14 | N9: 0.14 | O9: 0.14
A11: Net average order value (NAOV) | B11: INR | E11: ='Revenue Schedule'!D48 -> 364.81678 | F11: ='Revenue Schedule'!E48 -> 385.3424 | G11: ='Revenue Schedule'!F48 -> 387.96079 | H11: =ROUND((G11*(1+H12)),1) -> 399.6 | I11: =ROUND((H11*(1+I12)),1) -> 411.6 | J11: =ROUND((I11*(1+J12)),1) -> 423.9 | K11: =ROUND((J11*(1+K12)),1) -> 436.6 | L11: =ROUND((K11*(1+L12)),1) -> 449.7 | M11: =ROUND((L11*(1+M12)),1) -> 463.2 | N11: =ROUND((M11*(1+N12)),1) -> 477.1 | O11: =ROUND((N11*(1+O12)),1) -> 491.4
A12: Net AOV growth | B12: % | E12: =IFERROR(E11/D11-1,"") | F12: =IFERROR(F11/E11-1,"") -> 0.056262817 | G12: =IFERROR(G11/F11-1,"") -> 0.0067949616 | H12: 0.03 | I12: 0.03 | J12: 0.03 | K12: 0.03 | L12: 0.03 | M12: 0.03 | N12: 0.03 | O12: 0.03
A13: Adjusted revenue as % of NOV (take rate) | B13: % | G13: ='Revenue Schedule'!F52 -> 0.30789882 | H13: 0.315 | I13: 0.32 | J13: 0.325 | K13: 0.33 | L13: 0.33 | M13: 0.33 | N13: 0.33 | O13: 0.33 | P13: FY26A take rate 30.8% (adj. revenue 11,698 / NOV 37,993). Rising slowly on platform fee + ad monetisation, capped at 33% — mgmt says 'revenue per order and cost efficiencies have kept pace' (Q4FY26 letter, Q7).
A15: QUICK COMMERCE (BLINKIT) | Q15: =Data_Sources!$D$19&" | "&Data_Sources!$E$19&" | "&Data_Sources!$F$19 -> Eternal Q4FY26 shareholders' letter | Q2, Q3 and Q6 of the Q&A | https://b.zmtcdn.com/investor-relations/Eternal_Shareholders_Letter_Q4FY26_Results.pdf
A16: Dark stores (EOY) | B16: # | F16: ='Revenue Schedule'!E60 -> 1301 | G16: ='Revenue Schedule'!F60 -> 2243 | H16: =G16+H18 -> 3343 | I16: =H16+I18 -> 4543 | J16: =I16+J18 -> 5843 | K16: =J16+K18 -> 7243 | L16: =K16+L18 -> 8693 | M16: =L16+M18 -> 10193 | N16: =M16+N18 -> 11743 | O16: =N16+O18 -> 13343 | P16: Management is firmly on track to reach 3,000 stores by March 2027. they may aim for 3,500 to 4,000 stores by March 2027 to sustain Net Order Value (NOV) growth above 100% year-on-year.
A17: % growth | G17: =G16/F16-1 -> 0.72405842 | H17: =H16/G16-1 -> 0.49041462 | I17: =I16/H16-1 -> 0.35895902 | J17: =J16/I16-1 -> 0.28615452 | K17: =K16/J16-1 -> 0.23960294 | L17: =L16/K16-1 -> 0.20019329 | M17: =M16/L16-1 -> 0.17255263 | N17: =N16/M16-1 -> 0.15206514 | O17: =O16/N16-1 -> 0.13625138
A18: Net new dark stores added | B18: # | E18: =E16-D16 -> 0 | G18: =G16-F16 -> 942 | H18: 1100 | I18: 1200 | J18: 1300 | K18: 1400 | L18: 1450 | M18: 1500 | N18: 1550 | O18: 1600
A19: Blinkit throughput ladder selector (1 = Ladder A documented, 2 = Ladder B as-received) | B19: 1
A20: NOV per day, per store — OPERATIVE (selected ladder) | B20: INR '000 | E20: ='Revenue Schedule'!D66 -> 672 | F20: ='Revenue Schedule'!E66 -> 766 | G20: ='Revenue Schedule'!F66 -> 756 | H20: =CHOOSE($B$19,H22,H23) -> 1200 | I20: =CHOOSE($B$19,I22,I23) -> 1200 | J20: =CHOOSE($B$19,J22,J23) -> 1250 | K20: =CHOOSE($B$19,K22,K23) -> 1300 | L20: =CHOOSE($B$19,L22,L23) -> 1350 | M20: =CHOOSE($B$19,M22,M23) -> 1400 | N20: =CHOOSE($B$19,N22,N23) -> 1450 | O20: =CHOOSE($B$19,O22,O23) -> 1450 | P20: ="THROUGHPUT (price-setting). SOURCE: FY24A–FY26A NOV/store/day from the Eternal KPI databook (Data_Sources row 39): "&TEXT(E20,"#,##0")&" / "&TEXT(F20,"#,##0")&" / "&TEXT(G20,"#,##0")&" (INR '000). The 'INR 11 lakh' management figure had no document, date or page and is removed. FY26A START: "&TEXT(G20,"#,##0")&". BRIDGE: selector B19 = "&B19&"; FY27E "&TEXT(H20,"#,##0")&" is "&TEXT(H20/G20-1,"+0%")&" on FY26A while average stores grow "&TEXT('Revenue Schedule'!G64,"0%")&"; FY34E "&TEXT(O20,"#,##0")&". No disclosed bridge supports the FY27E step — MANUAL – OPEN. WRONG IF: new stores ramp slowly (OpMetrics maturity curve) or throughput falls as the network densifies, as it did in FY26A ("&TEXT(G21,"0.0%")&")." -> THROUGHPUT (price-setting). SOURCE: FY24A–FY26A NOV/store/day from the Eternal KPI databook (Data_Sources row 39): 672 / 766 / 756 (INR '000). The 'INR 11 lakh' management figure had no document, date or page and is removed. FY26A START: 756. BRIDGE: selector B19 = 1; FY27E 1,200 is +59% on FY26A while average stores grow 58%; FY34E 1,450. No disclosed bridge supports the FY27E step — MANUAL – OPEN. WRONG IF: new stores ramp slowly (OpMetrics maturity curve) or throughput falls as the network densifies, as it did in FY26A (-1.3%).
A21: % change | F21: =F20/E20-1 -> 0.13988095 | G21: =G20/F20-1 -> -0.01305483 | H21: =H20/G20-1 -> 0.58730159 | I21: =I20/H20-1 -> 0 | J21: =J20/I20-1 -> 0.041666667 | K21: =K20/J20-1 -> 0.04 | L21: =L20/K20-1 -> 0.038461538 | M21: =M20/L20-1 -> 0.037037037 | ... O21: =O20/N20-1 -> 0
A22: Ladder A — documented ladder (rationale in P20) | B22: INR '000 | H22: 1200 | I22: 1200 | J22: 1250 | K22: 1300 | L22: 1350 | M22: 1400 | N22: 1450 | O22: 1450
A23: Ladder B — ladder typed in Revenue Schedule H66:N66 as received | B23: INR '000 | H23: 1200 | I23: 1250 | J23: 1300 | K23: 1350 | L23: 1400 | M23: 1450 | N23: 1500 | O23: 1550
A24: Store ownership mix — COCO (company-operated) vs FOCO (local-partner operated; Eternal funds capex and holds the lease on both) | P24: Disclosure layer only. Eternal funds the capex (recognised as PPE), holds the Ind AS 116 right-of-use asset and lease liability, and pays the rent on BOTH formats; the local partner supplies day-to-day operations. Because no driver differs between the two, this block deliberately has no effect on revenue, EBITDA, capex, leases or valuation . it exists to show how much of the network is partner-run.
A25: FOCO share of the installed dark store base (FY2026A seed) | B25: % | G25: 0.5 | P25: Q2 FY23 shareholders' letter (10 Nov 2022) disclosed that almost half the dark store network was run by local partners, reiterated on later calls as roughly 50/50. Applied to the FY2026A closing base of 2,243 stores.
A26: FOCO share of net new dark stores | B26: % | D26: 0 | E26: 0 | F26: 0 | G26: 0 | H26: 0.5 | I26: 0.5 | J26: 0.5 | K26: 0.5 | L26: 0.5 | M26: 0.5 | N26: 0.5 | O26: 0.5 | P26: Management's stated long-term attempt and priority is that every new store is eventually run by a local partner, adding more trustworthy franchisees rather than expanding the company-run estate. Modelled as a ramp rather than a step: the 50% start is what the realised data implies, since partner share of the base held near half from FY23 to FY26 while the base grew several-fold, which is only possible if net new adds were already running near 50% partner-run.
A27: Net new FOCO stores added | B27: # | D27: =ROUND(D18*D26,0) -> 0 | E27: =ROUND(E18*E26,0) -> 0 | F27: =ROUND(F18*F26,0) -> 0 | G27: =ROUND(G18*G26,0) -> 0 | H27: =ROUND(H18*H26,0) -> 550 | I27: =ROUND(I18*I26,0) -> 600 | J27: =ROUND(J18*J26,0) -> 650 | K27: =ROUND(K18*K26,0) -> 700 | ... O27: =ROUND(O18*O26,0) -> 800 | P27: Net new stores x the partner share above. Rounded to whole stores.
A28: Net new COCO stores added | B28: # | D28: =D18-D27 -> 0 | E28: =E18-E27 -> 0 | F28: =F18-F27 -> 0 | G28: =G18-G27 -> 942 | H28: =H18-H27 -> 550 | I28: =I18-I27 -> 600 | J28: =J18-J27 -> 650 | K28: =K18-K27 -> 700 | ... O28: =O18-O27 -> 800 | P28: ="Residual of net new stores after partner adds: "&TEXT(H28,"#,##0")&" in FY2027E and "&TEXT(O28,"#,##0")&" in FY2034E at a "&TEXT(O26,"0%")&" FOCO share of adds (row 26)." -> Residual of net new stores after partner adds: 550 in FY2027E and 800 in FY2034E at a 50% FOCO share of adds (row 26).
A29: FOCO dark stores (EOY) | B29: # | D29: 0 | E29: =D29+E27 -> 0 | F29: =E29+F27 -> 0 | G29: =ROUND(G16*G25,0) -> 1122 | H29: =G29+H27 -> 1672 | I29: =H29+I27 -> 2272 | J29: =I29+J27 -> 2922 | K29: =J29+K27 -> 3622 | L29: =K29+L27 -> 4347 | M29: =L29+M27 -> 5097 | N29: =M29+N27 -> 5872 | O29: =N29+O27 -> 6672 | P29: ="Prior year closing plus net new partner stores. Reaches "&TEXT(O29,"#,##0")&" by FY2034E, or "&TEXT(O29/O16,"0%")&" of the network." -> Prior year closing plus net new partner stores. Reaches 6,672 by FY2034E, or 50% of the network.
A30: COCO dark stores (EOY) | B30: # | D30: =D16-D29 -> 0 | E30: =E16-E29 -> 0 | F30: =F16-F29 -> 1301 | G30: =G16-G29 -> 1121 | H30: =H16-H29 -> 1671 | I30: =I16-I29 -> 2271 | J30: =J16-J29 -> 2921 | K30: =K16-K29 -> 3621 | ... O30: =O16-O29 -> 6671 | P30: Taken as the residual against total dark stores on row 17 rather than accumulated independently, so the split can never drift away from the store count that actually drives revenue. Peaks near 2,966 and plateaus.
A31: Check: COCO + FOCO less total dark stores (must be nil) | H31: =H30-G30-H28 -> 0 | I31: =I30-H30-I28 -> 0 | J31: =J30-I30-J28 -> 0 | K31: =K30-J30-K28 -> 0 | L31: =L30-K30-L28 -> 0 | M31: =M30-L30-M28 -> 0 | N31: =N30-M30-N28 -> 0 | O31: =O30-N30-O28 -> 0 | P31: ="Integrity check: closing COCO must equal prior year plus net new COCO. Reported on the Checks tab (COCO + FOCO tie)." -> Integrity check: closing COCO must equal prior year plus net new COCO. Reported on the Checks tab (COCO + FOCO tie).
A33: Adjusted revenue as % of NOV (1P model) | B33: % | D33: ='Revenue Schedule'!C68/'Revenue Schedule'!C56 -> 0.14165202 | E33: ='Revenue Schedule'!D68/'Revenue Schedule'!D56 -> 0.21917547 | F33: ='Revenue Schedule'!E68/'Revenue Schedule'!E56 -> 0.23271199 | G33: ='Revenue Schedule'!F68/'Revenue Schedule'!F56 -> 0.77785785 | H33: 0.92 | I33: 0.92 | J33: 0.92 | K33: 0.92 | L33: 0.92 | M33: 0.92 | N33: 0.92 | O33: 0.92 | P33: Q4FY26 run-rate: revenue 13,232 / NOV 14,386 = 92% under the full inventory-led (1P) model adopted from Q1FY26. mgt expects no more increase in overall
Q34: =Data_Sources!$D$21&" | "&Data_Sources!$E$21&" | "&Data_Sources!$F$21 -> Eternal Q4FY26 shareholders' letter | Q9 of the Q&A | https://b.zmtcdn.com/investor-relations/Eternal_Shareholders_Letter_Q4FY26_Results.pdf
A35: GOING-OUT (DISTRICT)
A36: NOV growth | B36: % | D36: ='Revenue Schedule'!C73 -> 0 | E36: ='Revenue Schedule'!D73 -> 0 | F36: ='Revenue Schedule'!E73 -> 1.0524031 | G36: ='Revenue Schedule'!F73 -> 0.42000302 | H36: 0.4 | I36: 0.36 | J36: 0.32 | K36: 0.3 | L36: 0.25 | M36: 0.25 | N36: 0.25 | O36: 0.25 | P36: Going-out NOV grew 42% YoY in FY26 (mgmt asks investors to read the annual number, Q4FY26 letter Q9). Path sized to mgmt's $3bn NOV by FY30 guidance (Q9) and the analyst has taken flat 25% for beyond, as they will plan to go for international events too, if they are sizing up in the big and go through after bookmyshow as the competitor is that range.
A37: Revenue as % of NOV (take rate ) | B37: % | E37: ='Revenue Schedule'!D75/'Revenue Schedule'!D72 -> 0.079689922 | F37: ='Revenue Schedule'!E75/'Revenue Schedule'!E72 -> 0.11285693 | G37: ='Revenue Schedule'!F75/'Revenue Schedule'!F72 -> 0.10352165 | H37: 0.105 | I37: 0.11 | J37: 0.115 | K37: 0.12 | L37: 0.12 | M37: 0.12 | N37: 0.12 | O37: 0.12 | P37: FY26A: revenue 973 / NOV 9,399 = 10.4%. Mix shift toward higher-take live events and movies lifts it modestly.
Q38: =Data_Sources!$D$22&" | "&Data_Sources!$E$22&" | "&Data_Sources!$F$22 -> Eternal Q3FY26 shareholders' letter | Q&A on the Hyperpure business | https://b.zmtcdn.com/investor-relations/Eternal_Shareholders_Letter_Q3FY26_Results.pdf
A39: B2B SUPPLIES (HYPERPURE)
A40: Restaurant business revenue | B40: INR Cr | E40: 1970 | F40: 2699 | G40: 3722 | P40: Historical restaurant-business revenue (FY24A–FY26A) only. The duplicate forecast that sat in H40:O40 (ending ₹54,929 Cr) was deleted; the single operative Hyperpure forecast is Revenue Schedule row 83, driven by row 41 growth (each year reads its own column).
F41: =F40/E40-1 -> 0.37005076 | G41: =G40/F40-1 -> 0.37902927 | H41: 0.4 | I41: 0.4 | J41: 0.4 | K41: 0.4 | L41: 0.4 | M41: 0.4 | N41: 0.4 | O41: 0.4 | P41: ="Hyperpure restaurant revenue growth "&TEXT(H41,"0%")&" flat FY27E–FY34E. Guidance (Data_Sources row 22) covers ~3 years only; extending 40% for eight years has no basis — MANUAL – OPEN. FY26A actual "&TEXT(G41,"0.0%")&"." -> Hyperpure restaurant revenue growth 40% flat FY27E–FY34E. Guidance (Data_Sources row 22) covers ~3 years only; extending 40% for eight years has no basis — MANUAL – OPEN. FY26A actual 37.9%.
A42: Hyperpure non-restaurant revenue (B2B supplies to non-restaurant customers) | B42: INR Cr | H42: 0 | I42: 0 | J42: 0 | K42: 0 | L42: 0 | M42: 0 | N42: 0 | O42: 0 | P42: MANUAL – OPEN. Held at nil from FY27E on the stated rationale that non-restaurant B2B supply (largely to Blinkit) ends with the 1P transition. No locatable source in the workbook; FY26A was ₹1,644 Cr (Revenue Schedule!F84). Vipul to supply the disclosure.
A43: OTHERS (incl. Bistro)
A44: Revenue growth | B44: % | E44: ='Revenue Schedule'!D87/'Revenue Schedule'!C87-1 -> -0.90598291 | F44: ='Revenue Schedule'!E87/'Revenue Schedule'!D87-1 -> 0.36363636 | G44: ='Revenue Schedule'!F87/'Revenue Schedule'!E87-1 -> 1.9 | H44: 0.4 | I44: 0.35 | J44: 0.3 | K44: 0.25 | L44: 0.2 | M44: 0.15 | N44: 0.12 | O44: 0.1 | P44: Bistro and other early-stage bets small base (FY26A adj. revenue INR 87 Cr).
A48: EBITDA (Adjusted IN P&L ) | P48: Management Adjusted EBITDA guidance,of US$1bn annual Adjusted EBITDA, targeted around FY29, with management explicitly prioritising absolute Adjusted EBITDA rupees over percentage margin and reinvesting incremental gains into growth where high-quality opportunities exist. Forecast years are therefore held AT the guided corridors rather than extrapolated above them.
A49: Adjusted EBITDA margin (% of NOV) Food Delivery | B49: % | G49: =IS!G43/'Revenue Schedule'!F42 -> 0.053088727 | H49: 0.056 | I49: 0.058 | J49: 0.06 | K49: 0.06 | L49: 0.06 | M49: 0.06 | N49: 0.06 | O49: 0.06 | P49: ="Food delivery margin. SOURCE: Data_Sources row 20 (Q4FY26 letter Q1/Q7): long-term 5–6% of NOV. FY26A START "&TEXT(G49,"0.0%")&". BRIDGE: "&TEXT(H49,"0.0%")&" FY27E to "&TEXT(O49,"0.0%")&" cap. The Q1FY27 5.6% print was 'supplied by user' and is not logged — MANUAL – OPEN." -> Food delivery margin. SOURCE: Data_Sources row 20 (Q4FY26 letter Q1/Q7): long-term 5–6% of NOV. FY26A START 5.3%. BRIDGE: 5.6% FY27E to 6.0% cap. The Q1FY27 5.6% print was 'supplied by user' and is not logged — MANUAL – OPEN.
A50: Adjusted EBITDA margin (% of NOV) Quick commerce | B50: % | D50: =IS!D44/'Revenue Schedule'!C56 -> -0.098769772 | E50: =IS!E44/'Revenue Schedule'!D56 -> -0.036560983 | F50: =IS!F44/'Revenue Schedule'!E56 -> -0.013052613 | G50: =IS!G44/'Revenue Schedule'!F56 -> -0.0057033438 | H50: =H56 -> 0.005 | I50: =I56 -> 0.015 | J50: =J56 -> 0.025 | K50: =K56 -> 0.035 | L50: =L56 -> 0.045 | M50: =M56 -> 0.05 | N50: =N56 -> 0.055 | O50: =O56 -> 0.06 | P50: ="Blinkit margin (from row 56). SOURCE: Data_Sources row 19: 5–6% steady state of NOV. FY26A START "&TEXT(G50,"0.0%")&". BRIDGE: "&TEXT(H50,"0.0%")&" FY27E to "&TEXT(O50,"0.0%")&" FY34E. Q1FY27 0.6% print not logged — MANUAL – OPEN." -> Blinkit margin (from row 56). SOURCE: Data_Sources row 19: 5–6% steady state of NOV. FY26A START -0.6%. BRIDGE: 0.5% FY27E to 6.0% FY34E. Q1FY27 0.6% print not logged — MANUAL – OPEN.
A51: Adjusted EBITDA margin (% of NOV) Going out | B51: % | E51: =IS!E45/'Revenue Schedule'!D72 -> -0.0018604651 | F51: =IS!F45/'Revenue Schedule'!E72 -> -0.0057410485 | G51: =IS!G45/'Revenue Schedule'!F72 -> -0.033939781 | H51: -0.0225 | I51: -0.01 | J51: 0.025 | K51: 0.05 | L51: 0.05 | M51: 0.05 | N51: 0.05 | O51: 0.05 | P51: ="District margin. SOURCE: Data_Sources row 21 (Q4FY26 letter, Q9): USD 3bn NOV and USD 150mn Adjusted EBITDA by FY30 = 5% of NOV. FY26A START: "&TEXT(G51,"0.0%")&". BRIDGE: analyst glide "&TEXT(H51,"0.0%")&" (FY27E) to "&TEXT(K51,"0.0%")&" (FY30E), "&TEXT(O51,"0.0%")&" FY34E. WRONG IF: live-events mix keeps losses wider for longer." -> District margin. SOURCE: Data_Sources row 21 (Q4FY26 letter, Q9): USD 3bn NOV and USD 150mn Adjusted EBITDA by FY30 = 5% of NOV. FY26A START: -3.4%. BRIDGE: analyst glide -2.3% (FY27E) to 5.0% (FY30E), 5.0% FY34E. WRONG IF: live-events mix keeps losses wider for longer.
A52: Adjusted EBITDA margin (% of revenue) Hyperpure | B52: % | D52: =IS!D46/'Revenue Schedule'!C80 -> -0.12881806 | E52: =IS!E46/'Revenue Schedule'!D80 -> -0.039722573 | F52: =IS!F46/'Revenue Schedule'!E80 -> -0.013557134 | G52: =IS!G46/'Revenue Schedule'!F80 -> -0.0031680954 | H52: 0.015 | I52: 0.03 | J52: 0.045 | K52: 0.05 | L52: 0.05 | M52: 0.05 | N52: 0.05 | O52: 0.05 | P52: ="Hyperpure margin. SOURCE: Data_Sources row 22 (Q3FY26 letter): 4–5% at ~USD 1bn revenue in ~3 years. FY26A START "&TEXT(G52,"0.0%")&". BRIDGE: "&TEXT(H52,"0.0%")&" FY27E to "&TEXT(O52,"0.0%")&". Q1FY27 commentary not logged — MANUAL – OPEN." -> Hyperpure margin. SOURCE: Data_Sources row 22 (Q3FY26 letter): 4–5% at ~USD 1bn revenue in ~3 years. FY26A START -0.3%. BRIDGE: 1.5% FY27E to 5.0%. Q1FY27 commentary not logged — MANUAL – OPEN.
A53: Adjusted EBITDA (others) | B53: INR Cr | D53: =IS!D47 -> -17 | E53: =IS!E47 -> -24 | F53: =IS!F47 -> -12 | G53: =IS!G47 -> -215 | H53: -380 | I53: -300 | J53: -200 | K53: -100 | L53: -50 | M53: 0 | N53: 25 | O53: 50 | P53: ="Others Adj. EBITDA. FY26A START "&TEXT(G53,"#,##0")&" Cr (residual of consolidated vs segment). FY27E "&TEXT(H53,"#,##0")&" annualises a Q1FY27 loss that is not logged in Data_Sources — MANUAL – OPEN; tapers to "&TEXT(O53,"#,##0")&" by FY34E (analyst)." -> Others Adj. EBITDA. FY26A START -215 Cr (residual of consolidated vs segment). FY27E -380 annualises a Q1FY27 loss that is not logged in Data_Sources — MANUAL – OPEN; tapers to 50 by FY34E (analyst).
A55: PARTNER ECONOMICS UNDER FOCO — block deleted (rows 57–65): it netted to nil by construction (old H62 = H61) and its commission/payout inputs had no source. Row 56 is the margin input.
A56: Blinkit Adjusted EBITDA margin input (% of NOV) — feeds row 50 | B56: % | H56: 0.005 | I56: 0.015 | J56: 0.025 | K56: 0.035 | L56: 0.045 | M56: 0.05 | N56: 0.055 | O56: 0.06 | P56: The former margin input ladder, now reframed as the margin a fully company-operated network would earn. Sourced to management guidance of 5-6% steady state on NOV.
A67: Memo: Blinkit gross profit FY26A (input for G71) | B67: INR Cr | G67: 12706 | P67: MANUAL – OPEN: value was buried in the old G71 formula (=12706/…); source document not recorded. Vipul to cite (Q4FY26 letter, Blinkit segment table).
A68: COST STRUCTURE DRIVERS (reported P&L waterfall) | P68: management only component guidance for Blinkit and Hyperpure plus a direction of travel. Source: (Q1FY27 results / earnings call), Overall direction: absolute COGS grows with scale, but COGS as a percentage of revenue is expected to be optimised through supply-chain automation, better sourcing via Hyperpure, and a shift toward higher-margin categories. External cost pressures noted by management: select raw materials are seeing inflation but it has not yet hit production volumes or brand supply; fuel price rises hit last-mile delivery cost rather than COGS, and management believes it can pass on drastic hikes to consumers as it did with GST increases.
A69: Quick commerce gross profit (% of NOV) — mgmt "effective take rate" | B69: % | H69: 0.275 | I69: 0.285 | J69: 0.29 | K69: 0.295 | L69: 0.3 | M69: 0.3 | N69: 0.305 | O69: 0.305 | P69: ="Blinkit gross profit % of NOV. Q1FY27 27.5% and the +1pp 1P accretion are cited from Q1FY27 commentary that is not logged in Data_Sources — MANUAL – OPEN. Path "&TEXT(H69,"0.0%")&" FY27E to "&TEXT(O69,"0.0%")&" FY34E feeds row 71." -> Blinkit gross profit % of NOV. Q1FY27 27.5% and the +1pp 1P accretion are cited from Q1FY27 commentary that is not logged in Data_Sources — MANUAL – OPEN. Path 27.5% FY27E to 30.5% FY34E feeds row 71.
A70: of which: inventory losses (% of NOV) | B70: % | H70: 0.018 | I70: 0.017 | J70: 0.016 | K70: 0.015 | L70: 0.014 | M70: 0.013 | N70: 0.013 | O70: 0.012 | P70: Management disclosed inventory losses (expiry, shrinkage, damage, transit loss, pilferage) at approximately 1.8% of NOV, to be optimised through better replenishment planning and supply-chain efficiency. This records that guidance and its assumed taper to 1.2% by FY34E. It is deliberately NOT wired into the COGS build because inventory losses are already inside the gross profit % linking both would double-count the cost. Kept visible so the assumption can be challenged on its own.
A71: Quick commerce gross margin (% of consolidated segment revenue) | B71: % | D71: 1 | E71: 1 | F71: 1 | G71: =G67/'Revenue Schedule'!F68 -> 0.33632441 | H71: =IFERROR(H69/H33,"n.a.") -> 0.29891304 | I71: =IFERROR(I69/I33,"n.a.") -> 0.30978261 | J71: =IFERROR(J69/J33,"n.a.") -> 0.31521739 | K71: =IFERROR(K69/K33,"n.a.") -> 0.32065217 | L71: =IFERROR(L69/L33,"n.a.") -> 0.32608696 | M71: =IFERROR(M69/M33,"n.a.") -> 0.32608696 | N71: =IFERROR(N69/N33,"n.a.") -> 0.33152174 | O71: =IFERROR(O69/O33,"n.a.") -> 0.33152174 | P71: ="FY26A = Blinkit gross profit (G67) / Blinkit revenue. Forecast DERIVED: row 69 (gross profit % of NOV) ÷ row 33 (revenue as % of NOV): FY27E "&TEXT(H71,"0.0%")&". Feeds Cost Schedule row 6." -> FY26A = Blinkit gross profit (G67) / Blinkit revenue. Forecast DERIVED: row 69 (gross profit % of NOV) ÷ row 33 (revenue as % of NOV): FY27E 29.9%. Feeds Cost Schedule row 6.
A72: Hyperpure gross margin (% of revenue) | B72: % | D72: =1-('Cost Schedule'!D6-'Revenue Schedule'!C68*(1-D71))/'Revenue Schedule'!C80 -> 0.073705179 | E72: =1-('Cost Schedule'!E6-'Revenue Schedule'!D68*(1-E71))/'Revenue Schedule'!D80 -> 0.091424968 | F72: =1-('Cost Schedule'!F6-'Revenue Schedule'!E68*(1-F71))/'Revenue Schedule'!E80 -> 0.1018399 | G72: =1-('Cost Schedule'!G6-'Revenue Schedule'!F68*(1-G71))/'Revenue Schedule'!F80 -> 0.050689527 | H72: 0.12 | I72: 0.125 | J72: 0.13 | K72: 0.13 | L72: 0.135 | M72: 0.135 | N72: 0.14 | O72: 0.14 | P72: B2B food distribution gross margins run low double digits; company targets 4-5% Adjusted EBITDA margin at $1bn scale. Q1FY27 guidance adds only DIRECTION, no numbers: margin gains attributed to better sourcing and supply-chain efficiency (segment Adjusted EBITDA margin improved from -4% FY24 to -1% FY25), to Hyperpure acting as the backward-integrated sourcing engine for Blinkit fresh produce (better rates, lower wastage), and to own processing plants for sauces, spreads and pre-cut perishables improving price realisation. LEFT UNCHANGED at 12.0% rising to 14.0%. This opens at 12.0% against an FY26A actual of 5.1%, a one-year doubling with no stated cause. The 5.1% is itself only a derived residual (the algebraic inverse of the reported COGS build once quick commerce gross margin is fixed), so it may be distorted rather than real. Not overridden on judgement because the low-double-digit industry rationale above is a sourced view and the new guidance does not quantify this line.
A73: Delivery & related charges (% ofrevenue from operations) | B73: % | D73: ='Cost Schedule'!D25 -> 0.35838395 | E73: ='Cost Schedule'!E25 -> 0.32317979 | F73: ='Cost Schedule'!F25 -> 0.28296201 | G73: ='Cost Schedule'!G25 -> 0.16674638 | H73: 0.16379582 | I73: 0.16062985 | J73: 0.15752498 | K73: 0.15445054 | L73: 0.15140517 | M73: 0.14836867 | N73: 0.14636498 | O73: 0.14334058 | P73: FY26A INR 9,065 Cr = 16.2% of net Revenue. Guidance of mgt Improves slowly with batching, denser stores and shorter trip distances.
A74: Employee benefits expense (% of revenue from operations) | B74: % | D74: ='Cost Schedule'!D26 -> 0.20695013 | E74: ='Cost Schedule'!E26 -> 0.13694898 | F74: ='Cost Schedule'!F26 -> 0.12636467 | G74: ='Cost Schedule'!G26 -> 0.065043043 | H74: 0.059375986 | I74: 0.055248483 | J74: 0.051144473 | K74: 0.048074009 | L74: 0.046035357 | M74: 0.043998985 | N74: 0.042988316 | O74: 0.041978312 | P74: FY26A INR 3,536 Cr = 6.3% of Net Revenue (includes INR 819 Cr of share-based payment). Mgt provides guidance than trends will in downwards but in long term
A75: Advertisement & sales promotion (% of revenue from operations) | B75: % | D75: ='Cost Schedule'!D27 -> 0.17332957 | E75: ='Cost Schedule'!E27 -> 0.11821034 | F75: ='Cost Schedule'!F27 -> 0.097416391 | G75: ='Cost Schedule'!G27 -> 0.061621661 | H75: 0.058352262 | I75: 0.055248483 | J75: 0.051144473 | K75: 0.04909686 | L75: 0.047058365 | M75: 0.045022217 | N75: 0.044011848 | O75: 0.043002173 | P75: FY26A INR 3,350 Cr = 6.0% of Net Revenue. Competitive intensity in quick commerce keeps this elevated near term.Mgt guidance that will continue to advertisement aggressively like is on , as it is a competiton in the market.
A76: Customer delivery charges (% of B2C NOV) | B76: % | D76: =IFERROR('Revenue Schedule'!C37,"") -> 0.057252315 | E76: =IFERROR('Revenue Schedule'!D37,"") -> 0.034727952 | F76: =IFERROR('Revenue Schedule'!E37,"") -> 0.021890966 | G76: =IFERROR('Revenue Schedule'!F37,"") -> 0.016037932 | H76: 0.016 | I76: 0.016 | J76: 0.016 | K76: 0.016 | L76: 0.016 | M76: 0.016 | N76: 0.016 | O76: 0.016 | P76: 40+ partnerships with rental agencies, battery swapping companies, and logistics providers,efforts led to a 10.5% reduction in last-mile delivery emissions ,lowered the minimum order value (MOV) for free delivery,in Q2 FY26,In early FY27, management dropped delivery charges in specific markets to counter competitors offering "freebies" and zero delivery fees.
A77: Other expenses (% of revenue from operations) | B77: % | D77: ='Cost Schedule'!D28 -> 0.23520271 | E77: ='Cost Schedule'!E28 -> 0.18028727 | F77: ='Cost Schedule'!F28 -> 0.18687942 | G77: ='Cost Schedule'!G28 -> 0.12946067 | H77: =MAX($B$93,G77-$B$92) -> 0.11946067 | I77: =MAX($B$93,H77-$B$92) -> 0.10946067 | J77: =MAX($B$93,I77-$B$92) -> 0.099460673 | K77: =MAX($B$93,J77-$B$92) -> 0.089460673 | L77: =MAX($B$93,K77-$B$92) -> 0.079460673 | M77: =MAX($B$93,L77-$B$92) -> 0.069460673 | N77: =MAX($B$93,M77-$B$92) -> 0.059460673 | O77: =MAX($B$93,N77-$B$92) -> 0.055 | P77: Driver replaces the former balancing line. Starts from the FY26A actual ratio (G77 = 12.9%, Cost Schedule!G28) and steps down by B92 each year (operating leverage on tech, outsourced support, G&A) to a floor of B93. Step and floor are ANALYST JUDGEMENT, no external source — confirm or replace. Wrong if: payment-gateway and tech costs scale with NOV rather than revenue, or the 1P gross-up keeps the ratio falling faster than modelled.
A78: OTHER EXPENSES MIX (% of other expenses)
A79: IT support, server & communication costs | B79: % | D79: 0.17 | E79: 0.17 | F79: 0.17 | G79: 0.17 | H79: 0.17 | I79: 0.17 | J79: 0.17 | K79: 0.17 | L79: 0.17 | M79: 0.17 | N79: 0.17 | O79: 0.17
A80: Outsourced support costs | B80: % | D80: 0.15 | E80: 0.15 | F80: 0.15 | G80: 0.15 | H80: 0.15 | I80: 0.15 | J80: 0.15 | K80: 0.15 | L80: 0.15 | M80: 0.15 | N80: 0.15 | O80: 0.15
A81: Payment gateway & related charges | B81: % | D81: 0.12 | E81: 0.12 | F81: 0.12 | G81: 0.12 | H81: 0.12 | I81: 0.12 | J81: 0.12 | K81: 0.12 | L81: 0.12 | M81: 0.12 | N81: 0.12 | O81: 0.12
A82: Rent, rates & taxes | B82: % | D82: 0.08 | E82: 0.08 | F82: 0.08 | G82: 0.08 | H82: 0.08 | I82: 0.08 | J82: 0.08 | K82: 0.08 | L82: 0.08 | M82: 0.08 | N82: 0.08 | O82: 0.08
A84: CORPORATE / P&L DRIVERS
A85: Share-based payment expense | B85: INR Cr | D85: ='ESOP Schedule'!C5 -> 0 | E85: ='ESOP Schedule'!D5 -> 515 | F85: ='ESOP Schedule'!E5 -> 798 | G85: ='ESOP Schedule'!F5 -> 819 | H85: 850 | I85: 880 | J85: 900 | K85: 920 | L85: 940 | M85: 960 | N85: 980 | O85: 1000 | P85: ="FY25A "&TEXT(F85,"#,##0")&" / FY26A "&TEXT(G85,"#,##0")&" Cr (Q4FY26 cash flow statement, Data_Sources row 8). Forecast +20–30 Cr a year to "&TEXT(O85,"#,##0")&" is a smooth analyst ladder with no basis — MANUAL – OPEN." -> FY25A 798 / FY26A 819 Cr (Q4FY26 cash flow statement, Data_Sources row 8). Forecast +20–30 Cr a year to 1,000 is a smooth analyst ladder with no basis — MANUAL – OPEN.
A86: Rent paid on Ind AS 116 leases (average stores x contractual rent) | B86: INR Cr | E86: =IS!E56 -> 185 | F86: =IS!F56 -> 356 | G86: =IS!G56 -> 838 | H86: =ROUND((G16+H16)/2*$B$122*12*(1+$B$123)^1,0) -> 1387 | I86: =ROUND((H16+I16)/2*$B$122*12*(1+$B$123)^2,0) -> 2056 | J86: =ROUND((I16+J16)/2*$B$122*12*(1+$B$123)^3,0) -> 2843 | K86: =ROUND((J16+K16)/2*$B$122*12*(1+$B$123)^4,0) -> 3761 | L86: =ROUND((K16+L16)/2*$B$122*12*(1+$B$123)^5,0) -> 4809 | M86: =ROUND((L16+M16)/2*$B$122*12*(1+$B$123)^6,0) -> 5984 | N86: =ROUND((M16+N16)/2*$B$122*12*(1+$B$123)^7,0) -> 7298 | O86: =ROUND((N16+O16)/2*$B$122*12*(1+$B$123)^8,0) -> 8764 | P86: Rebuilt: average stores during the year times the contractual monthly rent times 12, escalated. Previously an independent growth ladder that had rent per store FALLING from 47 lakh to 24 lakh a year by FY2034E, which no lease contract would produce.
A87: ↳ implied growth in lease rent paid | B87: % | F87: =IFERROR(F86/E86-1,"") -> 0.92432432 | G87: =IFERROR(G86/F86-1,"") -> 1.3539326 | H87: =H86/G86-1 -> 0.65513126 | I87: =I86/H86-1 -> 0.48233598 | J87: =J86/I86-1 -> 0.3827821 | K87: =K86/J86-1 -> 0.32289835 | L87: =L86/K86-1 -> 0.2786493 | M87: =M86/L86-1 -> 0.24433354 | N87: =N86/M86-1 -> 0.21958556 | O87: =O86/N86-1 -> 0.20087695 | P87: Tracks net store adds (Blinkit added 17mn sq ft of dark-store/warehouse space by Q4FY26).
A88: (deleted) D&A % of adjusted revenue — fed nothing; IS takes D&A from FA_Schedule
A89: (deleted) Finance cost % of adjusted revenue — fed nothing; IS takes finance costs from Lease_Schedule
A90: Treasury yield on opening cash & investments | B90: % | E90: =IFERROR(IS!E23/CFS!D32,"") -> 0.074803497 | F90: =IFERROR(IS!F23/CFS!E32,"") -> 0.087983008 | G90: =IFERROR(IS!G23/CFS!F32,"") -> 0.083065572 | H90: 0.065 | I90: 0.065 | J90: 0.065 | K90: 0.065 | L90: 0.065 | M90: 0.065 | N90: 0.065 | O90: 0.065 | P90: FY26A other income INR 1,396 Cr on INR 18,400 Cr average treasury. Portfolio is G-secs, bonds and MFs held to maturity and yield set near the 10-yr G-Sec (6.70-6.85%, Jul-26).
A91: Effective tax rate (FY27E+: output of Tax_Schedule) | B91: % | D91: =-IS!D27/IS!D26 -> 0.043392505 | E91: =-IS!E27/IS!E26 -> -0.20618557 | F91: =-IS!F27/IS!F26 -> 0.24390244 | G91: =-IS!G27/IS!G26 -> 0.40487805 | H91: =Tax_Schedule!H12 -> 0 | I91: =Tax_Schedule!I12 -> 0 | J91: =Tax_Schedule!J12 -> 0 | K91: =Tax_Schedule!K12 -> 0 | L91: =Tax_Schedule!L12 -> 0 | M91: =Tax_Schedule!M12 -> 0 | N91: =Tax_Schedule!N12 -> 0.16374128 | O91: =Tax_Schedule!O12 -> 0.2517 | P91: FY24A–FY26A actual (tax ÷ PBT). Forecast is no longer typed: it is the output of the tax-loss carry-forward schedule (Tax_Schedule row 12) at the statutory rate in B157.
A92: Other expenses: annual step-down in % of revenue (pp) | B92: 0.01 | P92: Analyst judgement – MANUAL – OPEN (no source). Drives Assumptions row 77.
A93: Other expenses: floor (% of revenue from operations) | B93: 0.055 | P93: Analyst judgement – MANUAL – OPEN (no source). Roughly the FY27E level the old balancing line implied (5.5%).
A94: RECONCILIATION / PLUG DRIVERS (nil unless flexed)
A95: Customer platform fee & other adjustments (Revenue Schedule bridge) | B95: INR Cr | H95: 0 | I95: 0 | J95: 0 | K95: 0 | L95: 0 | M95: 0 | N95: 0 | O95: 0
A96: Other lease liability movements | B96: INR Cr | H96: 0 | I96: 0 | J96: 0 | K96: 0 | L96: 0 | M96: 0 | N96: 0 | O96: 0
A97: Other items in cash bridge (CFS) | B97: INR Cr | H97: 0 | I97: 0 | J97: 0 | K97: 0 | L97: 0 | M97: 0 | N97: 0 | O97: 0
A99: B. WORKING CAPITAL & CAPEX ASSUMPTIONS
A101: WORKING CAPITAL DRIVERS
A102: Receivable days (on revenue from operations) | B102: Days | D102: =BS!D13/'Revenue Schedule'!C31*365 -> 23.563356 | E102: =BS!E13/'Revenue Schedule'!D31*365 -> 23.92356 | F102: =BS!F13/'Revenue Schedule'!E31*365 -> 35.088179 | G102: =BS!G13/'Revenue Schedule'!F31*365 -> 11.843499 | H102: 12 | I102: 12 | J102: 12 | K102: 12 | L102: 12 | M102: 12 | N102: 12 | O102: 12 | P102: FY26A 11.8 days (receivables 1,764 on revenue from operations 54,364). Basis changed from adjusted revenue to reported revenue from operations so the driver matches the Ind AS statements the WC schedule feeds. Consumer platforms collect from payment gateways in days; receivables are mostly brand-ad and Hyperpure dues.
A103: Inventory days (on cost of goods sold) | B103: Days | D103: =WC_Schedule!D8 -> 21.716846 | E103: =WC_Schedule!E8 -> 11.145038 | F103: =WC_Schedule!F8 -> 11.543576 | G103: =WC_Schedule!G8 -> 26.388603 | H103: 26 | I103: 26 | J103: 25 | K103: 25 | L103: 24 | M103: 24 | N103: 24 | O103: 24 | P103: FY26A 26 days (inventories 2,181 on COGS 30,167). First full year of owning quick-commerce inventory and will improves modestly with assortment planning and Hyperpure backward integration.
A104: Payable days (on cost of goods sold) | B104: Days | D104: =WC_Schedule!D9 -> 177.6595 | E104: =WC_Schedule!E9 -> 112.21027 | F104: =WC_Schedule!F9 -> 100.74394 | G104: =WC_Schedule!G9 -> 36.418935 | H104: 36 | I104: 37 | J104: 38 | K104: 38 | L104: 38 | M104: 38 | N104: 38 | O104: 38 | P104: FY26A 36 days (payables 3,010 on COGS 30,167). Scale should lengthen terms with brands modestly in quick commerce.
A105: Other current assets (% of revenue from operations) | B105: % | D105: =(WC_Schedule!D15-WC_Schedule!D12-WC_Schedule!D13)/WC_Schedule!D5 -> 0.67650798 | E105: =(WC_Schedule!E15-WC_Schedule!E12-WC_Schedule!E13)/WC_Schedule!E5 -> 0.21173848 | F105: =(WC_Schedule!F15-WC_Schedule!F12-WC_Schedule!F13)/WC_Schedule!F5 -> 0.28222101 | G105: =(WC_Schedule!G15-WC_Schedule!G12-WC_Schedule!G13)/WC_Schedule!G5 -> 0.094566257 | H105: 0.085 | I105: 0.085 | J105: 0.08 | K105: 0.08 | L105: 0.08 | M105: 0.08 | N105: 0.08 | O105: 0.08 | P105: FY26A: other financial assets (current) 3,537 + other current assets 1,604 = 5,141 = 9.5% of revenue from operations (54,364). Includes gateway balances and supplier advances. Basis changed from adjusted revenue to revenue from operations.
A106: Other current liabilities (% of revenue from operations) | B106: % | D106: =WC_Schedule!D19/WC_Schedule!D5 -> 0.086452889 | E106: =WC_Schedule!E19/WC_Schedule!E5 -> 0.085520885 | F106: =WC_Schedule!F19/WC_Schedule!F5 -> 0.06911031 | G106: =WC_Schedule!G19/WC_Schedule!G5 -> 0.034728865 | H106: 0.034 | I106: 0.034 | J106: 0.034 | K106: 0.034 | L106: 0.034 | M106: 0.034 | N106: 0.034 | O106: 0.034 | P106: FY26A: other financial liabilities 1,105 + other current liabilities 744 + provisions 39 = 1,888 = 3.5% of revenue from operations (54,364).
A110: CAPEX & WORKING CAPITAL
A111: Capex per net new dark store | B111: INR Cr | E111: =FA_Schedule!D44 | F111: =FA_Schedule!E44 -> 0.71560338 | G111: =FA_Schedule!F44 -> 1.8535032 | H111: 2.5 | I111: 2.5 | J111: 2.5 | K111: 2.5 | L111: 2.5 | M111: 2.5 | N111: 2.5 | O111: 2.5 | P111: FY26A group capex INR 1,746 Cr on 942 net new stores (INR 1.85 Cr each including warehousing). UPDATED FOR Q1FY27 MANAGEMENT GUIDANCE: management has raised capex per store to INR 2.5 Cr, up from about INR 1 Cr, reflecting larger store formats and added warehousing/automation; commentary also notes it takes time for a new store to reach full productivity. Modelled at 2.5 Cr flat across FY27E-FY34E — held at the guided level.
A112: Other / maintenance capex | B112: INR Cr | H112: 450 | I112: 500 | J112: 550 | K112: 600 | L112: 650 | M112: 700 | N112: 750 | O112: 800 | P112: Technology, warehousing, Hyperpure facilities and maintenance capex. +50 Cr a year is a smooth analyst ladder with no basis — MANUAL – OPEN.
A113: (deleted) NWC % of revenue increase — fed nothing (and carried #REF!); NWC is built on days in WC_Schedule
A116: C. SCHEDULE / STRUCTURAL ASSUMPTIONS — feed the FA, Lease and WC schedules
A118: SCHEDULE DRIVERS — structural inputs (feed FA / Lease / WC schedules)
A119: PPE depreciation rate (% of average net block) | B119: 0.3 | P119: ="FY25A implied PPE depreciation "&TEXT(FA_Schedule!E10,"0%")&", FY26A "&TEXT(FA_Schedule!F10,"0%")&" (FA_Schedule row 10). Forecast uses "&TEXT(B119,"0%")&" — analyst judgement below the historical range as the asset base lengthens; MANUAL – OPEN." -> FY25A implied PPE depreciation 33%, FY26A 37% (FA_Schedule row 10). Forecast uses 30% — analyst judgement below the historical range as the asset base lengthens; MANUAL – OPEN.
A120: ROU depreciation rate (% of average ROU asset) | B120: 0.22 | P120: Dark store and warehouse leases run 5-9 years, 22% of the average ROU balance implies a 4.5-year weighted average remaining term given the young estate.
A121: Incremental borrowing rate (implied by FY25A-FY26A lease interest) | B121: =AVERAGE(Lease_Schedule!F21/((Lease_Schedule!F5+Lease_Schedule!F12)/2),Lease_Schedule!G21/((Lease_Schedule!G5+Lease_Schedule!G12)/2)) -> 0.10790881 | P121: Derived, not assumed: average of the FY2025A and FY2026A rates implied by lease interest accretion over the average lease liability (10.5% and 11.1%). Replaces a hardcoded 9.0%, which the actuals do not support.
A122: Monthly cash rent per store (implied by FY2026A) | B122: =Lease_Schedule!G23/((F16+G16)/2)/12 -> 0.03940933 | P122: FY2026A total lease payments of 838 Cr divided by average dark stores of 1,772 and by 12. Covers the whole leased estate - stores, warehousing and offices - expressed per store, which is consistent with how ROU additions per store are derived below.
A123: ↳ contractual rent escalation p.a. | B123: 0.05 | P123: Judgement. Typical Indian commercial lease escalation is around 5% p.a. or 15% every three years. Not disclosed by Eternal. This is the single most sensitive input in the lease rebuild.
A124: Lease term (months) — implied by FY2026A ROU additions per store | B124: =NPER(B121/12,-B122,FA_Schedule!F20/G18) -> 152.47276 | P124: Solved with NPER from the FY2026A actuals: the term that discounts the derived monthly rent back to the ROU asset actually recognised per net new store. 152 months is about 12.7 years, consistent with long lock-in dark store leases.
A125: New ROU / lease liability per net new dark store — PV of the rent stream | B125: =PV(B121/12,B124,-B122) -> 3.2632696 | P125: PV of the contractual rent stream at the incremental borrowing rate over the implied term. Reproduces the FY2026A actual of 3.26 Cr per store by construction. Replaces a flat 2.00 Cr placeholder that had no link to rent, term or discount rate.
A126: Lease renewals / extensions (% of opening liability) | B126: 0.1 | P126: ="Renewals at "&TEXT(B126,"0%")&" of opening lease liability (Lease_Schedule row 8). The SAME amount is added to the ROU asset (FA_Schedule row 21 = Lease_Schedule row 8), so a renewal raises asset and liability equally. Analyst judgement – MANUAL – OPEN." -> Renewals at 10% of opening lease liability (Lease_Schedule row 8). The SAME amount is added to the ROU asset (FA_Schedule row 21 = Lease_Schedule row 8), so a renewal raises asset and liability equally. Analyst judgement – MANUAL – OPEN.
A127: Lease terminations (% of opening liability) | B127: 0.02 | P127: ="Terminations at "&TEXT(B127,"0%")&" of opening lease LIABILITY (Lease_Schedule row 10); FA_Schedule row 23 derecognises the same amount of ROU asset, so no P&L gain/loss is created. FY26A gain on termination was INR 13 Cr (small volume). Analyst judgement – MANUAL – OPEN." -> Terminations at 2% of opening lease LIABILITY (Lease_Schedule row 10); FA_Schedule row 23 derecognises the same amount of ROU asset, so no P&L gain/loss is created. FY26A gain on termination was INR 13 Cr (small volume). Analyst judgement – MANUAL – OPEN.
...

Sheet Revenue Schedule
A1: SEGMENT MODEL — NOV and Adjusted Revenue by business (INR Cr) | P1: Source (linked to Data_Sources)
A2: Line item | B2: Unit | C2: FY2023A | D2: FY2024A | E2: FY2025A | F2: FY2026A | G2: FY2027E | H2: FY2028E | I2: FY2029E | J2: FY2030E | K2: FY2031E | L2: FY2032E | M2: FY2033E | N2: FY2034E | O2: Source (historicals)
A3: NOV TO ADJUSTED REVENUE BRIDGE | P3: =Data_Sources!$D$15&" | "&Data_Sources!$E$15&" | "&Data_Sources!$F$15 -> Eternal Q4FY26 shareholders' letter | Annexure A & B (reconciliation to reported P&L) | https://b.zmtcdn.com/investor-relations/Eternal_Shareholders_Letter_Q4FY26_Results.pdf
A4: Food delivery NOV | B4: INR Cr | C4: =C42 -> 22501 | D4: =D42 -> 27478 | E4: =E42 -> 32862 | F4: =F42 -> 37993 | G4: =G42 -> 44994.96 | H4: =H42 -> 53302.2 | I4: =I42 -> 63118.71 | J4: =J42 -> 74745.92 | ... N4: =N42 -> 142112.88
A5: × Take rate (% of NOV) | B5: % | C5: =IFERROR(C51/C4,"n.a.") -> 0.27318786 | D5: =IFERROR(D51/D4,"n.a.") -> 0.28357231 | E5: =IFERROR(E51/E4,"n.a.") -> 0.28659242 | F5: =IFERROR(F51/F4,"n.a.") -> 0.30789882 | G5: =IFERROR(G51/G4,"n.a.") -> 0.315 | H5: =IFERROR(H51/H4,"n.a.") -> 0.32 | I5: =IFERROR(I51/I4,"n.a.") -> 0.325 | J5: =IFERROR(J51/J4,"n.a.") -> 0.33 | ... N5: =IFERROR(N51/N4,"n.a.") -> 0.33
A6: = Food delivery adjusted revenue | B6: INR Cr | C6: =IFERROR(C4*C5,"n.a.") -> 6147 | D6: =IFERROR(D4*D5,"n.a.") -> 7792 | E6: =IFERROR(E4*E5,"n.a.") -> 9418 | F6: =IFERROR(F4*F5,"n.a.") -> 11698 | G6: =IFERROR(G4*G5,"n.a.") -> 14173.412 | H6: =IFERROR(H4*H5,"n.a.") -> 17056.704 | I6: =IFERROR(I4*I5,"n.a.") -> 20513.581 | J6: =IFERROR(J4*J5,"n.a.") -> 24666.154 | ... N6: =IFERROR(N4*N5,"n.a.") -> 46897.25
A8: Quick commerce NOV | B8: INR Cr | C8: =C56 -> 5690 | D8: =D56 -> 10503 | E8: =E56 -> 22371 | F8: =F56 -> 48568 | G8: =G56 -> 122333.4 | H8: =H56 -> 172703.4 | I8: =I56 -> 236930.62 | J8: =J56 -> 310465.35 | ... N8: =N56 -> 663838.28
A9: × Take rate (% of NOV) | B9: % | C9: =IFERROR(C68/C8,"n.a.") -> 0.14165202 | D9: =IFERROR(D68/D8,"n.a.") -> 0.21917547 | E9: =IFERROR(E68/E8,"n.a.") -> 0.23271199 | F9: =IFERROR(F68/F8,"n.a.") -> 0.77785785 | G9: =IFERROR(G68/G8,"n.a.") -> 0.92 | H9: =IFERROR(H68/H8,"n.a.") -> 0.92 | I9: =IFERROR(I68/I8,"n.a.") -> 0.92 | J9: =IFERROR(J68/J8,"n.a.") -> 0.92 | ... N9: =IFERROR(N68/N8,"n.a.") -> 0.92 | O9: The step-change here is the whole story of FY26. Blinkit's take rate runs at 14-23% while it operates as a marketplace earning commission, then jumps to c.78% in FY26 when the inventory-led (1P) model means the full value of goods sold is recognised as revenue rather than just the commission. NOV grew 117% in FY26; adjusted revenue grew 626%. Almost all of that gap is accounting basis, not trading performance — read the two together, never revenue alone. FY23 and FY24 order value is on the NOV basis, so the denominator is consistent throughout.
A10: = Quick commerce adjusted revenue | B10: INR Cr | C10: =IFERROR(C8*C9,"n.a.") -> 806 | D10: =IFERROR(D8*D9,"n.a.") -> 2302 | E10: =IFERROR(E8*E9,"n.a.") -> 5206 | F10: =IFERROR(F8*F9,"n.a.") -> 37779 | G10: =IFERROR(G8*G9,"n.a.") -> 112546.73 | H10: =IFERROR(H8*H9,"n.a.") -> 158887.13 | I10: =IFERROR(I8*I9,"n.a.") -> 217976.18 | J10: =IFERROR(J8*J9,"n.a.") -> 285628.12 | ... N10: =IFERROR(N8*N9,"n.a.") -> 610731.21
A12: Going-out NOV | B12: INR Cr | C12: =IF(ISNUMBER(C72),C72,"n.a.") -> n.a. | D12: =IF(ISNUMBER(D72),D72,"n.a.") -> 3225 | E12: =IF(ISNUMBER(E72),E72,"n.a.") -> 6619 | F12: =IF(ISNUMBER(F72),F72,"n.a.") -> 9399 | G12: =IF(ISNUMBER(G72),G72,"n.a.") -> 13158.6 | H12: =IF(ISNUMBER(H72),H72,"n.a.") -> 17895.696 | I12: =IF(ISNUMBER(I72),I72,"n.a.") -> 23622.319 | J12: =IF(ISNUMBER(J72),J72,"n.a.") -> 30709.014 | ... N12: =IF(ISNUMBER(N72),N72,"n.a.") -> 74973.18 | O12: Going-out was not a separate reportable segment in FY23 — it sat inside 'Others' — so FY23 shows n.a. rather than nil. The B2C NOV line below uses SUM, which ignores text, so the FY23 B2C total correctly excludes going-out.
A13: × Take rate (% of NOV) | B13: % | C13: =IFERROR(C75/C12,"n.a.") -> n.a. | D13: =IFERROR(D75/D12,"n.a.") -> 0.079689922 | E13: =IFERROR(E75/E12,"n.a.") -> 0.11285693 | F13: =IFERROR(F75/F12,"n.a.") -> 0.10352165 | G13: =IFERROR(G75/G12,"n.a.") -> 0.105 | H13: =IFERROR(H75/H12,"n.a.") -> 0.11 | I13: =IFERROR(I75/I12,"n.a.") -> 0.115 | J13: =IFERROR(J75/J12,"n.a.") -> 0.12 | ... N13: =IFERROR(N75/N12,"n.a.") -> 0.12
A14: = Going-out adjusted revenue | B14: INR Cr | C14: =IFERROR(C12*C13,"n.a.") -> n.a. | D14: =IFERROR(D12*D13,"n.a.") -> 257 | E14: =IFERROR(E12*E13,"n.a.") -> 747 | F14: =IFERROR(F12*F13,"n.a.") -> 973 | G14: =IFERROR(G12*G13,"n.a.") -> 1381.653 | H14: =IFERROR(H12*H13,"n.a.") -> 1968.5266 | I14: =IFERROR(I12*I13,"n.a.") -> 2716.5667 | J14: =IFERROR(J12*J13,"n.a.") -> 3685.0817 | ... N14: =IFERROR(N12*N13,"n.a.") -> 8996.7815
A16: B2C NOV (food delivery + quick commerce + going-out) | B16: INR Cr | C16: =SUM(C4,C8,C12) -> 28191 | D16: =SUM(D4,D8,D12) -> 41206 | E16: =SUM(E4,E8,E12) -> 61852 | F16: =SUM(F4,F8,F12) -> 95960 | G16: =SUM(G4,G8,G12) -> 180486.96 | H16: =SUM(H4,H8,H12) -> 243901.3 | I16: =SUM(I4,I8,I12) -> 323671.65 | J16: =SUM(J4,J8,J12) -> 415920.28 | ... N16: =SUM(N4,N8,N12) -> 880924.33
A17: × Blended B2C take rate (% of NOV) | B17: % | C17: =IFERROR(SUM(C6,C10,C14)/C16,"n.a.") -> 0.246639 | D17: =IFERROR(SUM(D6,D10,D14)/D16,"n.a.") -> 0.25120128 | E17: =IFERROR(SUM(E6,E10,E14)/E16,"n.a.") -> 0.24851258 | F17: =IFERROR(SUM(F6,F10,F14)/F16,"n.a.") -> 0.52573989 | G17: =IFERROR(SUM(G6,G10,G14)/G16,"n.a.") -> 0.7097565 | H17: =IFERROR(SUM(H6,H10,H14)/H16,"n.a.") -> 0.72944409 | I17: =IFERROR(SUM(I6,I10,I14)/I16,"n.a.") -> 0.74521917 | J17: =IFERROR(SUM(J6,J10,J14)/J16,"n.a.") -> 0.75490273 | ... N17: =IFERROR(SUM(N6,N10,N14)/N16,"n.a.") -> 0.75673383
A18: = B2C adjusted revenue | B18: INR Cr | C18: =IFERROR(C16*C17,"n.a.") -> 6953 | D18: =IFERROR(D16*D17,"n.a.") -> 10351 | E18: =IFERROR(E16*E17,"n.a.") -> 15371 | F18: =IFERROR(F16*F17,"n.a.") -> 50450 | G18: =IFERROR(G16*G17,"n.a.") -> 128101.79 | H18: =IFERROR(H16*H17,"n.a.") -> 177912.36 | I18: =IFERROR(I16*I17,"n.a.") -> 241206.32 | J18: =IFERROR(J16*J17,"n.a.") -> 313979.36 | ... N18: =IFERROR(N16*N17,"n.a.") -> 666625.24
A20: Add: B2B supplies (Hyperpure) — no NOV, revenue recognised gross | B20: INR Cr | C20: =C80 -> 1506 | D20: =D80 -> 3172 | E20: =E80 -> 6196 | F20: =F80 -> 5366 | G20: =G80 -> 5210.8 | H20: =H80 -> 7295.12 | I20: =I80 -> 10213.168 | J20: =J80 -> 14298.435 | ... N20: =N80 -> 54928.869
A21: Add: Others (incl. Bistro) — no NOV | B21: INR Cr | C21: =C87 -> 234 | D21: =D87 -> 22 | E21: =E87 -> 30 | F21: =F87 -> 87 | G21: =G87 -> 121.8 | H21: =H87 -> 164.43 | I21: =I87 -> 213.759 | J21: =J87 -> 267.19875 | ... N21: =N87 -> 454.28063
A23: TOTAL ADJUSTED REVENUE | B23: INR Cr | C23: =SUM(C18,C20,C21) -> 8693 | D23: =SUM(D18,D20,D21) -> 13545 | E23: =SUM(E18,E20,E21) -> 21597 | F23: =SUM(F18,F20,F21) -> 55903 | G23: =SUM(G18,G20,G21) -> 133434.39 | H23: =SUM(H18,H20,H21) -> 185371.91 | I23: =SUM(I18,I20,I21) -> 251633.25 | J23: =SUM(J18,J20,J21) -> 328544.99 | ... N23: =SUM(N18,N20,N21) -> 722008.39
A24: Check vs consolidated total below (must be nil) | B24: INR Cr | C24: =C23-C27 -> 0 | D24: =D23-D27 -> 0 | E24: =E23-E27 -> 0 | F24: =F23-F27 -> 0 | G24: =G23-G27 -> 0 | H24: =H23-H27 -> 0 | I24: =I23-I27 -> 0 | J24: =J23-J27 -> 0 | ... N24: =N23-N27 -> 0
A26: CONSOLIDATED
A27: Total Adjusted Revenue | B27: INR Cr | C27: =SUM(C51,C68,C75,C80,C87) -> 8693 | D27: =SUM(D51,D68,D75,D80,D87) -> 13545 | E27: =E51+E68+E75+E80+E87 -> 21597 | F27: =F51+F68+F75+F80+F87 -> 55903 | G27: =G51+G68+G75+G80+G87 -> 133434.39 | H27: =H51+H68+H75+H80+H87 -> 185371.91 | I27: =I51+I68+I75+I80+I87 -> 251633.25 | J27: =J51+J68+J75+J80+J87 -> 328544.99 | K27: =K51+K68+K75+K80+K87 -> 415126.02 | L27: =L51+L68+L75+L80+L87 -> 512096.38 | ... N27: =N51+N68+N75+N80+N87 -> 722008.39 | O27: Cross-check against disclosure: FY23 8,693, FY24 13,545, FY25 21,597 and FY26 55,903 all tie to Eternal's disclosed consolidated adjusted revenue (sum of quarterly figures; FY25 reported as 21,581 in the AGM commentary, the difference being rounding of quarterly disclosures).
A28: % Growth | D28: =D27/C27-1 -> 0.55815024 | E28: =E27/D27-1 -> 0.5944629 | F28: =F27/E27-1 -> 1.5884614 | G28: =G27/F27-1 -> 1.3868915 | H28: =H27/G27-1 -> 0.38923634 | I28: =I27/H27-1 -> 0.35745082 | J28: =J27/I27-1 -> 0.30565016 | K28: =K27/J27-1 -> 0.26352868 | ... N28: =N27/M27-1 -> 0.16296999
A30: BRIDGE — REVENUE FROM OPERATIONS (IND AS) TO ADJUSTED REVENUE
A31: Revenue from operations (reported, Ind AS) | B31: INR Cr | C31: 7079 | D31: 12114 | E31: 20243 | F31: 54364 | G31: =G27-G33-G34 -> 130546.6 | H31: =H27-H33-H34 -> 181469.49 | I31: =I27-I33-I34 -> 246454.5 | J31: =J27-J33-J34 -> 321890.27 | K31: =K27-K33-K34 -> 406825.36 | L31: =L27-L33-L34 -> 501959.07 | M31: =M27-M33-M34 -> 608647.49 | N31: =N27-N33-N34 -> 707913.6
A32: Growth | B32: % | D32: =IFERROR(D31/C31-1,"") -> 0.71125865 | E32: =IFERROR(E31/D31-1,"") -> 0.67104177 | F32: =IFERROR(F31/E31-1,"") -> 1.6855703 | G32: =IFERROR(G31/F31-1,"") -> 1.4013428 | H32: =IFERROR(H31/G31-1,"") -> 0.39007439 | I32: =IFERROR(I31/H31-1,"") -> 0.35810436 | J32: =IFERROR(J31/I31-1,"") -> 0.30608393 | K32: =IFERROR(K31/J31-1,"") -> 0.26386352 | ... N32: =IFERROR(N31/M31-1,"") -> 0.16309296
A33: Add: Customer delivery charges (netted off in reported revenue) | B33: INR Cr | C33: =C27-C31-C34 -> 1614 | D33: =D27-D31-D34 -> 1431 | E33: =E27-E31-E34 -> 1354 | F33: =F27-F31-F34 -> 1539 | G33: =G16*G37 -> 2887.7914 | H33: =H16*H37 -> 3902.4207 | I33: =I16*I37 -> 5178.7465 | J33: =J16*J37 -> 6654.7245 | K33: =K16*K37 -> 8300.6545 | L33: =L16*L37 -> 10137.314 | M33: =M16*M37 -> 12184.003 | N33: =N16*N37 -> 14094.789
A34: Add: Customer platform fee & other adjustments | B34: INR Cr | C34: =Assumptions!D95 -> 0 | D34: =Assumptions!E95 -> 0 | E34: =Assumptions!F95 -> 0 | F34: =Assumptions!G95 -> 0 | G34: =Assumptions!H95 -> 0 | H34: =Assumptions!I95 -> 0 | I34: =Assumptions!J95 -> 0 | J34: =Assumptions!K95 -> 0 | ... N34: =Assumptions!O95 -> 0
A35: TOTAL ADJUSTED REVENUE | B35: INR Cr | C35: =C31+C33+C34 -> 8693 | D35: =D31+D33+D34 -> 13545 | E35: =E31+E33+E34 -> 21597 | F35: =F31+F33+F34 -> 55903 | G35: =G31+G33+G34 -> 133434.39 | H35: =H31+H33+H34 -> 185371.91 | I35: =I31+I33+I34 -> 251633.25 | J35: =J31+J33+J34 -> 328544.99 | ... N35: =N31+N33+N34 -> 722008.39
A36: Check vs consolidated total above (must be nil) | B36: INR Cr | C36: =IFERROR(ROUND(C35-C27,6),"n.a.") -> 0 | D36: =IFERROR(ROUND(D35-D27,6),"n.a.") -> 0 | E36: =IFERROR(ROUND(E35-E27,6),"n.a.") -> 0 | F36: =IFERROR(ROUND(F35-F27,6),"n.a.") -> 0 | G36: =IFERROR(ROUND(G35-G27,6),"n.a.") -> 0 | H36: =IFERROR(ROUND(H35-H27,6),"n.a.") -> 0 | I36: =IFERROR(ROUND(I35-I27,6),"n.a.") -> 0 | J36: =IFERROR(ROUND(J35-J27,6),"n.a.") -> 0 | ... N36: =IFERROR(ROUND(N35-N27,6),"n.a.") -> 0
A37: Memo: delivery charges as % of B2C NOV | B37: % | C37: =IFERROR(C33/C16,"") -> 0.057252315 | D37: =IFERROR(D33/D16,"") -> 0.034727952 | E37: =IFERROR(E33/E16,"") -> 0.021890966 | F37: =IFERROR(F33/F16,"") -> 0.016037932 | G37: =Assumptions!H76 -> 0.016 | H37: =Assumptions!I76 -> 0.016 | I37: =Assumptions!J76 -> 0.016 | J37: =Assumptions!K76 -> 0.016 | K37: =Assumptions!L76 -> 0.016 | L37: =Assumptions!M76 -> 0.016 | M37: =Assumptions!N76 -> 0.016 | N37: =Assumptions!O76 -> 0.016
A41: FOOD DELIVERY (ZOMATO) | P41: =Data_Sources!$D$11&" | "&Data_Sources!$E$11&" | "&Data_Sources!$F$11 -> Eternal Q4FY26 shareholders' letter | Annexure A — NOV (B2C business) | https://b.zmtcdn.com/investor-relations/Eternal_Shareholders_Letter_Q4FY26_Results.pdf
A42: Net Order Value (NOV) | B42: INR Cr | C42: 22501 | D42: 27478 | E42: 32862 | F42: 37993 | G42: =G45*G48 -> 44994.96 | H42: =H45*H48 -> 53302.2 | I42: =I45*I48 -> 63118.71 | J42: =J45*J48 -> 74745.92 | K42: =K45*K48 -> 87781.44 | L42: =L45*L48 -> 103062 | M42: =M45*M48 -> 121040.27 | N42: =N45*N48 -> 142112.88
A43: NOV growth | B43: % | D43: =D42/C42-1 -> 0.22119017 | E43: =E42/D42-1 -> 0.19593857 | F43: =F42/E42-1 -> 0.15613779 | G43: =G42/F42-1 -> 0.18429605 | H43: =H42/G42-1 -> 0.18462601 | I43: =I42/H42-1 -> 0.18416707 | J43: =J42/I42-1 -> 0.18421178 | K43: =K42/J42-1 -> 0.17439775 | ... N43: =N42/M42-1 -> 0.17409586
A45: Orders | B45: CR. | C45: =647/10 -> 64.7 | D45: =753.2/10 -> 75.32 | E45: =852.8/10 -> 85.28 | F45: =979.3/10 -> 97.93 | G45: =IFERROR(Assumptions!H8,"") -> 112.6 | H45: =IFERROR(Assumptions!I8,"") -> 129.5 | I45: =IFERROR(Assumptions!J8,"") -> 148.9 | J45: =IFERROR(Assumptions!K8,"") -> 171.2 | K45: =IFERROR(Assumptions!L8,"") -> 195.2 | L45: =IFERROR(Assumptions!M8,"") -> 222.5 | M45: =IFERROR(Assumptions!N8,"") -> 253.7 | N45: =IFERROR(Assumptions!O8,"") -> 289.2 | O45: Eternal quarterly KPI databook, sheet 'B. Annual data', section 2) Food delivery, row 'Orders (million)': FY23 647.0, FY24 753.2, FY25 852.8, FY26 979.3. Databook supplied by user upload (the IR site is JavaScript-rendered and its PDFs are image-only). Stated here in crore, so the formula divides the disclosed million figure by 10. Cross-check: the FY25 annual report also reports 853 mn orders against 753 mn in FY24. See Data_Sources row 38.
A46: % of Orders | B46: CR. | D46: =D45/C45-1 -> 0.16414219 | E46: =E45/D45-1 -> 0.13223579 | F46: =F45/E45-1 -> 0.1483349 | G46: =IFERROR(Assumptions!H9,"") -> 0.15 | H46: =IFERROR(Assumptions!I9,"") -> 0.15 | I46: =IFERROR(Assumptions!J9,"") -> 0.15 | J46: =IFERROR(Assumptions!K9,"") -> 0.15 | K46: =IFERROR(Assumptions!L9,"") -> 0.14 | L46: =IFERROR(Assumptions!M9,"") -> 0.14 | M46: =IFERROR(Assumptions!N9,"") -> 0.14 | N46: =IFERROR(Assumptions!O9,"") -> 0.14
A48: Net average order value (NAOV) | B48: INR | C48: =IFERROR(C42/C45,"") -> 347.77434 | D48: =IFERROR(D42/D45,"") -> 364.81678 | E48: =IFERROR(E42/E45,"") -> 385.3424 | F48: =IFERROR(F42/F45,"") -> 387.96079 | G48: =IFERROR(Assumptions!H11,"") -> 399.6 | H48: =IFERROR(Assumptions!I11,"") -> 411.6 | I48: =IFERROR(Assumptions!J11,"") -> 423.9 | J48: =IFERROR(Assumptions!K11,"") -> 436.6 | K48: =IFERROR(Assumptions!L11,"") -> 449.7 | L48: =IFERROR(Assumptions!M11,"") -> 463.2 | M48: =IFERROR(Assumptions!N11,"") -> 477.1 | N48: =IFERROR(Assumptions!O11,"") -> 491.4 | O48: This reproduces the databook's own disclosed net AOV of 365 / 385 / 388 for FY24-FY26 exactly, which validates the wiring. FY23 (348) has no disclosed counterpart , the databook publishes net AOV only from FY24, since NOV was first reported that year. See Data_Sources row 38.
A49: % change in orders | D49: =D48/C48-1 -> 0.049004301 | E49: =E48/D48-1 -> 0.056262817 | F49: =F48/E48-1 -> 0.0067949616 | G49: =G48/F48-1 -> 0.030001 | H49: =H48/G48-1 -> 0.03003003 | I49: =I48/H48-1 -> 0.029883382 | J49: =J48/I48-1 -> 0.029959896 | K49: =K48/J48-1 -> 0.030004581 | ... N49: =N48/M48-1 -> 0.029972752
A51: Adjusted revenue | B51: INR Cr | C51: 6147 | D51: 7792 | E51: 9418 | F51: 11698 | G51: =G42*Assumptions!H13 -> 14173.412 | H51: =H42*Assumptions!I13 -> 17056.704 | I51: =I42*Assumptions!J13 -> 20513.581 | J51: =J42*Assumptions!K13 -> 24666.154 | K51: =K42*Assumptions!L13 -> 28967.875 | L51: =L42*Assumptions!M13 -> 34010.46 | M51: =M42*Assumptions!N13 -> 39943.289 | N51: =N42*Assumptions!O13 -> 46897.25
A52: Take rate (% of NOV) | B52: % | C52: =C51/C42 -> 0.27318786 | D52: =D51/D42 -> 0.28357231 | E52: =E51/E42 -> 0.28659242 | F52: =F51/F42 -> 0.30789882 | G52: =G51/G42 -> 0.315 | H52: =H51/H42 -> 0.32 | I52: =I51/I42 -> 0.325 | J52: =J51/J42 -> 0.33 | ... N52: =N51/N42 -> 0.33
A55: QUICK COMMERCE (BLINKIT) | P55: =Data_Sources!$D$12&" | "&Data_Sources!$E$12&" | "&Data_Sources!$F$12 -> Eternal Q4FY26 shareholders' letter | Annexure A — quick commerce financial and operating metrics | https://b.zmtcdn.com/investor-relations/Eternal_Shareholders_Letter_Q4FY26_Results.pdf
A56: Net Order Value (NOV) | B56: INR Cr | C56: 5690 | D56: 10503 | E56: 22371 | F56: 48568 | G56: =G63*G66*365/10000 -> 122333.4 | H56: =H63*H66*365/10000 -> 172703.4 | I56: =I63*I66*365/10000 -> 236930.62 | J56: =J63*J66*365/10000 -> 310465.35 | K56: =K63*K66*365/10000 -> 392623.2 | L56: =L63*L66*365/10000 -> 482537.3 | M56: =M63*M66*365/10000 -> 580481.4 | N56: =N63*N66*365/10000 -> 663838.28 | O56: Quick commerce NOV. FY23 5,690 and FY24 10,503 per Eternal's Annual Report FY2024-25, implies a net AOV of 517 on 203 mn orders against a disclosed Q4FY24 net AOV of 511; FY23 is consistent with management's stated 104% FY23-FY26 NOV CAGR in the Q4FY26 letter (5,690 to 48,568 = 104.4%). FY25 22,371 (4,061 + 4,928 + 6,020 + 7,362) and FY26 48,568 (9,203 + 11,679 + 13,300 + 14,386): Eternal Q4FY25 and Q4FY26 Shareholders' Letters, Annexure A. FY23 is not a full-year comparable — Blinkit was consolidated only from 10-Aug-22 and Q1/Q2FY23 are unaudited MIS figures.
A57: NOV growth | B57: % | D57: =D56/C56-1 -> 0.84586995 | E57: =E56/D56-1 -> 1.1299629 | F57: =F56/E56-1 -> 1.171025 | G57: =G56/F56-1 -> 1.5188066 | H57: =H56/G56-1 -> 0.41174364 | I57: =I56/H56-1 -> 0.37189323 | J57: =J56/I56-1 -> 0.31036395 | K57: =K56/J56-1 -> 0.26462808 | ... N57: =N56/M56-1 -> 0.14359956
A58: Memo: Gross Order Value (GOV) — FY23/FY24 disclosure basis | B58: INR Cr | C58: 6449 | D58: 12469 | O58: Memo GOV, retained for reference only — the NOV row is the model's order-value basis. FY23 6,449 on a full-year unaudited MIS basis (quarterly 11.72 + 14.82 + 17.49 + 20.46 INR bn): Zomato Q4FY23 Shareholders' Letter, Annexure A, https://b.zmtcdn.com/investor-relations/4dbd068492199a12eee4cd3ffca15fe4_1684493677.pdf. FY24 12,469 (2,140 + 2,760 + 3,542 + 4,027): Zomato Q4FY24 Shareholders' Letter
A60: Dark stores (end of year) | B60: # | C60: 377 | D60: 526 | E60: 1301 | F60: 2243 | G60: =Assumptions!H16 -> 3343 | H60: =Assumptions!I16 -> 4543 | I60: =Assumptions!J16 -> 5843 | J60: =Assumptions!K16 -> 7243 | K60: =Assumptions!L16 -> 8693 | L60: =Assumptions!M16 -> 10193 | M60: =Assumptions!N16 -> 11743 | N60: =Assumptions!O16 -> 13343 | O60: Dark stores at period end. Q4FY26 letter, Annexure A: 1,301 (Mar-25) to 2,243 (Mar-26). Earlier years 377 (Q4FY23) and 526 (Q4FY24) from Zomato Q4FY24 Shareholders' Letter, Annexure A
A61: % change growth | D61: =D60/C60-1 -> 0.39522546 | E61: =E60/D60-1 -> 1.473384 | F61: =F60/E60-1 -> 0.72405842 | G61: =G60/F60-1 -> 0.49041462 | H61: =H60/G60-1 -> 0.35895902 | I61: =I60/H60-1 -> 0.28615452 | J61: =J60/I60-1 -> 0.23960294 | K61: =K60/J60-1 -> 0.20019329 | ... N61: =N60/M60-1 -> 0.13625138
A63: Average stores during year | B63: # | D63: =(C60+D60)/2 -> 451.5 | E63: =(D60+E60)/2 -> 913.5 | F63: =(E60+F60)/2 -> 1772 | G63: =(F60+G60)/2 -> 2793 | H63: =(G60+H60)/2 -> 3943 | I63: =(H60+I60)/2 -> 5193 | J63: =(I60+J60)/2 -> 6543 | K63: =(J60+K60)/2 -> 7968 | ... N63: =(M60+N60)/2 -> 12543
A64: Stores growth | E64: =E63/D63-1 -> 1.0232558 | F64: =F63/E63-1 -> 0.93979201 | G64: =G63/F63-1 -> 0.5761851 | H64: =H63/G63-1 -> 0.41174364 | I64: =I63/H63-1 -> 0.3170175 | J64: =J63/I63-1 -> 0.25996534 | K64: =K63/J63-1 -> 0.21779 | L64: =L63/K63-1 -> 0.18511546 | ... N64: =N63/M63-1 -> 0.14359956
A66: NOV per day, per store | B66: INR '000 | D66: 672 | E66: 766 | F66: 756 | G66: =Assumptions!H20 -> 1200 | H66: =Assumptions!I20 -> 1200 | I66: =Assumptions!J20 -> 1250 | J66: =Assumptions!K20 -> 1300 | K66: =Assumptions!L20 -> 1350 | L66: =Assumptions!M20 -> 1400 | M66: =Assumptions!N20 -> 1450 | N66: =Assumptions!O20 -> 1450
A67: per day,per store NOV growth | E67: =E66/D66-1 -> 0.13988095 | F67: =F66/E66-1 -> -0.01305483 | G67: =G66/F66-1 -> 0.58730159 | H67: =H66/G66-1 -> 0 | I67: =I66/H66-1 -> 0.041666667 | J67: =J66/I66-1 -> 0.04 | K67: =K66/J66-1 -> 0.038461538 | L67: =L66/K66-1 -> 0.037037037 | ... N67: =N66/M66-1 -> 0
A68: Adjusted revenue | B68: INR Cr | C68: 806 | D68: 2302 | E68: 5206 | F68: 37779 | G68: =G56*Assumptions!H33 -> 112546.73 | H68: =H56*Assumptions!I33 -> 158887.13 | I68: =I56*Assumptions!J33 -> 217976.18 | J68: =J56*Assumptions!K33 -> 285628.12 | K68: =K56*Assumptions!L33 -> 361213.34 | L68: =L56*Assumptions!M33 -> 443934.32 | M68: =M56*Assumptions!N33 -> 534042.89 | N68: =N56*Assumptions!O33 -> 610731.21 | O68: Quick commerce adjusted revenue. FY23 806 (part year from 10-Aug-22; nil + 1.42 + 3.01 + 3.63 INR bn), FY24 2,302 (384 + 505 + 644 + 769), FY25 5,206 (942 + 1,156 + 1,399 + 1,709) — all on the marketplace/commission model. FY26 37,779 (2,400 + 9,891 + 12,256 + 13,232); the step-up reflects the shift to an inventory-led (1P) model from Q1FY26, where revenue captures the full value of goods sold. Source: Zomato Q4FY23 and Q4FY24, Eternal Q4FY25 and Q4FY26 Shareholders' Letters, Annexure A.
A69: Take rate (% of NOV) | B69: % | C69: =IFERROR(C68/C56,"n.a.") -> 0.14165202 | D69: =IFERROR(D68/D56,"n.a.") -> 0.21917547 | E69: =IFERROR(E68/E56,"n.a.") -> 0.23271199 | F69: =IFERROR(F68/F56,"n.a.") -> 0.77785785 | G69: =IFERROR(G68/G56,"n.a.") -> 0.92 | H69: =IFERROR(H68/H56,"n.a.") -> 0.92 | I69: =IFERROR(I68/I56,"n.a.") -> 0.92 | J69: =IFERROR(J68/J56,"n.a.") -> 0.92 | ... N69: =IFERROR(N68/N56,"n.a.") -> 0.92
A71: GOING-OUT (DISTRICT) | P71: =Data_Sources!$D$13&" | "&Data_Sources!$E$13&" | "&Data_Sources!$F$13 -> Eternal Q4FY26 shareholders' letter | Annexure A — going-out metrics | https://b.zmtcdn.com/investor-relations/Eternal_Shareholders_Letter_Q4FY26_Results.pdf
A72: Net Order Value (NOV) | B72: INR Cr | D72: 3225 | E72: 6619 | F72: 9399 | G72: =F72*(1+Assumptions!H36) -> 13158.6 | H72: =G72*(1+Assumptions!I36) -> 17895.696 | I72: =H72*(1+Assumptions!J36) -> 23622.319 | J72: =I72*(1+Assumptions!K36) -> 30709.014 | K72: =J72*(1+Assumptions!L36) -> 38386.268 | L72: =K72*(1+Assumptions!M36) -> 47982.835 | M72: =L72*(1+Assumptions!N36) -> 59978.544 | N72: =M72*(1+Assumptions!O36) -> 74973.18 | O72: Going-out order value. FY23 n.a. — going-out was not a separate reportable segment until 1-Jul-2023 (identified from Q2FY24); in FY23 it sat within 'All other segments' and is therefore inside the Others line below. FY24 3,225 is GOV, NOT NOV (616 + 682 + 858 + 1,069; cross-check: B2C GOV 47,918 less food delivery 32,224 less quick commerce 12,469) — Eternal has never published FY24 going-out NOV, so this row is mixed-basis at the FY24/FY25 boundary. FY25 6,619 (1,031 + 1,562 + 2,158 + 1,868) and FY26 9,399 (2,013 + 2,063 + 2,587 + 2,736) are NOV. Source: Zomato Q4FY24, Eternal Q4FY25 and Q4FY26 Shareholders' Letters, Annexure A.
A73: NOV growth | B73: % | E73: =E72/D72-1 -> 1.0524031 | F73: =F72/E72-1 -> 0.42000302 | G73: =G72/F72-1 -> 0.4 | H73: =H72/G72-1 -> 0.36 | I73: =I72/H72-1 -> 0.32 | J73: =J72/I72-1 -> 0.3 | K73: =K72/J72-1 -> 0.25 | L73: =L72/K72-1 -> 0.25 | ... N73: =N72/M72-1 -> 0.25
A75: Revenue | B75: INR Cr | D75: 257 | E75: 747 | F75: 973 | G75: =G72*Assumptions!H37 -> 1381.653 | H75: =H72*Assumptions!I37 -> 1968.5266 | I75: =I72*Assumptions!J37 -> 2716.5667 | J75: =J72*Assumptions!K37 -> 3685.0817 | K75: =K72*Assumptions!L37 -> 4606.3522 | L75: =L72*Assumptions!M37 -> 5757.9402 | M75: =M72*Assumptions!N37 -> 7197.4252 | N75: =N72*Assumptions!O37 -> 8996.7815 | O75: Going-out adjusted revenue. FY24 257 (42 + 49 + 73 + 93), FY25 747 (95 + 164 + 259 + 229), FY26 973 (207 + 189 + 300 + 277). Source: Zomato Q4FY24, Eternal Q4FY25 and Q4FY26 Shareholders' Letters, Annexure A.
A76: Take rate (% of NOV) | B76: % | D76: =IFERROR(D75/D72,"n.a.") -> 0.079689922 | E76: =IFERROR(E75/E72,"n.a.") -> 0.11285693 | F76: =IFERROR(F75/F72,"n.a.") -> 0.10352165 | G76: =IFERROR(G75/G72,"n.a.") -> 0.105 | H76: =IFERROR(H75/H72,"n.a.") -> 0.11 | I76: =IFERROR(I75/I72,"n.a.") -> 0.115 | J76: =IFERROR(J75/J72,"n.a.") -> 0.12 | K76: =IFERROR(K75/K72,"n.a.") -> 0.12 | ... N76: =IFERROR(N75/N72,"n.a.") -> 0.12
A79: B2B SUPPLIES (HYPERPURE)
A80: Revenue | B80: INR Cr | C80: 1506 | D80: =D83+D84 -> 3172 | E80: =E83+E84 -> 6196 | F80: =F83+F84 -> 5366 | G80: =G83+G84 -> 5210.8 | H80: =H83+H84 -> 7295.12 | I80: =I83+I84 -> 10213.168 | J80: =J83+J84 -> 14298.435 | K80: =K83+K84 -> 20017.809 | ... N80: =N83+N84 -> 54928.869 | O80: Hyperpure adjusted revenue. FY23 1,506 (2.73 + 3.34 + 4.21 + 4.78 INR bn), FY24 3,172 (617 + 745 + 859 + 951), FY25 6,196 (1,212 + 1,473 + 1,671 + 1,840), FY26 5,366 (2,295 + 1,023 + 1,070 + 978) — the FY26 decline comes from inventory-led quick commerce sourcing now being reported inside Blinkit. Source: Zomato Q4FY23 and Q4FY24, Eternal Q4FY25 and Q4FY26 Shareholders' Letters, Annexure A.
A81: Revenue growth | B81: % | D81: =D80/C80-1 -> 1.1062417 | E81: =E80/D80-1 -> 0.95334174 | F81: =F80/E80-1 -> -0.13395739 | G81: =G80/F80-1 -> -0.028922848 | H81: =H80/G80-1 -> 0.4 | I81: =I80/H80-1 -> 0.4 | J81: =J80/I80-1 -> 0.4 | K81: =K80/J80-1 -> 0.4 | ... N81: =N80/M80-1 -> 0.4 | P81: =Data_Sources!$D$14&" | "&Data_Sources!$E$14&" | "&Data_Sources!$F$14 -> Eternal Q4FY26 shareholders' letter | Annexure A — B2B supplies metrics | https://b.zmtcdn.com/investor-relations/Eternal_Shareholders_Letter_Q4FY26_Results.pdf
A83: Restaurant business revenue | B83: INR Cr | D83: 1970 | E83: 2699 | F83: 3722 | G83: =F83*(1+Assumptions!H41) -> 5210.8 | H83: =G83*(1+Assumptions!I41) -> 7295.12 | I83: =H83*(1+Assumptions!J41) -> 10213.168 | J83: =I83*(1+Assumptions!K41) -> 14298.435 | K83: =J83*(1+Assumptions!L41) -> 20017.809 | L83: =K83*(1+Assumptions!M41) -> 28024.933 | M83: =L83*(1+Assumptions!N41) -> 39234.906 | N83: =M83*(1+Assumptions!O41) -> 54928.869 | O83: Restaurant / non-restaurant split: FY25A–FY26A values typed from disclosure; forecast restaurant line grows at Assumptions row 41 (own column); non-restaurant from Assumptions row 42 (MANUAL – OPEN).
A84: Non-restaurant business revenue (B2B sales to Blinkit sellers) | B84: INR Cr | D84: 1202 | E84: 3497 | F84: 1644 | G84: =Assumptions!H42 -> 0 | H84: =Assumptions!I42 -> 0 | I84: =Assumptions!J42 -> 0 | J84: =Assumptions!K42 -> 0 | K84: =Assumptions!L42 -> 0 | L84: =Assumptions!M42 -> 0 | M84: =Assumptions!N42 -> 0 | N84: =Assumptions!O42 -> 0 | O84: Discontinued the B2B with Blinkit as it transform to IP model.
A86: OTHERS (incl. Bistro)
A87: Revenue | B87: INR Cr | C87: 234 | D87: 22 | E87: 30 | F87: 87 | G87: =F87*(1+Assumptions!H44) -> 121.8 | H87: =G87*(1+Assumptions!I44) -> 164.43 | I87: =H87*(1+Assumptions!J44) -> 213.759 | J87: =I87*(1+Assumptions!K44) -> 267.19875 | K87: =J87*(1+Assumptions!L44) -> 320.6385 | L87: =K87*(1+Assumptions!M44) -> 368.73427 | M87: =L87*(1+Assumptions!N44) -> 412.98239 | N87: =M87*(1+Assumptions!O44) -> 454.28063 | O87: Others' adjusted revenue. FY23 234 (0.67 + 0.49 + 0.75 + 0.43 INR bn) — NOT comparable with later years, because FY23 'Others' still includes the going-out / dining-out business, which became a separate reportable segment only from 1-Jul-2023. FY24 22 (1 + 5 + 8 + 10), FY25 30 (15 + 4 + 4 + 7), FY26 87 (residual of disclosed consolidated adjusted revenue of 55,903 less the four reported segments). Source: Zomato Q4FY23 and Q4FY24, Eternal Q4FY25 and Q4FY26 Shareholders' Letters, Annexure A.

Sheet Cost Schedule
A1: COST STRUCTURE — reported P&L expense waterfall and operating leverage (INR Cr) | Q1: =Data_Sources!$D$30&" | "&Data_Sources!$E$30&" | "&Data_Sources!$F$30 -> Eternal Q4FY26 audited consolidated P&L | Annexure D — expenses | https://b.zmtcdn.com/investor-relations/Eternal_Shareholders_Letter_Q4FY26_Results.pdf
A2: Line item | B2: Unit | D2: FY2023A | E2: FY2024A | F2: FY2025A | G2: FY2026A | H2: FY2027E | I2: FY2028E | J2: FY2029E | K2: FY2030E | L2: FY2031E | M2: FY2032E | N2: FY2033E | O2: FY2034E | P2: Source / Note
A4: A. EXPENSE BUILD (INR Cr)
A5: Revenue from operations (reported, Ind AS) | B5: INR Cr | D5: =IS!D6 -> 7079 | E5: =IS!E6 -> 12114 | F5: =IS!F6 -> 20243 | G5: =IS!G6 -> 54364 | H5: =IS!H6 -> 130546.6 | I5: =IS!I6 -> 181469.49 | J5: =IS!J6 -> 246454.5 | K5: =IS!K6 -> 321890.27 | ... O5: =IS!O6 -> 707913.6
A6: Cost of goods sold (purchases + materials + inventory change) | B6: INR Cr | D6: 1395 | E6: 2882 | F6: 5565 | G6: 30167 | H6: ='Revenue Schedule'!G68*(1-Assumptions!H71)+'Revenue Schedule'!G80*(1-Assumptions!H72) -> 83490.547 | I6: ='Revenue Schedule'!H68*(1-Assumptions!I71)+'Revenue Schedule'!H80*(1-Assumptions!I72) -> 116049.89 | J6: ='Revenue Schedule'!I68*(1-Assumptions!J71)+'Revenue Schedule'!I80*(1-Assumptions!J72) -> 158151.75 | K6: ='Revenue Schedule'!J68*(1-Assumptions!K71)+'Revenue Schedule'!J80*(1-Assumptions!K72) -> 206480.48 | L6: ='Revenue Schedule'!K68*(1-Assumptions!L71)+'Revenue Schedule'!K80*(1-Assumptions!L72) -> 260741.79 | M6: ='Revenue Schedule'!L68*(1-Assumptions!M71)+'Revenue Schedule'!L80*(1-Assumptions!M72) -> 323414.69 | N6: ='Revenue Schedule'!M68*(1-Assumptions!N71)+'Revenue Schedule'!M80*(1-Assumptions!N72) -> 390738.08 | O6: ='Revenue Schedule'!N68*(1-Assumptions!O71)+'Revenue Schedule'!N80*(1-Assumptions!O72) -> 455499.37 | P6: Forecast = quick commerce revenue x (1 − QC gross margin) + Hyperpure revenue x (1 − HP gross margin). Food delivery and going-out are commission businesses with no cost of goods.
A7: Delivery & related charges | B7: INR Cr | D7: 2537 | E7: 3915 | F7: 5728 | G7: 9065 | H7: =H5*Assumptions!H73 -> 21382.988 | I7: =I5*Assumptions!I73 -> 29149.417 | J7: =J5*Assumptions!J73 -> 38822.74 | K7: =K5*Assumptions!K73 -> 49716.125 | L7: =L5*Assumptions!L73 -> 61595.465 | M7: =M5*Assumptions!M73 -> 74474.999 | N7: =N5*Assumptions!N73 -> 89084.679 | O7: =O5*Assumptions!O73 -> 101472.75
A8: Employee benefits expense (incl. share-based payment) | B8: INR Cr | D8: 1465 | E8: 1659 | F8: 2558 | G8: 3536 | H8: =H5*Assumptions!H74 -> 7751.3333 | I8: =I5*Assumptions!I74 -> 10025.914 | J8: =J5*Assumptions!J74 -> 12604.786 | K8: =K5*Assumptions!K74 -> 15474.555 | L8: =L5*Assumptions!L74 -> 18728.351 | M8: =M5*Assumptions!M74 -> 22085.689 | N8: =N5*Assumptions!N74 -> 26164.731 | O8: =O5*Assumptions!O74 -> 29717.018
A9: of which: salaries, wages & bonus (excl. ESOP) | B9: INR Cr | D9: =IFERROR(D8-D10,"") -> 1465 | E9: =IFERROR(E8-E10,"") -> 1144 | F9: =IFERROR(F8-F10,"") -> 1760 | G9: =IFERROR(G8-G10,"") -> 2717 | H9: =IFERROR(H8-H10,"") -> 6901.3333 | I9: =IFERROR(I8-I10,"") -> 9145.914 | J9: =IFERROR(J8-J10,"") -> 11704.786 | K9: =IFERROR(K8-K10,"") -> 14554.555 | ... O9: =IFERROR(O8-O10,"") -> 28717.018
A10: of which: share-based payment (ESOP) | B10: INR Cr | D10: ='ESOP Schedule'!C5 -> 0 | E10: ='ESOP Schedule'!D5 -> 515 | F10: ='ESOP Schedule'!E5 -> 798 | G10: ='ESOP Schedule'!F5 -> 819 | H10: ='ESOP Schedule'!G5 -> 850 | I10: ='ESOP Schedule'!H5 -> 880 | J10: ='ESOP Schedule'!I5 -> 900 | K10: ='ESOP Schedule'!J5 -> 920 | ... O10: ='ESOP Schedule'!N5 -> 1000
A11: Advertisement & sales promotion | B11: INR Cr | D11: 1227 | E11: 1432 | F11: 1972 | G11: 3350 | H11: =H5*Assumptions!H75 -> 7617.6896 | I11: =I5*Assumptions!I75 -> 10025.914 | J11: =J5*Assumptions!J75 -> 12604.786 | K11: =K5*Assumptions!K75 -> 15803.801 | L11: =L5*Assumptions!L75 -> 19144.536 | M11: =M5*Assumptions!M75 -> 22599.31 | N11: =N5*Assumptions!N75 -> 26787.701 | O11: =O5*Assumptions!O75 -> 30441.824
A12: Other expenses (incl. cash lease rent, tech, G&A) — balancing | B12: INR Cr | D12: 1665 | E12: 2184 | F12: 3783 | G12: 7038 | H12: =H5*Assumptions!H77 -> 15595.185 | I12: =I5*Assumptions!I77 -> 19863.772 | J12: =J5*Assumptions!J77 -> 24512.531 | K12: =K5*Assumptions!K77 -> 28796.52 | L12: =L5*Assumptions!L77 -> 32326.617 | M12: =M5*Assumptions!M77 -> 34866.415 | N12: =N5*Assumptions!N77 -> 36190.589 | O12: =O5*Assumptions!O77 -> 38935.248 | P12: Forecast = revenue from operations × Assumptions row 77 (% of revenue driver). No longer a balancing line; EBITDA is now the output of this waterfall.
A13: of which: IT support, server & communication | B13: INR Cr | D13: =IFERROR(D12*Assumptions!D79,"") -> 283.05 | E13: =IFERROR(E12*Assumptions!E79,"") -> 371.28 | F13: =IFERROR(F12*Assumptions!F79,"") -> 643.11 | G13: =IFERROR(G12*Assumptions!G79,"") -> 1196.46 | H13: =IFERROR(H12*Assumptions!H79,"") -> 2651.1814 | I13: =IFERROR(I12*Assumptions!I79,"") -> 3376.8413 | J13: =IFERROR(J12*Assumptions!J79,"") -> 4167.1302 | K13: =IFERROR(K12*Assumptions!K79,"") -> 4895.4084 | ... O13: =IFERROR(O12*Assumptions!O79,"") -> 6618.9922
A14: of which: outsourced support costs | B14: INR Cr | D14: =IFERROR(D12*Assumptions!D80,"") -> 249.75 | E14: =IFERROR(E12*Assumptions!E80,"") -> 327.6 | F14: =IFERROR(F12*Assumptions!F80,"") -> 567.45 | G14: =IFERROR(G12*Assumptions!G80,"") -> 1055.7 | H14: =IFERROR(H12*Assumptions!H80,"") -> 2339.2777 | I14: =IFERROR(I12*Assumptions!I80,"") -> 2979.5658 | J14: =IFERROR(J12*Assumptions!J80,"") -> 3676.8796 | K14: =IFERROR(K12*Assumptions!K80,"") -> 4319.478 | ... O14: =IFERROR(O12*Assumptions!O80,"") -> 5840.2872
A15: of which: payment gateway & related charges | B15: INR Cr | D15: =IFERROR(D12*Assumptions!D81,"") -> 199.8 | E15: =IFERROR(E12*Assumptions!E81,"") -> 262.08 | F15: =IFERROR(F12*Assumptions!F81,"") -> 453.96 | G15: =IFERROR(G12*Assumptions!G81,"") -> 844.56 | H15: =IFERROR(H12*Assumptions!H81,"") -> 1871.4222 | I15: =IFERROR(I12*Assumptions!I81,"") -> 2383.6527 | J15: =IFERROR(J12*Assumptions!J81,"") -> 2941.5037 | K15: =IFERROR(K12*Assumptions!K81,"") -> 3455.5824 | ... O15: =IFERROR(O12*Assumptions!O81,"") -> 4672.2298
A16: of which: rent, rates & taxes | B16: INR Cr | D16: =IFERROR(D12*Assumptions!D82,"") -> 133.2 | E16: =IFERROR(E12*Assumptions!E82,"") -> 174.72 | F16: =IFERROR(F12*Assumptions!F82,"") -> 302.64 | G16: =IFERROR(G12*Assumptions!G82,"") -> 563.04 | H16: =IFERROR(H12*Assumptions!H82,"") -> 1247.6148 | I16: =IFERROR(I12*Assumptions!I82,"") -> 1589.1018 | J16: =IFERROR(J12*Assumptions!J82,"") -> 1961.0024 | K16: =IFERROR(K12*Assumptions!K82,"") -> 2303.7216 | ... O16: =IFERROR(O12*Assumptions!O82,"") -> 3114.8199
A17: of which: other (residual) | B17: INR Cr | D17: =IFERROR(D12-SUM(D13:D16),"") -> 799.2 | E17: =IFERROR(E12-SUM(E13:E16),"") -> 1048.32 | F17: =IFERROR(F12-SUM(F13:F16),"") -> 1815.84 | G17: =IFERROR(G12-SUM(G13:G16),"") -> 3378.24 | H17: =IFERROR(H12-SUM(H13:H16),"") -> 7485.6887 | I17: =IFERROR(I12-SUM(I13:I16),"") -> 9534.6106 | J17: =IFERROR(J12-SUM(J13:J16),"") -> 11766.015 | K17: =IFERROR(K12-SUM(K13:K16),"") -> 13822.329 | ... O17: =IFERROR(O12-SUM(O13:O16),"") -> 18688.919
A19: TOTAL OPERATING EXPENSES | B19: INR Cr | D19: =D6+D7+D8+D11+D12 -> 8289 | E19: =E6+E7+E8+E11+E12 -> 12072 | F19: =F6+F7+F8+F11+F12 -> 19606 | G19: =G6+G7+G8+G11+G12 -> 53156 | H19: =H6+H7+H8+H11+H12 -> 135837.74 | I19: =I6+I7+I8+I11+I12 -> 185114.91 | J19: =J6+J7+J8+J11+J12 -> 246696.59 | K19: =K6+K7+K8+K11+K12 -> 316271.48 | ... O19: =O6+O7+O8+O11+O12 -> 656066.2
A20: EBITDA (reported basis) — check vs IS row 35 | B20: INR Cr | D20: =D5-D19 -> -1210 | E20: =E5-E19 -> 42 | F20: =F5-F19 -> 637 | G20: =G5-G19 -> 1208 | H20: =H5-H19 -> -5291.141 | I20: =I5-I19 -> -3645.4179 | J20: =J5-J19 -> -242.08899 | K20: =K5-K19 -> 5618.783 | ... O20: =O5-O19 -> 51847.403
A21: Check: waterfall EBITDA vs IS EBITDA (must be nil; fails if any IS line link breaks) | B21: INR Cr | D21: =ROUND(D20-IS!D16,2) -> 0 | E21: =ROUND(E20-IS!E16,2) -> 0 | F21: =ROUND(F20-IS!F16,2) -> 0 | G21: =ROUND(G20-IS!G16,2) -> 0 | H21: =ROUND(H20-IS!H16,2) -> 0 | I21: =ROUND(I20-IS!I16,2) -> 0 | J21: =ROUND(J20-IS!J16,2) -> 0 | K21: =ROUND(K20-IS!K16,2) -> 0 | ... O21: =ROUND(O20-IS!O16,2) -> 0 | P21: Historical difference reflects reported revenue vs adjusted revenue (delivery charges and platform fees added back in the adjusted measure).
A23: B. COST WATERFALL AS % OF REVENUE FROM OPERATIONS
A24: Cost of goods sold | B24: % | D24: =D6/D5 -> 0.19706173 | E24: =E6/E5 -> 0.23790655 | F24: =F6/F5 -> 0.27490985 | G24: =G6/G5 -> 0.55490766 | H24: =H6/H5 -> 0.63954592 | I24: =I6/I5 -> 0.63950084 | J24: =J6/J5 -> 0.64170769 | K24: =K6/K5 -> 0.64146234 | ... O24: =O6/O5 -> 0.6434392
A25: Delivery & related charges | B25: % | D25: =D7/D5 -> 0.35838395 | E25: =E7/E5 -> 0.32317979 | F25: =F7/F5 -> 0.28296201 | G25: =G7/G5 -> 0.16674638 | H25: =H7/H5 -> 0.16379582 | I25: =I7/I5 -> 0.16062985 | J25: =J7/J5 -> 0.15752498 | K25: =K7/K5 -> 0.15445054 | ... O25: =O7/O5 -> 0.14334058
A26: Employee benefits | B26: % | D26: =D8/D5 -> 0.20695013 | E26: =E8/E5 -> 0.13694898 | F26: =F8/F5 -> 0.12636467 | G26: =G8/G5 -> 0.065043043 | H26: =H8/H5 -> 0.059375986 | I26: =I8/I5 -> 0.055248483 | J26: =J8/J5 -> 0.051144473 | K26: =K8/K5 -> 0.048074009 | ... O26: =O8/O5 -> 0.041978312
A27: Advertisement & sales promotion | B27: % | D27: =D11/D5 -> 0.17332957 | E27: =E11/E5 -> 0.11821034 | F27: =F11/F5 -> 0.097416391 | G27: =G11/G5 -> 0.061621661 | H27: =H11/H5 -> 0.058352262 | I27: =I11/I5 -> 0.055248483 | J27: =J11/J5 -> 0.051144473 | K27: =K11/K5 -> 0.04909686 | ... O27: =O11/O5 -> 0.043002173
A28: Other expenses | B28: % | D28: =D12/D5 -> 0.23520271 | E28: =E12/E5 -> 0.18028727 | F28: =F12/F5 -> 0.18687942 | G28: =G12/G5 -> 0.12946067 | H28: =H12/H5 -> 0.11946067 | I28: =I12/I5 -> 0.10946067 | J28: =J12/J5 -> 0.099460673 | K28: =K12/K5 -> 0.089460673 | ... O28: =O12/O5 -> 0.055
A30: TOTAL OPEX % of revenue from operations | B30: % | D30: =D19/D5 -> 1.1709281 | E30: =E19/E5 -> 0.99653294 | F30: =F19/F5 -> 0.96853233 | G30: =G19/G5 -> 0.97777941 | H30: =H19/H5 -> 1.0405307 | I30: =I19/I5 -> 1.0200883 | J30: =J19/J5 -> 1.0009823 | K30: =K19/K5 -> 0.98254441 | ... O30: =O19/O5 -> 0.92676027
A31: EBITDA margin (% of revenue from operations) | B31: % | D31: =D20/D5 -> -0.1709281 | E31: =E20/E5 -> 0.0034670629 | F31: =F20/F5 -> 0.031467668 | G31: =G20/G5 -> 0.022220587 | H31: =H20/H5 -> -0.040530668 | I31: =I20/I5 -> -0.020088324 | J31: =J20/J5 -> -0.00098228675 | K31: =K20/K5 -> 0.017455585 | ... O31: =O20/O5 -> 0.073239733
A34: C. DETAIL ANALYSIS — gross margin & operating leverage
A36: Gross profit ( Operational revenue − COGS) | B36: INR Cr | D36: =D5-D6 -> 5684 | E36: =E5-E6 -> 9232 | F36: =F5-F6 -> 14678 | G36: =G5-G6 -> 24197 | H36: =H5-H6 -> 47056.055 | I36: =I5-I6 -> 65419.599 | J36: =J5-J6 -> 88302.753 | K36: =K5-K6 -> 115409.78 | ... O36: =O5-O6 -> 252414.24
A37: Gross margin | B37: % | D37: =D36/D5 -> 0.80293827 | E37: =E36/E5 -> 0.76209345 | F37: =F36/F5 -> 0.72509015 | G37: =G36/G5 -> 0.44509234 | H37: =H36/H5 -> 0.36045408 | I37: =I36/I5 -> 0.36049916 | J37: =J36/J5 -> 0.35829231 | K37: =K36/K5 -> 0.35853766 | ... O37: =O36/O5 -> 0.3565608
A39: Contribution after delivery costs | B39: INR Cr | D39: =D36-D7 -> 3147 | E39: =E36-E7 -> 5317 | F39: =F36-F7 -> 8950 | G39: =G36-G7 -> 15132 | H39: =H36-H7 -> 25673.067 | I39: =I36-I7 -> 36270.182 | J39: =J36-J7 -> 49480.013 | K39: =K36-K7 -> 65693.659 | ... O39: =O36-O7 -> 150941.49
A40: as % of revenue from operations | B40: % | D40: =D39/D5 -> 0.44455432 | E40: =E39/E5 -> 0.43891365 | F40: =F39/F5 -> 0.44212814 | G40: =G39/G5 -> 0.27834596 | H40: =H39/H5 -> 0.19665825 | I40: =I39/I5 -> 0.19986932 | J40: =J39/J5 -> 0.20076733 | K40: =K39/K5 -> 0.20408713 | ... O40: =O39/O5 -> 0.21322022
A42: Fixed-cost base (employee + advertising + other) | B42: INR Cr | D42: =D8+D11+D12 -> 4357 | E42: =E8+E11+E12 -> 5275 | F42: =F8+F11+F12 -> 8313 | G42: =G8+G11+G12 -> 13924 | H42: =H8+H11+H12 -> 30964.208 | I42: =I8+I11+I12 -> 39915.6 | J42: =J8+J11+J12 -> 49722.102 | K42: =K8+K11+K12 -> 60074.876 | ... O42: =O8+O11+O12 -> 99094.09
A43: as % of revenue from operations | B43: % | D43: =D42/D5 -> 0.61548241 | E43: =E42/E5 -> 0.43544659 | F43: =F42/F5 -> 0.41066048 | G43: =G42/G5 -> 0.25612538 | H43: =H42/H5 -> 0.23718892 | I43: =I42/I5 -> 0.21995764 | J43: =J42/J5 -> 0.20174962 | K43: =K42/K5 -> 0.18663154 | ... O43: =O42/O5 -> 0.13998049
A45: Incremental EBITDA margin (ΔEBITDA / Δrevenue) | B45: % | E45: =(E20-D20)/(E5-D5) -> 0.24865938 | F45: =(F20-E20)/(F5-E5) -> 0.073194735 | G45: =(G20-F20)/(G5-F5) -> 0.016734562 | H45: =(H20-G20)/(H5-G5) -> -0.085310042 | I45: =(I20-H20)/(I5-H5) -> 0.032317946 | J45: =(J20-I20)/(J5-I5) -> 0.05237098 | K45: =(K20-J20)/(K5-J5) -> 0.077693546 | L45: =(L20-K20)/(L5-K5) -> 0.10207586 | ... O45: =(O20-N20)/(O5-N5) -> 0.12255637 | P45: The single most important operating-leverage statistic: how much of each incremental rupee of revenue drops to EBITDA.
A48: READ-THROUGH
A49: 1. The FY26 cost structure is not comparable to FY25. Moving Blinkit to an inventory-led (1P) model pulled the full value of goods sold into both revenue and cost — COGS jumped from 26% to 54% of adjusted revenue with no change in underlying economics.
A50: 2. Because of that, gross margin is now the number to watch, not EBITDA margin on revenue. Blinkit's gross profit ran at 26.9% of NOV in Q4FY26 (29% of segment revenue); private label, ad income and Hyperpure sourcing are the levers.
A51: 3. Delivery & related charges (16% of adjusted revenue) are the largest controllable cost. Batching, store density and shorter trip distances are what convert NOV growth into margin.
A52: 4. The fixed-cost base (people, marketing, G&A) is where operating leverage lives. Holding it roughly flat in rupee terms while NOV compounds 25-30% is the entire path to the $1bn Adjusted EBITDA ambition.
A53: 5. Employee costs include share-based payment of INR 819 Cr in FY26 — real dilution, non-cash expense. Adjusted EBITDA adds it back; the DCF does not credit it as cash, and the share count should be watched for creep.

Sheet IS
A1: INCOME STATEMENT — Eternal Limited, consolidated (INR Cr) | Q1: Source (linked to Data_Sources)
A2: Line item | B2: Unit | D2: FY2023A | E2: FY2024A | F2: FY2025A | G2: FY2026A | H2: FY2027E | I2: FY2028E | J2: FY2029E | K2: FY2030E | L2: FY2031E | M2: FY2032E | N2: FY2033E | O2: FY2034E | P2: Source / Note
A5: A. REPORTED P&L (IND AS) | Q5: =Data_Sources!$D$30&" | "&Data_Sources!$E$30&" | "&Data_Sources!$F$30 -> Eternal Q4FY26 audited consolidated P&L | Annexure D — expenses | https://b.zmtcdn.com/investor-relations/Eternal_Shareholders_Letter_Q4FY26_Results.pdf
A6: Revenue from operations | B6: INR Cr | D6: ='Revenue Schedule'!C31 -> 7079 | E6: ='Revenue Schedule'!D31 -> 12114 | F6: ='Revenue Schedule'!E31 -> 20243 | G6: ='Revenue Schedule'!F31 -> 54364 | H6: ='Revenue Schedule'!G31 -> 130546.6 | I6: ='Revenue Schedule'!H31 -> 181469.49 | J6: ='Revenue Schedule'!I31 -> 246454.5 | K6: ='Revenue Schedule'!J31 -> 321890.27 | ... O6: ='Revenue Schedule'!N31 -> 707913.6
A7: Less: Cost of goods sold | B7: INR Cr | D7: =-'Cost Schedule'!D6 -> -1395 | E7: =-'Cost Schedule'!E6 -> -2882 | F7: =-'Cost Schedule'!F6 -> -5565 | G7: =-'Cost Schedule'!G6 -> -30167 | H7: =-'Cost Schedule'!H6 -> -83490.547 | I7: =-'Cost Schedule'!I6 -> -116049.89 | J7: =-'Cost Schedule'!J6 -> -158151.75 | K7: =-'Cost Schedule'!K6 -> -206480.48 | ... O7: =-'Cost Schedule'!O6 -> -455499.37
A9: GROSS PROFIT | B9: INR Cr | D9: =D6+D7 -> 5684 | E9: =E6+E7 -> 9232 | F9: =F6+F7 -> 14678 | G9: =G6+G7 -> 24197 | H9: =H6+H7 -> 47056.055 | I9: =I6+I7 -> 65419.599 | J9: =J6+J7 -> 88302.753 | K9: =K6+K7 -> 115409.78 | ... O9: =O6+O7 -> 252414.24
A10: Gross margin (% of revenue) | B10: % | D10: =IFERROR(D9/D6,"") -> 0.80293827 | E10: =IFERROR(E9/E6,"") -> 0.76209345 | F10: =IFERROR(F9/F6,"") -> 0.72509015 | G10: =IFERROR(G9/G6,"") -> 0.44509234 | H10: =IFERROR(H9/H6,"") -> 0.36045408 | I10: =IFERROR(I9/I6,"") -> 0.36049916 | J10: =IFERROR(J9/J6,"") -> 0.35829231 | K10: =IFERROR(K9/K6,"") -> 0.35853766 | ... O10: =IFERROR(O9/O6,"") -> 0.3565608
A11: Less: Employee benefits expense (incl. ESOP) | B11: INR Cr | D11: =-'Cost Schedule'!D8 -> -1465 | E11: =-'Cost Schedule'!E8 -> -1659 | F11: =-'Cost Schedule'!F8 -> -2558 | G11: =-'Cost Schedule'!G8 -> -3536 | H11: =-'Cost Schedule'!H8 -> -7751.3333 | I11: =-'Cost Schedule'!I8 -> -10025.914 | J11: =-'Cost Schedule'!J8 -> -12604.786 | K11: =-'Cost Schedule'!K8 -> -15474.555 | ... O11: =-'Cost Schedule'!O8 -> -29717.018
A12: Less: Delivery & related charges | B12: INR Cr | D12: =-'Cost Schedule'!D7 -> -2537 | E12: =-'Cost Schedule'!E7 -> -3915 | F12: =-'Cost Schedule'!F7 -> -5728 | G12: =-'Cost Schedule'!G7 -> -9065 | H12: =-'Cost Schedule'!H7 -> -21382.988 | I12: =-'Cost Schedule'!I7 -> -29149.417 | J12: =-'Cost Schedule'!J7 -> -38822.74 | K12: =-'Cost Schedule'!K7 -> -49716.125 | ... O12: =-'Cost Schedule'!O7 -> -101472.75
A13: Less: Advertisement & sales promotion | B13: INR Cr | D13: =-'Cost Schedule'!D11 -> -1227 | E13: =-'Cost Schedule'!E11 -> -1432 | F13: =-'Cost Schedule'!F11 -> -1972 | G13: =-'Cost Schedule'!G11 -> -3350 | H13: =-'Cost Schedule'!H11 -> -7617.6896 | I13: =-'Cost Schedule'!I11 -> -10025.914 | J13: =-'Cost Schedule'!J11 -> -12604.786 | K13: =-'Cost Schedule'!K11 -> -15803.801 | ... O13: =-'Cost Schedule'!O11 -> -30441.824
A14: Less: Other expenses (incl. cash lease rent, tech, G&A) | B14: INR Cr | D14: =-'Cost Schedule'!D12 -> -1665 | E14: =-'Cost Schedule'!E12 -> -2184 | F14: =-'Cost Schedule'!F12 -> -3783 | G14: =-'Cost Schedule'!G12 -> -7038 | H14: =-'Cost Schedule'!H12 -> -15595.185 | I14: =-'Cost Schedule'!I12 -> -19863.772 | J14: =-'Cost Schedule'!J12 -> -24512.531 | K14: =-'Cost Schedule'!K12 -> -28796.52 | ... O14: =-'Cost Schedule'!O12 -> -38935.248
A16: EBITDA (reported) | B16: INR Cr | D16: =SUM(D9,D11:D14) -> -1210 | E16: =SUM(E9,E11:E14) -> 42 | F16: =SUM(F9,F11:F14) -> 637 | G16: =SUM(G9,G11:G14) -> 1208 | H16: =SUM(H9,H11:H14) -> -5291.141 | I16: =SUM(I9,I11:I14) -> -3645.4179 | J16: =SUM(J9,J11:J14) -> -242.08899 | K16: =SUM(K9,K11:K14) -> 5618.783 | ... O16: =SUM(O9,O11:O14) -> 51847.403
A17: EBITDA margin (% of revenue) | B17: % | D17: =IFERROR(D16/D6,"") -> -0.1709281 | E17: =IFERROR(E16/E6,"") -> 0.0034670629 | F17: =IFERROR(F16/F6,"") -> 0.031467668 | G17: =IFERROR(G16/G6,"") -> 0.022220587 | H17: =IFERROR(H16/H6,"") -> -0.040530668 | I17: =IFERROR(I16/I6,"") -> -0.020088324 | J17: =IFERROR(J16/J6,"") -> -0.00098228675 | K17: =IFERROR(K16/K6,"") -> 0.017455585 | ... O17: =IFERROR(O16/O6,"") -> 0.073239733
A18: Check: IS EBITDA vs Cost Schedule waterfall (must be nil) | B18: INR Cr | D18: =ROUND(D16-'Cost Schedule'!D20,2) -> 0 | E18: =ROUND(E16-'Cost Schedule'!E20,2) -> 0 | F18: =ROUND(F16-'Cost Schedule'!F20,2) -> 0 | G18: =ROUND(G16-'Cost Schedule'!G20,2) -> 0 | H18: =ROUND(H16-'Cost Schedule'!H20,2) -> 0 | I18: =ROUND(I16-'Cost Schedule'!I20,2) -> 0 | J18: =ROUND(J16-'Cost Schedule'!J20,2) -> 0 | K18: =ROUND(K16-'Cost Schedule'!K20,2) -> 0 | ... O18: =ROUND(O16-'Cost Schedule'!O20,2) -> 0
A19: Less: Depreciation & amortisation | B19: INR Cr | D19: =-FA_Schedule!C37 -> -437 | E19: =-FA_Schedule!D37 -> -526 | F19: =-FA_Schedule!E37 -> -863 | G19: =-FA_Schedule!F37 -> -1597 | H19: =-FA_Schedule!G37 -> -2838.1476 | I19: =-FA_Schedule!H37 -> -4122.4038 | J19: =-FA_Schedule!I37 -> -5286.4737 | K19: =-FA_Schedule!J37 -> -6369.0036 | ... O19: =-FA_Schedule!N37 -> -9782.1131
A21: EBIT | B21: INR Cr | D21: =D16+D19 -> -1647 | E21: =E16+E19 -> -484 | F21: =F16+F19 -> -226 | G21: =G16+G19 -> -389 | H21: =H16+H19 -> -8129.2886 | I21: =I16+I19 -> -7767.8217 | J21: =J16+J19 -> -5528.5627 | K21: =K16+K19 -> -750.2206 | ... O21: =O16+O19 -> 42065.29
A22: EBIT margin (% of revenue) | B22: % | D22: =IFERROR(D21/D6,"") -> -0.23265998 | E22: =IFERROR(E21/E6,"") -> -0.039953772 | F22: =IFERROR(F21/F6,"") -> -0.011164353 | G22: =IFERROR(G21/G6,"") -> -0.0071554705 | H22: =IFERROR(H21/H6,"") -> -0.062271162 | I22: =IFERROR(I21/I6,"") -> -0.042805112 | J22: =IFERROR(J21/J6,"") -> -0.022432387 | K22: =IFERROR(K21/K6,"") -> -0.0023306719 | ... O22: =IFERROR(O21/O6,"") -> 0.059421503
A23: Add: Other income (treasury & investments) | B23: INR Cr | D23: ='Other Income Schedule '!D12 -> 682 | E23: ='Other Income Schedule '!E12 -> 847 | F23: ='Other Income Schedule '!F12 -> 1077 | G23: ='Other Income Schedule '!G12 -> 1396 | H23: ='Other Income Schedule '!H12 -> 1168.18 | I23: ='Other Income Schedule '!I12 -> 366.44605 | J23: ='Other Income Schedule '!J12 -> -349.60919 | K23: ='Other Income Schedule '!K12 -> -896.76274 | ... O23: ='Other Income Schedule '!O12 -> 451.11302
A24: Less: Finance costs | B24: INR Cr | D24: =-Lease_Schedule!D25 -> -49 | E24: =-Lease_Schedule!E25 -> -72 | F24: =-Lease_Schedule!F25 -> -154 | G24: =-Lease_Schedule!G25 -> -392 | H24: =-Lease_Schedule!H25 -> -495.51725 | I24: =-Lease_Schedule!I25 -> -826.30888 | J24: =-Lease_Schedule!J25 -> -1182.2817 | K24: =-Lease_Schedule!K25 -> -1555.4344 | ... O24: =-Lease_Schedule!O25 -> -2850.3063
A26: PROFIT BEFORE TAX | B26: INR Cr | D26: =SUM(D21,D23:D24) -> -1014 | E26: =SUM(E21,E23:E24) -> 291 | F26: =SUM(F21,F23:F24) -> 697 | G26: =SUM(G21,G23:G24) -> 615 | H26: =SUM(H21,H23:H24) -> -7456.6258 | I26: =SUM(I21,I23:I24) -> -8227.6845 | J26: =SUM(J21,J23:J24) -> -7060.4536 | K26: =SUM(K21,K23:K24) -> -3202.4177 | ... O26: =SUM(O21,O23:O24) -> 39666.097
A27: Less: Tax expense | B27: INR Cr | D27: 44 | E27: 60 | F27: -170 | G27: -249 | H27: =Tax_Schedule!H11 -> 0 | I27: =Tax_Schedule!I11 -> 0 | J27: =Tax_Schedule!J11 -> 0 | K27: =Tax_Schedule!K11 -> 0 | L27: =Tax_Schedule!L11 -> 0 | M27: =Tax_Schedule!M11 -> 0 | N27: =Tax_Schedule!N11 -> -4474.9843 | O27: =Tax_Schedule!O11 -> -9983.9566
A29: PROFIT AFTER TAX (PAT) | B29: INR Cr | D29: =D26+D27 -> -970 | E29: =E26+E27 -> 351 | F29: =F26+F27 -> 527 | G29: =G26+G27 -> 366 | H29: =H26+H27 -> -7456.6258 | I29: =I26+I27 -> -8227.6845 | J29: =J26+J27 -> -7060.4536 | K29: =K26+K27 -> -3202.4177 | ... O29: =O26+O27 -> 29682.14
A30: PAT margin (% of revenue) | B30: % | D30: =IFERROR(D29/D6,"") -> -0.137025 | E30: =IFERROR(E29/E6,"") -> 0.02897474 | F30: =IFERROR(F29/F6,"") -> 0.026033691 | G30: =IFERROR(G29/G6,"") -> 0.0067323964 | H30: =IFERROR(H29/H6,"") -> -0.057118498 | I30: =IFERROR(I29/I6,"") -> -0.045339217 | J30: =IFERROR(J29/J6,"") -> -0.028648101 | K30: =IFERROR(K29/K6,"") -> -0.009948787 | ... O30: =IFERROR(O29/O6,"") -> 0.041929044
A31: Earnings per share (basic) | B31: INR | D31: =IFERROR(D29/Assumptions!$B$141,"") -> -1.0554951 | E31: =IFERROR(E29/Assumptions!$B$141,"") -> 0.38193689 | F31: =IFERROR(F29/Assumptions!$B$141,"") -> 0.5734494 | G31: =IFERROR(G29/Assumptions!$B$141,"") -> 0.39825898 | H31: =IFERROR(H29/Assumptions!$B$141,"") -> -8.1138475 | I31: =IFERROR(I29/Assumptions!$B$141,"") -> -8.9528667 | J31: =IFERROR(J29/Assumptions!$B$141,"") -> -7.6827569 | K31: =IFERROR(K29/Assumptions!$B$141,"") -> -3.4846765 | ... O31: =IFERROR(O29/Assumptions!$B$141,"") -> 32.298303
A33: B. PRE-IND AS 116 EBITDA BRIDGE
A34: Reported EBITDA (Ind AS 116) | B34: INR Cr | D34: =D16 -> -1210 | E34: =E16 -> 42 | F34: =F16 -> 637 | G34: =G16 -> 1208 | H34: =H16 -> -5291.141 | I34: =I16 -> -3645.4179 | J34: =J16 -> -242.08899 | K34: =K16 -> 5618.783 | ... O34: =O16 -> 51847.403
A35: Less: Lease principal repaid | B35: INR Cr | D35: =IFERROR(-Lease_Schedule!D22,"") -> 0 | E35: =IFERROR(-Lease_Schedule!E22,"") -> -185 | F35: =IFERROR(-Lease_Schedule!F22,"") -> -209 | G35: =IFERROR(-Lease_Schedule!G22,"") -> -471 | H35: =IFERROR(-Lease_Schedule!H22,"") -> -891.48275 | I35: =IFERROR(-Lease_Schedule!I22,"") -> -1229.6911 | J35: =IFERROR(-Lease_Schedule!J22,"") -> -1660.7183 | K35: =IFERROR(-Lease_Schedule!K22,"") -> -2205.5656 | ... O35: =IFERROR(-Lease_Schedule!O22,"") -> -5913.6937
A36: Less: Lease interest paid | B36: INR Cr | D36: =IFERROR(-Lease_Schedule!D21,"") -> 0 | E36: =IFERROR(-Lease_Schedule!E21,"") | F36: =IFERROR(-Lease_Schedule!F21,"") -> -147 | G36: =IFERROR(-Lease_Schedule!G21,"") -> -367 | H36: =IFERROR(-Lease_Schedule!H21,"") -> -495.51725 | I36: =IFERROR(-Lease_Schedule!I21,"") -> -826.30888 | J36: =IFERROR(-Lease_Schedule!J21,"") -> -1182.2817 | K36: =IFERROR(-Lease_Schedule!K21,"") -> -1555.4344 | ... O36: =IFERROR(-Lease_Schedule!O21,"") -> -2850.3063
A37: Total fixed lease rent (effective cash rent) | B37: INR Cr | D37: =SUM(D35:D36) -> 0 | E37: =SUM(E35:E36) -> -185 | F37: =SUM(F35:F36) -> -356 | G37: =SUM(G35:G36) -> -838 | H37: =SUM(H35:H36) -> -1387 | I37: =SUM(I35:I36) -> -2056 | J37: =SUM(J35:J36) -> -2843 | K37: =SUM(K35:K36) -> -3761 | ... O37: =SUM(O35:O36) -> -8764
A38: Effective rent as % of revenue from operations | B38: % | D38: =IFERROR(-D37/D6,"") -> 0 | E38: =IFERROR(-E37/E6,"") -> 0.015271587 | F38: =IFERROR(-F37/F6,"") -> 0.017586326 | G38: =IFERROR(-G37/G6,"") -> 0.015414613 | H38: =IFERROR(-H37/H6,"") -> 0.010624558 | I38: =IFERROR(-I37/I6,"") -> 0.011329728 | J38: =IFERROR(-J37/J6,"") -> 0.011535598 | K38: =IFERROR(-K37/K6,"") -> 0.011684106 | ... O38: =IFERROR(-O37/O6,"") -> 0.012380042
A39: PRE-IND AS 116 EBITDA | B39: INR Cr | D39: =D34+D37 -> -1210 | E39: =E34+E37 -> -143 | F39: =F34+F37 -> 281 | G39: =G34+G37 -> 370 | H39: =H34+H37 -> -6678.141 | I39: =I34+I37 -> -5701.4179 | J39: =J34+J37 -> -3085.089 | K39: =K34+K37 -> 1857.783 | ... O39: =O34+O37 -> 43083.403
A40: Pre-Ind AS 116 EBITDA margin (%) | B40: % | D40: =IFERROR(D39/D6,"") -> -0.1709281 | E40: =IFERROR(E39/E6,"") -> -0.011804524 | F40: =IFERROR(F39/F6,"") -> 0.013881342 | G40: =IFERROR(G39/G6,"") -> 0.0068059745 | H40: =IFERROR(H39/H6,"") -> -0.051155226 | I40: =IFERROR(I39/I6,"") -> -0.031418052 | J40: =IFERROR(J39/J6,"") -> -0.012517884 | K40: =IFERROR(K39/K6,"") -> 0.0057714791 | ... O40: =IFERROR(O39/O6,"") -> 0.060859691
A42: C. ADJUSTED EBITDA BY SEGMENT | Q42: =Data_Sources!$D$15&" | "&Data_Sources!$E$15&" | "&Data_Sources!$F$15 -> Eternal Q4FY26 shareholders' letter | Annexure A & B (reconciliation to reported P&L) | https://b.zmtcdn.com/investor-relations/Eternal_Shareholders_Letter_Q4FY26_Results.pdf
A43: Food delivery (Zomato) | B43: INR Cr | D43: -10 | E43: 912 | F43: 1505 | G43: 2017 | H43: ='Revenue Schedule'!G42*Assumptions!H49 -> 2519.7178 | I43: ='Revenue Schedule'!H42*Assumptions!I49 -> 3091.5276 | J43: ='Revenue Schedule'!I42*Assumptions!J49 -> 3787.1226 | K43: ='Revenue Schedule'!J42*Assumptions!K49 -> 4484.7552 | L43: ='Revenue Schedule'!K42*Assumptions!L49 -> 5266.8864 | M43: ='Revenue Schedule'!L42*Assumptions!M49 -> 6183.72 | N43: ='Revenue Schedule'!M42*Assumptions!N49 -> 7262.4162 | O43: ='Revenue Schedule'!N42*Assumptions!O49 -> 8526.7728
A44: Quick commerce (Blinkit) | B44: INR Cr | D44: -562 | E44: -384 | F44: -292 | G44: -277 | H44: ='Revenue Schedule'!G56*Assumptions!H50 -> 611.667 | I44: ='Revenue Schedule'!H56*Assumptions!I50 -> 2590.551 | J44: ='Revenue Schedule'!I56*Assumptions!J50 -> 5923.2656 | K44: ='Revenue Schedule'!J56*Assumptions!K50 -> 10866.287 | L44: ='Revenue Schedule'!K56*Assumptions!L50 -> 17668.044 | M44: ='Revenue Schedule'!L56*Assumptions!M50 -> 24126.865 | N44: ='Revenue Schedule'!M56*Assumptions!N50 -> 31926.477 | O44: ='Revenue Schedule'!N56*Assumptions!O50 -> 39830.296
A45: Going-out (District) | B45: INR Cr | D45: - | E45: -6 | F45: -38 | G45: -319 | H45: ='Revenue Schedule'!G72*Assumptions!H51 -> -296.0685 | I45: ='Revenue Schedule'!H72*Assumptions!I51 -> -178.95696 | J45: ='Revenue Schedule'!I72*Assumptions!J51 -> 590.55797 | K45: ='Revenue Schedule'!J72*Assumptions!K51 -> 1535.4507 | L45: ='Revenue Schedule'!K72*Assumptions!L51 -> 1919.3134 | M45: ='Revenue Schedule'!L72*Assumptions!M51 -> 2399.1417 | N45: ='Revenue Schedule'!M72*Assumptions!N51 -> 2998.9272 | O45: ='Revenue Schedule'!N72*Assumptions!O51 -> 3748.659
A46: B2B supplies (Hyperpure) | B46: INR Cr | D46: -194 | E46: -126 | F46: -84 | G46: -17 | H46: ='Revenue Schedule'!G80*Assumptions!H52 -> 78.162 | I46: ='Revenue Schedule'!H80*Assumptions!I52 -> 218.8536 | J46: ='Revenue Schedule'!I80*Assumptions!J52 -> 459.59256 | K46: ='Revenue Schedule'!J80*Assumptions!K52 -> 714.92176 | L46: ='Revenue Schedule'!K80*Assumptions!L52 -> 1000.8905 | M46: ='Revenue Schedule'!L80*Assumptions!M52 -> 1401.2466 | N46: ='Revenue Schedule'!M80*Assumptions!N52 -> 1961.7453 | O46: ='Revenue Schedule'!N80*Assumptions!O52 -> 2746.4434
A47: Others (incl. Bistro) | B47: INR Cr | D47: -17 | E47: -24 | F47: -12 | G47: -215 | H47: =Assumptions!H53 -> -380 | I47: =Assumptions!I53 -> -300 | J47: =Assumptions!J53 -> -200 | K47: =Assumptions!K53 -> -100 | L47: =Assumptions!L53 -> -50 | M47: =Assumptions!M53 -> 0 | N47: =Assumptions!N53 -> 25 | O47: =Assumptions!O53 -> 50
A48: TOTAL ADJUSTED EBITDA | B48: INR Cr | D48: =SUM(D43:D47) -> -783 | E48: =SUM(E43:E47) -> 372 | F48: =SUM(F43:F47) -> 1079 | G48: =SUM(G43:G47) -> 1189 | H48: =SUM(H43:H47) -> 2533.4783 | I48: =SUM(I43:I47) -> 5421.9752 | J48: =SUM(J43:J47) -> 10560.539 | K48: =SUM(K43:K47) -> 17501.415 | ... O48: =SUM(O43:O47) -> 54902.172
A49: Adjusted EBITDA margin (% of adjusted revenue) | B49: % | D49: =IFERROR(D48/'Revenue Schedule'!C27,"") -> -0.090072472 | E49: =IFERROR(E48/'Revenue Schedule'!D27,"") -> 0.027464009 | F49: =IFERROR(F48/'Revenue Schedule'!E27,"") -> 0.049960643 | G49: =IFERROR(G48/'Revenue Schedule'!F27,"") -> 0.021268984 | H49: =IFERROR(H48/'Revenue Schedule'!G27,"") -> 0.018986696 | I49: =IFERROR(I48/'Revenue Schedule'!H27,"") -> 0.029249174 | J49: =IFERROR(J48/'Revenue Schedule'!I27,"") -> 0.041967978 | K49: =IFERROR(K48/'Revenue Schedule'!J27,"") -> 0.053269462 | ... O49: =IFERROR(O48/'Revenue Schedule'!N27,"") -> 0.076040905
A53: D. BRIDGE — ADJUSTED EBITDA TO EBITDA (IND AS) | Q53: =Data_Sources!$D$8&" | "&Data_Sources!$E$8&" | "&Data_Sources!$F$8 -> Eternal Q4FY26 consolidated statement of cash flows | Adjustments to reconcile PBT | https://b.zmtcdn.com/investor-relations/Eternal_Shareholders_Letter_Q4FY26_Results.pdf
A54: Total adjusted EBITDA | B54: INR Cr | D54: =D48 -> -783 | E54: =E48 -> 372 | F54: =F48 -> 1079 | G54: =G48 -> 1189 | H54: =H48 -> 2533.4783 | I54: =I48 -> 5421.9752 | J54: =J48 -> 10560.539 | K54: =K48 -> 17501.415 | ... O54: =O48 -> 54902.172
A55: Less: Share-based payment expense | B55: INR Cr | D55: =-'ESOP Schedule'!C5 -> 0 | E55: =-'ESOP Schedule'!D5 -> -515 | F55: =-'ESOP Schedule'!E5 -> -798 | G55: =-'ESOP Schedule'!F5 -> -819 | H55: =-'ESOP Schedule'!G5 -> -850 | I55: =-'ESOP Schedule'!H5 -> -880 | J55: =-'ESOP Schedule'!I5 -> -900 | K55: =-'ESOP Schedule'!J5 -> -920 | ... O55: =-'ESOP Schedule'!N5 -> -1000 | P55: FY26A 819 / FY25A 798 per consolidated cash flow statement
A56: Add: Rent paid on Ind AS 116 leases | B56: INR Cr | D56: MANUAL – OPEN | E56: =Lease_Schedule!E23 -> 185 | F56: =Lease_Schedule!F23 -> 356 | G56: =Lease_Schedule!G23 -> 838 | H56: =Lease_Schedule!H23 -> 1387 | I56: =Lease_Schedule!I23 -> 2056 | J56: =Lease_Schedule!J23 -> 2843 | K56: =Lease_Schedule!K23 -> 3761 | L56: =Lease_Schedule!L23 -> 4809 | ... O56: =Lease_Schedule!O23 -> 8764 | P56: FY26A 838 per Annexure B; forecast from Lease_Schedule row 24
A57: Segment-margin EBITDA (reported basis, comparison) | B57: INR Cr | D57: =D54+D55+N(D56) -> -783 | E57: =E54+E55+E56 -> 42 | F57: =F54+F55+F56 -> 637 | G57: =G54+G55+G56 -> 1208 | H57: =H54+H55+H56 -> 3070.4783 | I57: =I54+I55+I56 -> 6597.9752 | J57: =J54+J55+J56 -> 12503.539 | K57: =K54+K55+K56 -> 20342.415 | L57: =L54+L55+L56 -> 29674.134 | ... O57: =O54+O55+O56 -> 62666.172
A58: EBITDA margin (% of revenue from operations) | B58: % | D58: =IFERROR(D57/D6,"") -> -0.11060884 | E58: =IFERROR(E57/E6,"") -> 0.0034670629 | F58: =IFERROR(F57/F6,"") -> 0.031467668 | G58: =IFERROR(G57/G6,"") -> 0.022220587 | H58: =IFERROR(H57/H6,"") -> 0.02352017 | I58: =IFERROR(I57/I6,"") -> 0.036358593 | J58: =IFERROR(J57/J6,"") -> 0.050733659 | K58: =IFERROR(K57/K6,"") -> 0.063196738 | ... O58: =IFERROR(O57/O6,"") -> 0.088522344 | P58: Forecast = treasury yield x opening cash & investments
A59: Comparison: waterfall EBITDA (row 16) less segment-margin EBITDA (row 57) — NOT forced to nil | B59: INR Cr | D59: =D16-D57 -> -427 | E59: =E16-E57 -> 0 | F59: =F16-F57 -> 0 | G59: =G16-G57 -> 0 | H59: =H16-H57 -> -8361.6192 | I59: =I16-I57 -> -10243.393 | J59: =J16-J57 -> -12745.628 | K59: =K16-K57 -> -14723.632 | ... O59: =O16-O57 -> -10818.768 | P59: Positive = cost waterfall more profitable than the guided segment margins; negative = segment guidance requires cost efficiencies the waterfall does not assume. FY23A gap reflects missing FY23 SBP and rent inputs (IS!D56, ESOP Schedule!C5).

Sheet FA_Schedule
A1: FIXED ASSET SCHEDULE — PPE, right-of-use assets, intangibles, D&A and capex (INR Cr) | P1: =Data_Sources!$D$29&" | "&Data_Sources!$E$29&" | "&Data_Sources!$F$29 -> Eternal Q4FY25 and Q4FY26 audited consolidated balance sheets | Annexure E | https://b.zmtcdn.com/investor-relations/Eternal_Shareholders_Letter_Q4FY26_Results.pdf
A2: Line item | B2: Unit | C2: FY2023A | D2: FY2024A | E2: FY2025A | F2: FY2026A | G2: FY2027E | H2: FY2028E | I2: FY2029E | J2: FY2030E | K2: FY2031E | L2: FY2032E | M2: FY2033E | N2: FY2034E | O2: Source / Note
A4: A. PROPERTY, PLANT & EQUIPMENT (incl. CWIP)
A5: Opening net block | B5: INR Cr | D5: =C9 -> 216 | E5: =D9 -> 305 | F5: =E9 -> 1016 | G5: =F9 -> 2169 | H5: =G9 -> 4238.3 | I5: =H9 -> 5941.81 | J5: =I9 -> 7389.267 | K5: =J9 -> 8657.4869 | ... N5: =M9 -> 11329.056
A6: Add: capital expenditure | B6: INR Cr | C6: =C16 -> 0 | D6: =D16 -> 202 | E6: =E16 -> 931 | F6: =F16 -> 1746 | G6: =G16 -> 3200 | H6: =H16 -> 3500 | I6: =I16 -> 3800 | J6: =J16 -> 4100 | ... N6: =N16 -> 4800
A7: Less: depreciation on owned assets | B7: INR Cr | D7: =-(D5+D6-D9) -> -113 | E7: =-(E5+E6-E9) -> -220 | F7: =-(F5+F6-F9) -> -593 | G7: =-AVERAGE(G5,G5+G6)*Assumptions!$B$119 -> -1130.7 | H7: =-AVERAGE(H5,H5+H6)*Assumptions!$B$119 -> -1796.49 | I7: =-AVERAGE(I5,I5+I6)*Assumptions!$B$119 -> -2352.543 | J7: =-AVERAGE(J5,J5+J6)*Assumptions!$B$119 -> -2831.7801 | K7: =-AVERAGE(K5,K5+K6)*Assumptions!$B$119 -> -3238.4961 | L7: =-AVERAGE(L5,L5+L6)*Assumptions!$B$119 -> -3575.6972 | M7: =-AVERAGE(M5,M5+M6)*Assumptions!$B$119 -> -3864.2381 | N7: =-AVERAGE(N5,N5+N6)*Assumptions!$B$119 -> -4118.7167
A9: Closing net PPE + CWIP | B9: INR Cr | C9: 216 | D9: 305 | E9: 1016 | F9: 2169 | G9: =G5+G6+G7 -> 4238.3 | H9: =H5+H6+H7 -> 5941.81 | I9: =I5+I6+I7 -> 7389.267 | J9: =J5+J6+J7 -> 8657.4869 | K9: =K5+K6+K7 -> 9693.9908 | L9: =L5+L6+L7 -> 10568.294 | M9: =M5+M6+M7 -> 11329.056 | N9: =N5+N6+N7 -> 12010.339
A10: Implied depreciation rate (% of average net block) | B10: % | C10: =IFERROR(-C7/AVERAGE(C5,C9),"") -> 0 | D10: =IFERROR(-D7/AVERAGE(D5,D9),"") -> 0.43378119 | E10: =IFERROR(-E7/AVERAGE(E5,E9),"") -> 0.333081 | F10: =IFERROR(-F7/AVERAGE(F5,F9),"") -> 0.37237049 | G10: =IFERROR(-G7/AVERAGE(G5,G9),"") -> 0.35294118 | H10: =IFERROR(-H7/AVERAGE(H5,H9),"") -> 0.35294118 | I10: =IFERROR(-I7/AVERAGE(I5,I9),"") -> 0.35294118 | J10: =IFERROR(-J7/AVERAGE(J5,J9),"") -> 0.35294118 | ... N10: =IFERROR(-N7/AVERAGE(N5,N9),"") -> 0.35294118
A13: E. CAPEX SUMMARY — feeds CFS and DCF | P13: =Data_Sources!$D$27&" | "&Data_Sources!$E$27&" | "&Data_Sources!$F$27 -> Eternal Q4FY26 consolidated statement of cash flows | Adjustments to reconcile profit before tax; owned/ROU split derived from the PPE roll-forward | https://b.zmtcdn.com/investor-relations/Eternal_Shareholders_Letter_Q4FY26_Results.pdf
A14: New dark store capex | B14: INR Cr | G14: =Assumptions!H18*Assumptions!H111 -> 2750 | H14: =Assumptions!I18*Assumptions!I111 -> 3000 | I14: =Assumptions!J18*Assumptions!J111 -> 3250 | J14: =Assumptions!K18*Assumptions!K111 -> 3500 | K14: =Assumptions!L18*Assumptions!L111 -> 3625 | L14: =Assumptions!M18*Assumptions!M111 -> 3750 | M14: =Assumptions!N18*Assumptions!N111 -> 3875 | N14: =Assumptions!O18*Assumptions!O111 -> 4000
A15: Other / maintenance / technology capex | B15: INR Cr | G15: =Assumptions!H112 -> 450 | H15: =Assumptions!I112 -> 500 | I15: =Assumptions!J112 -> 550 | J15: =Assumptions!K112 -> 600 | K15: =Assumptions!L112 -> 650 | L15: =Assumptions!M112 -> 700 | M15: =Assumptions!N112 -> 750 | N15: =Assumptions!O112 -> 800
A16: Total capital expenditure | B16: INR Cr | D16: 202 | E16: 931 | F16: 1746 | G16: =G14+G15 -> 3200 | H16: =H14+H15 -> 3500 | I16: =I14+I15 -> 3800 | J16: =J14+J15 -> 4100 | K16: =K14+K15 -> 4275 | L16: =L14+L15 -> 4450 | M16: =M14+M15 -> 4625 | N16: =N14+N15 -> 4800
A18: B. RIGHT-OF-USE ASSETS (Ind AS 116)
A19: Opening ROU assets | B19: INR Cr | D19: =C24 -> 427 | E19: =D24 -> 690 | F19: =E24 -> 1918 | G19: =F24 -> 4294 | H19: =G24 -> 6860.909 | I19: =H24 -> 9365.0467 | J19: =I24 -> 11836.324 | K19: =J24 -> 14292.956 | ... N19: =M24 -> 20803.884
A20: Add: new leases (dark stores, warehousing, offices) | B20: INR Cr | D20: =D24-D19-D22-D23 -> 439 | E20: =E24-E19-E22-E23 -> 1584 | F20: =F24-F19-F22-F23 -> 3074 | G20: =Assumptions!H18*Assumptions!$B$125 -> 3589.5966 | H20: =Assumptions!I18*Assumptions!$B$125 -> 3915.9236 | I20: =Assumptions!J18*Assumptions!$B$125 -> 4242.2505 | J20: =Assumptions!K18*Assumptions!$B$125 -> 4568.5775 | K20: =Assumptions!L18*Assumptions!$B$125 -> 4731.741 | L20: =Assumptions!M18*Assumptions!$B$125 -> 4894.9045 | M20: =Assumptions!N18*Assumptions!$B$125 -> 5058.0679 | N20: =Assumptions!O18*Assumptions!$B$125 -> 5221.2314
A21: Add: renewals / extensions of existing leases | B21: INR Cr | G21: =Lease_Schedule!H8 -> 459.2 | H21: =Lease_Schedule!I8 -> 765.74739 | I21: =Lease_Schedule!J8 -> 1095.6304 | J21: =Lease_Schedule!K8 -> 1441.4341 | K21: =Lease_Schedule!L8 -> 1793.05 | L21: =Lease_Schedule!M8 -> 2122.254 | M21: =Lease_Schedule!N8 -> 2412.1346 | N21: =Lease_Schedule!O8 -> 2641.4028
A22: Less: ROU depreciation | B22: INR Cr | D22: -176 | E22: =-(E37-E34-E36) -> -356 | F22: -698 | G22: =-AVERAGE(G19,G19+G20+G21)*Assumptions!$B$120 -> -1390.0476 | H22: =-AVERAGE(H19,H19+H20+H21)*Assumptions!$B$120 -> -2024.3838 | I22: =-AVERAGE(I19,I19+I20+I21)*Assumptions!$B$120 -> -2647.4772 | J22: =-AVERAGE(J19,J19+J20+J21)*Assumptions!$B$120 -> -3265.0926 | K22: =-AVERAGE(K19,K19+K20+K21)*Assumptions!$B$120 -> -3862.1774 | L22: =-AVERAGE(L19,L19+L20+L21)*Assumptions!$B$120 -> -4423.2186 | M22: =-AVERAGE(M19,M19+M20+M21)*Assumptions!$B$120 -> -4950.3411 | N22: =-AVERAGE(N19,N19+N20+N21)*Assumptions!$B$120 -> -5441.7442 | O22: Derived, not directly disclosed: total D&A of 526 less depreciation on owned assets of 113 (row 7) less intangible amortisation of 237 (row 21). Eternal does not split D&A by asset class in the shareholders' letters.
A23: Less: terminations / derecognition | B23: INR Cr | G23: =Lease_Schedule!H10 -> -91.84 | H23: =Lease_Schedule!I10 -> -153.14948 | I23: =Lease_Schedule!J10 -> -219.12608 | J23: =Lease_Schedule!K10 -> -288.28682 | K23: =Lease_Schedule!L10 -> -358.61 | L23: =Lease_Schedule!M10 -> -424.4508 | M23: =Lease_Schedule!N10 -> -482.42693 | N23: =Lease_Schedule!O10 -> -528.28056
A24: Closing ROU assets | B24: INR Cr | C24: 427 | D24: 690 | E24: 1918 | F24: 4294 | G24: =G19+G20+G21+G22+G23 -> 6860.909 | H24: =H19+H20+H21+H22+H23 -> 9365.0467 | I24: =I19+I20+I21+I22+I23 -> 11836.324 | J24: =J19+J20+J21+J22+J23 -> 14292.956 | K24: =K19+K20+K21+K22+K23 -> 16596.96 | L24: =L19+L20+L21+L22+L23 -> 18766.449 | M24: =M19+M20+M21+M22+M23 -> 20803.884 | N24: =N19+N20+N21+N22+N23 -> 22696.493
A28: C. GOODWILL & OTHER INTANGIBLES
A29: Opening balance | B29: INR Cr | D29: =C31 -> 5708 | E29: =D31 -> 5471 | F29: =E31 -> 6649 | G29: =F31 -> 6348 | H29: =G31 -> 6030.6 | I29: =H31 -> 5729.07 | J29: =I31 -> 5442.6165 | K29: =J31 -> 5170.4857 | ... N29: =M31 -> 4433.0452
A30: Less: amortisation of intangibles | B30: INR Cr | D30: =D31-D29 -> -237 | E30: -287 | F30: -306 | G30: =-Assumptions!H128 -> -317.4 | H30: =-Assumptions!I128 -> -301.53 | I30: =-Assumptions!J128 -> -286.4535 | J30: =-Assumptions!K128 -> -272.13083 | K30: =-Assumptions!L128 -> -258.52428 | L30: =-Assumptions!M128 -> -245.59807 | M30: =-Assumptions!N128 -> -233.31817 | N30: =-Assumptions!O128 -> -221.65226 | O30: Movement in goodwill and other intangibles. Goodwill was unchanged at 4,717 across FY23 and FY24, so the entire 237 movement is amortisation of other intangible assets (991 to 754), assuming no additions in the year
A31: Closing goodwill & intangibles | B31: INR Cr | C31: 5708 | D31: 5471 | E31: 6649 | F31: 6348 | G31: =G29+G30 -> 6030.6 | H31: =H29+H30 -> 5729.07 | I31: =I29+I30 -> 5442.6165 | J31: =J29+J30 -> 5170.4857 | K31: =K29+K30 -> 4911.9614 | L31: =L29+L30 -> 4666.3633 | M31: =M29+M30 -> 4433.0452 | N31: =N29+N30 -> 4211.3929
A33: D. TOTAL DEPRECIATION & AMORTISATION — feeds IS row 27
A34: Depreciation on owned assets | B34: INR Cr | D34: =-D7 -> 113 | E34: =-E7 -> 220 | F34: =-F7 -> 593 | G34: =-G7 -> 1130.7 | H34: =-H7 -> 1796.49 | I34: =-I7 -> 2352.543 | J34: =-J7 -> 2831.7801 | K34: =-K7 -> 3238.4961 | ... N34: =-N7 -> 4118.7167
A35: ROU asset depreciation | B35: INR Cr | D35: =-D22 -> 176 | E35: =-E22 -> 356 | F35: =-F22 -> 698 | G35: =-G22 -> 1390.0476 | H35: =-H22 -> 2024.3838 | I35: =-I22 -> 2647.4772 | J35: =-J22 -> 3265.0926 | K35: =-K22 -> 3862.1774 | ... N35: =-N22 -> 5441.7442
A36: Amortisation of intangibles | B36: INR Cr | D36: =-D30 -> 237 | E36: =-E30 -> 287 | F36: =-F30 -> 306 | G36: =-G30 -> 317.4 | H36: =-H30 -> 301.53 | I36: =-I30 -> 286.4535 | J36: =-J30 -> 272.13083 | K36: =-K30 -> 258.52428 | ... N36: =-N30 -> 221.65226
A37: TOTAL D&A | B37: INR Cr | C37: 437 | D37: =SUM(D34:D36) -> 526 | E37: 863 | F37: =SUM(F34:F36) -> 1597 | G37: =SUM(G34:G36) -> 2838.1476 | H37: =SUM(H34:H36) -> 4122.4038 | I37: =SUM(I34:I36) -> 5286.4737 | J37: =SUM(J34:J36) -> 6369.0036 | K37: =SUM(K34:K36) -> 7359.1978 | L37: =SUM(L34:L36) -> 8244.514 | M37: =SUM(M34:M36) -> 9047.8973 | N37: =SUM(N34:N36) -> 9782.1131 | O37: Check: reported D&A FY26A INR 1,597 Cr (1,291 depreciation + 306 amortisation)
A40: F. DETAIL ANALYSIS — capital intensity & asset productivity
A41: Revenue from operations (reported, Ind AS) | B41: INR Cr | C41: =IS!D6 -> 7079 | D41: =IS!E6 -> 12114 | E41: =IS!F6 -> 20243 | F41: =IS!G6 -> 54364 | G41: =IS!H6 -> 130546.6 | H41: =IS!I6 -> 181469.49 | I41: =IS!J6 -> 246454.5 | J41: =IS!K6 -> 321890.27 | ... N41: =IS!O6 -> 707913.6
A42: Net fixed assets (PPE + ROU) as % of revenue | B42: % | C42: =IFERROR((C9+C24)/IS!D6,"") -> 0.090832038 | D42: =IFERROR((D9+D24)/IS!E6,"") -> 0.082136371 | E42: =IFERROR((E9+E24)/IS!F6,"") -> 0.14493899 | F42: =IFERROR((F9+F24)/IS!G6,"") -> 0.11888382 | G42: =IFERROR((G9+G24)/IS!H6,"") -> 0.085021048 | H42: =IFERROR((H9+H24)/IS!I6,"") -> 0.084349479 | I42: =IFERROR((I9+I24)/IS!J6,"") -> 0.078008684 | J42: =IFERROR((J9+J24)/IS!K6,"") -> 0.071298967 | ... N42: =IFERROR((N9+N24)/IS!O6,"") -> 0.049026932
A43: Capex as % of revenue from operations | B43: % | C43: =IF(C16="","",C16/IS!D6) | D43: =IFERROR(D16/IS!E6,"") -> 0.016674922 | E43: =IFERROR(E16/IS!F6,"") -> 0.045991207 | F43: =IFERROR(F16/IS!G6,"") -> 0.032116842 | G43: =IFERROR(G16/IS!H6,"") -> 0.024512319 | H43: =IFERROR(H16/IS!I6,"") -> 0.019286989 | I43: =IFERROR(I16/IS!J6,"") -> 0.015418667 | J43: =IFERROR(J16/IS!K6,"") -> 0.01273726 | K43: =IFERROR(K16/IS!L6,"") -> 0.010508194 | ... N43: =IFERROR(N16/IS!O6,"") -> 0.0067804884
A44: Capex per net new dark store | B44: INR Cr | D44: =IFERROR(D16/(Assumptions!E16-Assumptions!D16),"") | E44: =IFERROR(E16/(Assumptions!F16-Assumptions!E16),"") -> 0.71560338 | F44: =F16/(Assumptions!G16-Assumptions!F16) -> 1.8535032 | G44: =IFERROR(G16/Assumptions!H18,"") -> 2.9090909 | H44: =IFERROR(H16/Assumptions!I18,"") -> 2.9166667 | I44: =IFERROR(I16/Assumptions!J18,"") -> 2.9230769 | J44: =IFERROR(J16/Assumptions!K18,"") -> 2.9285714 | K44: =IFERROR(K16/Assumptions!L18,"") -> 2.9482759 | L44: =IFERROR(L16/Assumptions!M18,"") -> 2.9666667 | M44: =IFERROR(M16/Assumptions!N18,"") -> 2.983871 | N44: =IFERROR(N16/Assumptions!O18,"") -> 3
A45: D&A as % of revenue from operations | B45: % | C45: =IFERROR(C37/IS!D6,"") -> 0.061731883 | D45: =IFERROR(D37/IS!E6,"") -> 0.043420835 | E45: =IFERROR(E37/IS!F6,"") -> 0.042632021 | F45: =IFERROR(F37/IS!G6,"") -> 0.029376058 | G45: =IFERROR(G37/IS!H6,"") -> 0.021740494 | H45: =IFERROR(H37/IS!I6,"") -> 0.022716787 | I45: =IFERROR(I37/IS!J6,"") -> 0.0214501 | J45: =IFERROR(J37/IS!K6,"") -> 0.019786257 | ... N45: =IFERROR(N37/IS!O6,"") -> 0.01381823
A46: Fixed asset turns (revenue from operations / closing PPE + ROU) | B46: x | C46: =IFERROR(IS!D6/(C9+C24),"") -> 11.009331 | D46: =IFERROR(IS!E6/(D9+D24),"") -> 12.174874 | E46: =IFERROR(IS!F6/(E9+E24),"") -> 6.8994547 | F46: =IFERROR(IS!G6/(F9+F24),"") -> 8.4115736 | G46: =IFERROR(IS!H6/(G9+G24),"") -> 11.761793 | H46: =IFERROR(IS!I6/(H9+H24),"") -> 11.855438 | I46: =IFERROR(IS!J6/(I9+I24),"") -> 12.819086 | J46: =IFERROR(IS!K6/(J9+J24),"") -> 14.025449 | ... N46: =IFERROR(IS!O6/(N9+N24),"") -> 20.396953
A47: ROU as % of total fixed assets (asset-light indicator) | B47: % | C47: =IFERROR(C24/(C9+C24),"") -> 0.66407465 | D47: =IFERROR(D24/(D9+D24),"") -> 0.69346734 | E47: =IFERROR(E24/(E9+E24),"") -> 0.65371506 | F47: =IFERROR(F24/(F9+F24),"") -> 0.66439734 | G47: =IFERROR(G24/(G9+G24),"") -> 0.61814396 | H47: =IFERROR(H24/(H9+H24),"") -> 0.61182037 | I47: =IFERROR(I24/(I9+I24),"") -> 0.61565463 | J47: =IFERROR(J24/(J9+J24),"") -> 0.62277474 | ... N47: =IFERROR(N24/(N9+N24),"") -> 0.65394886
A48: EBITDA (reported) / D&A (depreciation cover) | B48: x | C48: =IFERROR(IS!D57/C37,"") -> -1.791762 | D48: =IFERROR(IS!E57/D37,"") -> 0.079847909 | E48: =IFERROR(IS!F57/E37,"") -> 0.73812283 | F48: =IFERROR(IS!G57/F37,"") -> 0.75641828 | G48: =IFERROR(IS!H57/G37,"") -> 1.08186 | H48: =IFERROR(IS!I57/H37,"") -> 1.6005165 | I48: =IFERROR(IS!J57/I37,"") -> 2.3651946 | J48: =IFERROR(IS!K57/J37,"") -> 3.1939714 | ... N48: =IFERROR(IS!O57/N37,"") -> 6.4061999
A49: Capex / D&A (growth vs replacement) | B49: x | D49: =D16/D37 -> 0.38403042 | E49: =E16/E37 -> 1.0787949 | F49: =F16/F37 -> 1.0932999 | G49: =G16/G37 -> 1.127496 | H49: =H16/H37 -> 0.84901921 | I49: =I16/I37 -> 0.71881565 | J49: =J16/J37 -> 0.64374277 | K49: =K16/K37 -> 0.58090571 | ... N49: =N16/N37 -> 0.49069153
A51: READ-THROUGH
A52: 1. The business is capital-light at group level but the quick-commerce build is not: FY26A capex of INR 1,746 Cr was 3.2% of revenue from operations, and roughly INR 1,700 Cr of it went into Blinkit stores and warehousing against INR 37 Cr of Q4 Adjusted EBITDA.
A53: 2. Two-thirds of the fixed asset base is leased (right-of-use), not owned — so reported EBITDA flatters cash economics. The Adjusted EBITDA definition used throughout this model deducts cash lease rent, which is the correct basis for valuation.
A54: 3. Capex/D&A above 1.0x means the estate is still growing; the ratio falling toward 1.0x through the forecast is the signal that the store build is maturing and free cash flow inflects.
A55: ="4. Watch fixed asset turns: dark stores must lift throughput from "&TEXT('Revenue Schedule'!F66,"#,##0")&"k NOV/store/day (FY26A) to justify the capex." -> 4. Watch fixed asset turns: dark stores must lift throughput from 756k NOV/store/day (FY26A) to justify the capex.

Sheet Lease_Schedule
A1: LEASE SCHEDULE — Ind AS 116 lease liabilities and finance costs (INR Cr) | Q1: =Data_Sources!$D$28&" | "&Data_Sources!$E$28&" | "&Data_Sources!$F$28 -> Eternal Q4FY26 consolidated statement of cash flows | Adjustments to reconcile profit before tax | https://b.zmtcdn.com/investor-relations/Eternal_Shareholders_Letter_Q4FY26_Results.pdf
A2: Line item | B2: Unit | D2: FY2023A | E2: FY2024A | F2: FY2025A | G2: FY2026A | H2: FY2027E | I2: FY2028E | J2: FY2029E | K2: FY2030E | L2: FY2031E | M2: FY2032E | N2: FY2033E | O2: FY2034E | P2: Source / Note
A4: A. LEASE LIABILITIES (Ind AS 116)
A5: Opening lease liability | B5: INR Cr | E5: =(BS!D23+BS!D27) -> 466 | F5: =(BS!E23+BS!E27) -> 749 | G5: =(BS!F23+BS!F27) -> 2045 | H5: =G12 -> 4592 | I5: =H12 -> 7657.4739 | J5: =I12 -> 10956.304 | K5: =J12 -> 14414.341 | L5: =K12 -> 17930.5 | M5: =L12 -> 21222.54 | N5: =M12 -> 24121.346 | O5: =N12 -> 26414.028
A6: Add: interest accretion | B6: INR Cr | E6: =N(E21) -> 0 | F6: =F21 -> 147 | G6: =G21 -> 367 | H6: =H5*Assumptions!$B$121 -> 495.51725 | I6: =I5*Assumptions!$B$121 -> 826.30888 | J6: =J5*Assumptions!$B$121 -> 1182.2817 | K6: =K5*Assumptions!$B$121 -> 1555.4344 | L6: =L5*Assumptions!$B$121 -> 1934.8589 | M6: =M5*Assumptions!$B$121 -> 2290.099 | N6: =N5*Assumptions!$B$121 -> 2602.9058 | O6: =O5*Assumptions!$B$121 -> 2850.3063
A7: Add: new leases (from FA schedule) | B7: INR Cr | E7: =FA_Schedule!D20 -> 439 | F7: =FA_Schedule!E20 -> 1584 | G7: =FA_Schedule!F20 -> 3074 | H7: =FA_Schedule!G20 -> 3589.5966 | I7: =FA_Schedule!H20 -> 3915.9236 | J7: =FA_Schedule!I20 -> 4242.2505 | K7: =FA_Schedule!J20 -> 4568.5775 | L7: =FA_Schedule!K20 -> 4731.741 | ... O7: =FA_Schedule!N20 -> 5221.2314
A8: Add: renewals / extensions of existing leases | B8: INR Cr | H8: =H5*Assumptions!$B$126 -> 459.2 | I8: =I5*Assumptions!$B$126 -> 765.74739 | J8: =J5*Assumptions!$B$126 -> 1095.6304 | K8: =K5*Assumptions!$B$126 -> 1441.4341 | L8: =L5*Assumptions!$B$126 -> 1793.05 | M8: =M5*Assumptions!$B$126 -> 2122.254 | N8: =N5*Assumptions!$B$126 -> 2412.1346 | O8: =O5*Assumptions!$B$126 -> 2641.4028
A9: Less: lease payments (rent paid, incl. interest) | B9: INR Cr | E9: -185 | F9: -356 | G9: -838 | H9: =-Assumptions!H86 -> -1387 | I9: =-Assumptions!I86 -> -2056 | J9: =-Assumptions!J86 -> -2843 | K9: =-Assumptions!K86 -> -3761 | L9: =-Assumptions!L86 -> -4809 | M9: =-Assumptions!M86 -> -5984 | N9: =-Assumptions!N86 -> -7298 | O9: =-Assumptions!O86 -> -8764 | P9: Forecast cash rent = average stores × monthly rent per store × 12 × escalation (Assumptions row 86). Interest accretion (row 6) and principal (row 22) are derived from it.
A10: Less: terminations / derecognition | B10: INR Cr | H10: =-H5*Assumptions!$B$127 -> -91.84 | I10: =-I5*Assumptions!$B$127 -> -153.14948 | J10: =-J5*Assumptions!$B$127 -> -219.12608 | K10: =-K5*Assumptions!$B$127 -> -288.28682 | L10: =-L5*Assumptions!$B$127 -> -358.61 | M10: =-M5*Assumptions!$B$127 -> -424.4508 | N10: =-N5*Assumptions!$B$127 -> -482.42693 | O10: =-O5*Assumptions!$B$127 -> -528.28056
A11: Add / (less): other movements (derived) | B11: INR Cr | E11: =E12-E5-E6-E7-E9 -> 29 | F11: =F12-F5-F6-F7-F9 -> -79 | G11: =G12-G5-G6-G7-G9 -> -56 | H11: =Assumptions!H96 -> 0 | I11: =Assumptions!I96 -> 0 | J11: =Assumptions!J96 -> 0 | K11: =Assumptions!K96 -> 0 | L11: =Assumptions!L96 -> 0 | M11: =Assumptions!M96 -> 0 | N11: =Assumptions!N96 -> 0 | O11: =Assumptions!O96 -> 0 | P11: Residual movement. Interest accretion (row 10) is not separately disclosed for FY24 - the reported finance cost of 72 is not split between lease interest and other - so that component falls into this residual.
A12: Closing lease liability | B12: INR Cr | D12: 466 | E12: 749 | F12: 2045 | G12: 4592 | H12: =H5+H6+H7+H8+H9+H10+H11 -> 7657.4739 | I12: =I5+I6+I7+I8+I9+I10+I11 -> 10956.304 | J12: =J5+J6+J7+J8+J9+J10+J11 -> 14414.341 | K12: =K5+K6+K7+K8+K9+K10+K11 -> 17930.5 | L12: =L5+L6+L7+L8+L9+L10+L11 -> 21222.54 | M12: =M5+M6+M7+M8+M9+M10+M11 -> 24121.346 | N12: =N5+N6+N7+N8+N9+N10+N11 -> 26414.028 | O12: =O5+O6+O7+O8+O9+O10+O11 -> 27834.688
A14: of which non-current | B14: INR Cr | D14: 351 | E14: 588 | F14: 1654 | G14: 3833 | H14: =H12*$G$15 -> 6391.7895 | I14: =I12*$G$15 -> 9145.3646 | J14: =J12*$G$15 -> 12031.831 | K14: =K12*$G$15 -> 14966.813 | L14: =L12*$G$15 -> 17714.72 | M14: =M12*$G$15 -> 20134.39 | N14: =N12*$G$15 -> 22048.12 | O14: =O12*$G$15 -> 23233.963
D15: =D14/D12 -> 0.75321888 | E15: =E14/E12 -> 0.78504673 | F15: =F14/F12 -> 0.80880196 | G15: =G14/G12 -> 0.83471254 | H15: =H14/H12 -> 0.83471254 | I15: =I14/I12 -> 0.83471254 | J15: =J14/J12 -> 0.83471254 | K15: =K14/K12 -> 0.83471254 | ... O15: =O14/O12 -> 0.83471254
A17: of which current | B17: INR Cr | D17: 115 | E17: 161 | F17: 391 | G17: 759 | H17: =H12*$G$18 -> 1265.6844 | I17: =I12*$G$18 -> 1810.9397 | J17: =J12*$G$18 -> 2382.5097 | K17: =K12*$G$18 -> 2963.6867 | L17: =L12*$G$18 -> 3507.8196 | M17: =M12*$G$18 -> 3986.956 | N17: =N12*$G$18 -> 4365.9075 | O17: =O12*$G$18 -> 4600.7247
D18: =D17/D12 -> 0.24678112 | E18: =E17/E12 -> 0.21495327 | F18: =F17/F12 -> 0.19119804 | G18: =G17/G12 -> 0.16528746 | H18: =H17/H12 -> 0.16528746 | I18: =I17/I12 -> 0.16528746 | J18: =J17/J12 -> 0.16528746 | K18: =K17/K12 -> 0.16528746 | ... O18: =O17/O12 -> 0.16528746
A20: B. DERIVED CASH & P&L ITEMS
A21: Lease interest (P&L finance cost) | B21: INR Cr | E21: MANUAL – OPEN | F21: 147 | G21: 367 | H21: =H6 -> 495.51725 | I21: =I6 -> 826.30888 | J21: =J6 -> 1182.2817 | K21: =K6 -> 1555.4344 | L21: =L6 -> 1934.8589 | M21: =M6 -> 2290.099 | N21: =N6 -> 2602.9058 | O21: =O6 -> 2850.3063 | P21: FY25A interest expense on lease liabilities per the consolidated cash flow statement.
A22: Lease principal repaid | B22: INR Cr | E22: =-E9-N(E21) -> 185 | F22: =-F9-F21 -> 209 | G22: =-G9-G21 -> 471 | H22: =-H9-H21 -> 891.48275 | I22: =-I9-I21 -> 1229.6911 | J22: =-J9-J21 -> 1660.7183 | K22: =-K9-K21 -> 2205.5656 | L22: =-L9-L21 -> 2874.1411 | M22: =-M9-M21 -> 3693.901 | ... O22: =-O9-O21 -> 5913.6937
A23: Total lease payment (cash rent) — feeds IS row 24 | B23: INR Cr | E23: =-E9 -> 185 | F23: =-F9 -> 356 | G23: =-G9 -> 838 | H23: =-H9 -> 1387 | I23: =-I9 -> 2056 | J23: =-J9 -> 2843 | K23: =-K9 -> 3761 | L23: =-L9 -> 4809 | ... O23: =-O9 -> 8764
A24: Other finance costs (non-lease) | B24: INR Cr | D24: =IFERROR(D25-D21,"") -> 49 | E24: =E25-N(E21) -> 72 | F24: =IFERROR(F25-F21,"") -> 7 | G24: =IFERROR(G25-G21,"") -> 25 | H24: 0 | I24: 0 | J24: 0 | K24: 0 | L24: 0 | M24: 0 | N24: 0 | O24: 0
A25: TOTAL FINANCE COSTS — feeds IS row 28 | B25: INR Cr | D25: 49 | E25: 72 | F25: 154 | G25: 392 | H25: =H21+H24 -> 495.51725 | I25: =I21+I24 -> 826.30888 | J25: =J21+J24 -> 1182.2817 | K25: =K21+K24 -> 1555.4344 | L25: =L21+L24 -> 1934.8589 | M25: =M21+M24 -> 2290.099 | N25: =N21+N24 -> 2602.9058 | O25: =O21+O24 -> 2850.3063
A28: C. DETAIL ANALYSIS — lease economics & leverage
A29: Cash rent as % of adjusted revenue | B29: % | E29: =E23/'Revenue Schedule'!D27 -> 0.013658176 | F29: =F23/'Revenue Schedule'!E27 -> 0.016483771 | G29: =G23/'Revenue Schedule'!F27 -> 0.014990251 | H29: =H23/'Revenue Schedule'!G27 -> 0.010394621 | I29: =I23/'Revenue Schedule'!H27 -> 0.011091217 | J29: =J23/'Revenue Schedule'!I27 -> 0.011298189 | K29: =K23/'Revenue Schedule'!J27 -> 0.011447443 | L29: =L23/'Revenue Schedule'!K27 -> 0.011584434 | ... O29: =O23/'Revenue Schedule'!N27 -> 0.012138363
A30: Cash rent as % of B2C NOV | B30: % | E30: =IFERROR(E23/'Revenue Schedule'!D16,"") -> 0.0044896374 | F30: =IFERROR(F23/'Revenue Schedule'!E16,"") -> 0.0057556748 | G30: =IFERROR(G23/'Revenue Schedule'!F16,"") -> 0.0087328053 | H30: =IFERROR(H23/'Revenue Schedule'!G16,"") -> 0.0076847657 | I30: =IFERROR(I23/'Revenue Schedule'!H16,"") -> 0.0084296395 | J30: =IFERROR(J23/'Revenue Schedule'!I16,"") -> 0.0087835928 | K30: =IFERROR(K23/'Revenue Schedule'!J16,"") -> 0.0090425982 | L30: =IFERROR(L23/'Revenue Schedule'!K16,"") -> 0.0092696305 | ... O30: =IFERROR(O23/'Revenue Schedule'!N16,"") -> 0.0099486411
A31: Indicative rent per dark store per year (company leases all stores) | B31: INR lakh | E31: =E23/'Revenue Schedule'!D60*100 -> 35.171103 | F31: =F23/'Revenue Schedule'!E60*100 -> 27.363566 | G31: =IFERROR(G23/Assumptions!G16*100,"") -> 37.360678 | H31: =IFERROR(H23/Assumptions!H16*100,"") -> 41.48968 | I31: =IFERROR(I23/Assumptions!I16*100,"") -> 45.256438 | J31: =IFERROR(J23/Assumptions!J16*100,"") -> 48.656512 | K31: =IFERROR(K23/Assumptions!K16*100,"") -> 51.925998 | L31: =IFERROR(L23/Assumptions!L16*100,"") -> 55.320373 | M31: =IFERROR(M23/Assumptions!M16*100,"") -> 58.706956 | N31: =IFERROR(N23/Assumptions!N16*100,"") -> 62.147662 | O31: =IFERROR(O23/Assumptions!O16*100,"") -> 65.68238 | P31: Total group cash rent divided by store count indicative only, as the estate also includes warehouses and offices.
A32: Lease liability / Adjusted EBITDA | B32: x | D32: =D12/IS!D48 -> -0.59514687 | E32: =E12/IS!E48 -> 2.0134409 | F32: =F12/IS!F48 -> 1.8952734 | G32: =G12/IS!G48 -> 3.862069 | H32: =H12/IS!H48 -> 3.0225141 | I32: =I12/IS!I48 -> 2.0207219 | J32: =J12/IS!J48 -> 1.3649248 | K32: =K12/IS!K48 -> 1.0245172 | ... O32: =O12/IS!O48 -> 0.50698701
A33: Net (cash) / debt including lease liabilities | B33: INR Cr | D33: =D12-CFS!D32 -> -10857 | E33: =E12-CFS!E32 -> -11492 | F33: =F12-CFS!F32 -> -14761 | G33: =G12-CFS!G32 -> -13380 | H33: =H12-CFS!H32 -> 2019.8424 | I33: =I12-CFS!I32 -> 16334.907 | J33: =J12-CFS!J32 -> 28210.691 | K33: =K12-CFS!K32 -> 38174.657 | ... O33: =O12-CFS!O32 -> -3510.2819
A34: Net debt / Adjusted EBITDA | B34: x | D34: =D33/IS!D48 -> 13.8659 | E34: =E33/IS!E48 -> -30.892473 | F34: =F33/IS!F48 -> -13.680259 | G34: =G33/IS!G48 -> -11.253154 | H34: =H33/IS!H48 -> 0.79726058 | I34: =I33/IS!I48 -> 3.0127226 | J34: =J33/IS!J48 -> 2.6713306 | K34: =K33/IS!K48 -> 2.1812326 | ... O34: =O33/IS!O48 -> -0.063937031
A35: Interest cover (Adjusted EBITDA / finance costs) | B35: x | D35: =IS!D48/D25 -> -15.979592 | E35: =IS!E48/E25 -> 5.1666667 | F35: =F17*0+IS!F48/F25 -> 7.0064935 | G35: =IS!G48/G25 -> 3.0331633 | H35: =IS!H48/H25 -> 5.1127953 | I35: =IS!I48/I25 -> 6.5616809 | J35: =IS!J48/J25 -> 8.9323369 | K35: =IS!K48/K25 -> 11.251786 | L35: =IS!L48/L25 -> 13.336959 | M35: =IS!M48/M25 -> 14.894978 | N35: =IS!N48/N25 -> 16.97125 | O35: =IS!O48/O25 -> 19.26185
A36: Implied remaining lease life (closing liability / principal repaid) | B36: x | F36: =F12/F22 -> 9.784689 | G36: =G12/G22 -> 9.7494692 | H36: =H12/H22 -> 8.5895929 | I36: =I12/I22 -> 8.9098019 | J36: =J12/J22 -> 8.6795823 | K36: =K12/K22 -> 8.1296605 | L36: =L12/L22 -> 7.3839589 | M36: =M12/M22 -> 6.5300468 | ... O36: =O12/O22 -> 4.7068193
A38: READ-THROUGH
A39: 1. There is no bank debt. The only leverage is the Ind AS 116 lease book, which is expanding with the dark store estate and lease liabilities roughly doubled in FY26 (2,045 to 4,592) as Blinkit added 942 stores.
A40: 2. On a net basis the group is deeply net cash: INR 17,972 Cr of treasury against INR 4,592 Cr of leases at FY26. Leverage is therefore not a solvency question and it is a question of how fast treasury is consumed by store capex and working capital.
A41: 3. Cash rent is the number that matters, not the lease liability. Rent is 1.5% of adjusted revenue but 0.9% of B2C NOV and every 10bps of rent leakage is meaningful against a 5-6% target NOV margin in quick commerce.
A42: 4. Because Adjusted EBITDA already deducts cash rent, the DCF does not additionally subtract the lease liability from enterprise value — doing both would double-count the obligation. See the note on DCF row 32.

Sheet Tax_Schedule
A1: TAX SCHEDULE — tax-loss carry-forward (replaces the hand-typed effective-rate glide, Assumptions H91:O91)
A2: Line item | B2: Unit | D2: =IS!D2 -> FY2023A | E2: =IS!E2 -> FY2024A | F2: =IS!F2 -> FY2025A | G2: =IS!G2 -> FY2026A | H2: =IS!H2 -> FY2027E | I2: =IS!I2 -> FY2028E | J2: =IS!J2 -> FY2029E | K2: =IS!K2 -> FY2030E | ... O2: =IS!O2 -> FY2034E
A4: Profit before tax (IS row 26) | B4: INR Cr | H4: =IS!H26 -> -7456.6258 | I4: =IS!I26 -> -8227.6845 | J4: =IS!J26 -> -7060.4536 | K4: =IS!K26 -> -3202.4177 | L4: =IS!L26 -> 3678.679 | M4: =IS!M26 -> 12717.939 | N4: =IS!N26 -> 27329.603 | O4: =IS!O26 -> 39666.097
A5: Opening unabsorbed tax losses | B5: INR Cr | H5: =Assumptions!B156 -> 0 | I5: =H8 -> 7456.6258 | J5: =I8 -> 15684.31 | K5: =J8 -> 22744.764 | L5: =K8 -> 25947.182 | M5: =L8 -> 22268.503 | N5: =M8 -> 9550.5636 | O5: =N8 -> 0
A6: Add: tax losses created (PBT < 0) | B6: INR Cr | H6: =MAX(0,-H4) -> 7456.6258 | I6: =MAX(0,-I4) -> 8227.6845 | J6: =MAX(0,-J4) -> 7060.4536 | K6: =MAX(0,-K4) -> 3202.4177 | L6: =MAX(0,-L4) -> 0 | M6: =MAX(0,-M4) -> 0 | N6: =MAX(0,-N4) -> 0 | O6: =MAX(0,-O4) -> 0
A7: Less: losses utilised against profit | B7: INR Cr | H7: =MIN(H5,MAX(0,H4)) -> 0 | I7: =MIN(I5,MAX(0,I4)) -> 0 | J7: =MIN(J5,MAX(0,J4)) -> 0 | K7: =MIN(K5,MAX(0,K4)) -> 0 | L7: =MIN(L5,MAX(0,L4)) -> 3678.679 | M7: =MIN(M5,MAX(0,M4)) -> 12717.939 | N7: =MIN(N5,MAX(0,N4)) -> 9550.5636 | O7: =MIN(O5,MAX(0,O4)) -> 0
A8: Closing unabsorbed tax losses | B8: INR Cr | H8: =H5+H6-H7 -> 7456.6258 | I8: =I5+I6-I7 -> 15684.31 | J8: =J5+J6-J7 -> 22744.764 | K8: =K5+K6-K7 -> 25947.182 | L8: =L5+L6-L7 -> 22268.503 | M8: =M5+M6-M7 -> 9550.5636 | N8: =N5+N6-N7 -> 0 | O8: =O5+O6-O7 -> 0
A9: Taxable income after loss set-off | B9: INR Cr | H9: =MAX(0,H4)-H7 -> 0 | I9: =MAX(0,I4)-I7 -> 0 | J9: =MAX(0,J4)-J7 -> 0 | K9: =MAX(0,K4)-K7 -> 0 | L9: =MAX(0,L4)-L7 -> 0 | M9: =MAX(0,M4)-M7 -> 0 | N9: =MAX(0,N4)-N7 -> 17779.04 | O9: =MAX(0,O4)-O7 -> 39666.097
A10: Statutory tax rate | B10: % | H10: =Assumptions!$B$157 -> 0.2517 | I10: =Assumptions!$B$157 -> 0.2517 | J10: =Assumptions!$B$157 -> 0.2517 | K10: =Assumptions!$B$157 -> 0.2517 | L10: =Assumptions!$B$157 -> 0.2517 | M10: =Assumptions!$B$157 -> 0.2517 | N10: =Assumptions!$B$157 -> 0.2517 | O10: =Assumptions!$B$157 -> 0.2517
A11: Tax expense (to IS row 27; negative = charge) | B11: INR Cr | H11: =-H9*H10 -> 0 | I11: =-I9*I10 -> 0 | J11: =-J9*J10 -> 0 | K11: =-K9*K10 -> 0 | L11: =-L9*L10 -> 0 | M11: =-M9*M10 -> 0 | N11: =-N9*N10 -> -4474.9843 | O11: =-O9*O10 -> -9983.9566
A12: Effective tax rate on PBT (to Assumptions row 91) | B12: % | H12: =IF(H4>0,-H11/H4,0) -> 0 | I12: =IF(I4>0,-I11/I4,0) -> 0 | J12: =IF(J4>0,-J11/J4,0) -> 0 | K12: =IF(K4>0,-K11/K4,0) -> 0 | L12: =IF(L4>0,-L11/L4,0) -> 0 | M12: =IF(M4>0,-M11/M4,0) -> 0 | N12: =IF(N4>0,-N11/N4,0) -> 0.16374128 | O12: =IF(O4>0,-O11/O4,0) -> 0.2517
A14: Limitations: ignores MAT / minimum tax and entity-level mismatch (FY26A effective rate was 40% because tax is paid on treasury income in profitable entities while losses sit elsewhere — Assumptions!G91). Deferred tax is not modelled; book tax = cash tax.

Sheet WC_Schedule
A1: WORKING CAPITAL SCHEDULE — days, balances and the cash conversion cycle (INR Cr) | Q1: =Data_Sources!$D$29&" | "&Data_Sources!$E$29&" | "&Data_Sources!$F$29 -> Eternal Q4FY25 and Q4FY26 audited consolidated balance sheets | Annexure E | https://b.zmtcdn.com/investor-relations/Eternal_Shareholders_Letter_Q4FY26_Results.pdf
A2: Line item | B2: Unit | D2: FY2023A | E2: FY2024A | F2: FY2025A | G2: FY2026A | H2: FY2027E | I2: FY2028E | J2: FY2029E | K2: FY2030E | L2: FY2031E | M2: FY2032E | N2: FY2033E | O2: FY2034E | P2: Source / Note
A4: A. DRIVERS
A5: Revenue from operations | B5: INR Cr | D5: ='Revenue Schedule'!C31 -> 7079 | E5: ='Revenue Schedule'!D31 -> 12114 | F5: ='Revenue Schedule'!E31 -> 20243 | G5: ='Revenue Schedule'!F31 -> 54364 | H5: ='Revenue Schedule'!G31 -> 130546.6 | I5: ='Revenue Schedule'!H31 -> 181469.49 | J5: ='Revenue Schedule'!I31 -> 246454.5 | K5: ='Revenue Schedule'!J31 -> 321890.27 | ... O5: ='Revenue Schedule'!N31 -> 707913.6
A6: Cost of goods sold (from Cost Structure) | B6: INR Cr | D6: ='Cost Schedule'!D6 -> 1395 | E6: ='Cost Schedule'!E6 -> 2882 | F6: ='Cost Schedule'!F6 -> 5565 | G6: ='Cost Schedule'!G6 -> 30167 | H6: ='Cost Schedule'!H6 -> 83490.547 | I6: ='Cost Schedule'!I6 -> 116049.89 | J6: ='Cost Schedule'!J6 -> 158151.75 | K6: ='Cost Schedule'!K6 -> 206480.48 | ... O6: ='Cost Schedule'!O6 -> 455499.37
A7: Receivable days | B7: Days | D7: =D12/D5*365 -> 23.563356 | E7: =E12/E5*365 -> 23.92356 | F7: =F12/F5*365 -> 35.088179 | G7: =G12/G5*365 -> 11.843499 | H7: =Assumptions!H102 -> 12 | I7: =Assumptions!I102 -> 12 | J7: =Assumptions!J102 -> 12 | K7: =Assumptions!K102 -> 12 | L7: =Assumptions!L102 -> 12 | M7: =Assumptions!M102 -> 12 | N7: =Assumptions!N102 -> 12 | O7: =Assumptions!O102 -> 12
A8: Inventory days (on COGS) | B8: Days | D8: =IFERROR(D13/D6*365,"") -> 21.716846 | E8: =IFERROR(E13/E6*365,"") -> 11.145038 | F8: =IFERROR(F13/F6*365,"") -> 11.543576 | G8: =IFERROR(G13/G6*365,"") -> 26.388603 | H8: =Assumptions!H103 -> 26 | I8: =Assumptions!I103 -> 26 | J8: =Assumptions!J103 -> 25 | K8: =Assumptions!K103 -> 25 | L8: =Assumptions!L103 -> 24 | M8: =Assumptions!M103 -> 24 | N8: =Assumptions!N103 -> 24 | O8: =Assumptions!O103 -> 24
A9: Payable days (on COGS) | B9: Days | D9: =IFERROR(D18/D6*365,"") -> 177.6595 | E9: =IFERROR(E18/E6*365,"") -> 112.21027 | F9: =IFERROR(F18/F6*365,"") -> 100.74394 | G9: =IFERROR(G18/G6*365,"") -> 36.418935 | H9: =Assumptions!H104 -> 36 | I9: =Assumptions!I104 -> 37 | J9: =Assumptions!J104 -> 38 | K9: =Assumptions!K104 -> 38 | L9: =Assumptions!L104 -> 38 | M9: =Assumptions!M104 -> 38 | N9: =Assumptions!N104 -> 38 | O9: =Assumptions!O104 -> 38
A11: B. CURRENT ASSETS (ex-cash)
A12: Trade receivables | B12: INR Cr | D12: 457 | E12: 794 | F12: 1946 | G12: 1764 | H12: =H5*H7/365 -> 4291.9431 | I12: =I5*I7/365 -> 5966.1201 | J12: =J5*J7/365 -> 8102.6138 | K12: =K5*K7/365 -> 10582.694 | L12: =L5*L7/365 -> 13375.08 | M12: =M5*M7/365 -> 16502.764 | N12: =N5*N7/365 -> 20010.328 | O12: =O5*O7/365 -> 23273.872
A13: Inventories | B13: INR Cr | D13: 83 | E13: 88 | F13: 176 | G13: 2181 | H13: =H6*H8/365 -> 5947.2718 | I13: =I6*I8/365 -> 8266.5674 | J13: =J6*J8/365 -> 10832.312 | K13: =K6*K8/365 -> 14142.499 | L13: =L6*L8/365 -> 17144.666 | M13: =M6*M8/365 -> 21265.624 | N13: =N6*N8/365 -> 25692.367 | O13: =O6*O8/365 -> 29950.643
A14: Other current assets (incl. other financial assets) | B14: INR Cr | D14: 4789 | E14: 2565 | F14: 5713 | G14: 5141 | H14: =H5*Assumptions!H105 -> 11096.461 | I14: =I5*Assumptions!I105 -> 15424.906 | J14: =J5*Assumptions!J105 -> 19716.36 | K14: =K5*Assumptions!K105 -> 25751.221 | L14: =L5*Assumptions!L105 -> 32546.029 | M14: =M5*Assumptions!M105 -> 40156.726 | N14: =N5*Assumptions!N105 -> 48691.799 | O14: =O5*Assumptions!O105 -> 56633.088
A15: Total current assets (ex-cash) | B15: INR Cr | D15: =D12+D13+D14 -> 5329 | E15: =E12+E13+E14 -> 3447 | F15: =F12+F13+F14 -> 7835 | G15: =G12+G13+G14 -> 9086 | H15: =H12+H13+H14 -> 21335.676 | I15: =I12+I13+I14 -> 29657.594 | J15: =J12+J13+J14 -> 38651.286 | K15: =K12+K13+K14 -> 50476.414 | ... O15: =O12+O13+O14 -> 109857.6
A17: C. CURRENT LIABILITIES (ex-debt)
A18: Trade payables | B18: INR Cr | D18: 679 | E18: 886 | F18: 1536 | G18: 3010 | H18: =H6*H9/365 -> 8234.6841 | I18: =I6*I9/365 -> 11763.961 | J18: =J6*J9/365 -> 16465.114 | K18: =K6*K9/365 -> 21496.598 | L18: =L6*L9/365 -> 27145.721 | M18: =M6*M9/365 -> 33670.571 | N18: =N6*N9/365 -> 40679.581 | O18: =O6*O9/365 -> 47421.852
A19: Other current liabilities & provisions | B19: INR Cr | D19: 612 | E19: 1036 | F19: 1399 | G19: 1888 | H19: =H5*Assumptions!H106 -> 4438.5845 | I19: =I5*Assumptions!I106 -> 6169.9626 | J19: =J5*Assumptions!J106 -> 8379.4531 | K19: =K5*Assumptions!K106 -> 10944.269 | L19: =L5*Assumptions!L106 -> 13832.062 | M19: =M5*Assumptions!M106 -> 17066.608 | N19: =N5*Assumptions!N106 -> 20694.015 | O19: =O5*Assumptions!O106 -> 24069.063
A20: Total current liabilities (ex-debt) | B20: INR Cr | D20: =D18+D19 -> 1291 | E20: =E18+E19 -> 1922 | F20: =F18+F19 -> 2935 | G20: =G18+G19 -> 4898 | H20: =H18+H19 -> 12673.269 | I20: =I18+I19 -> 17933.924 | J20: =J18+J19 -> 24844.567 | K20: =K18+K19 -> 32440.867 | ... O20: =O18+O19 -> 71490.914
A22: D. NET WORKING CAPITAL
A23: Net working capital | B23: INR Cr | D23: =D15-D20 -> 4038 | E23: =E15-E20 -> 1525 | F23: =F15-F20 -> 4900 | G23: =G15-G20 -> 4188 | H23: =H15-H20 -> 8662.4075 | I23: =I15-I20 -> 11723.67 | J23: =J15-J20 -> 13806.719 | K23: =K15-K20 -> 18035.547 | ... O23: =O15-O20 -> 38366.689
A24: Increase / (decrease) in NWC — feeds CFS row 11 and DCF row 16 | B24: INR Cr | E24: =E23-D23 -> -2513 | F24: =F23-E23 -> 3375 | G24: =G23-F23 -> -712 | H24: =H23-G23 -> 4474.4075 | I24: =I23-H23 -> 3061.2626 | J24: =J23-I23 -> 2083.0488 | K24: =K23-J23 -> 4228.8277 | L24: =L23-K23 -> 4052.4457 | ... O24: =O23-N23 -> 5345.7905 | P24: An increase is a cash outflow. Company-disclosed FY26 NWC movement was an outflow of INR 1,228 Cr.
A25: NWC as % of revenue from operations | B25: % | D25: =D23/D5 -> 0.57041955 | E25: =E23/E5 -> 0.1258874 | F25: =F23/F5 -> 0.24205898 | G25: =G23/G5 -> 0.077036274 | H25: =H23/H5 -> 0.066354906 | I25: =I23/I5 -> 0.064604084 | J25: =J23/J5 -> 0.05602137 | K25: =K23/K5 -> 0.056030109 | ... O25: =O23/O5 -> 0.054196852
A27: E. DETAIL ANALYSIS — cash conversion cycle & float
A28: Inventory days | B28: Days | D28: =IFERROR(D13/D6*365,"") -> 21.716846 | E28: =IFERROR(E13/E6*365,"") -> 11.145038 | F28: =IFERROR(F13/F6*365,"") -> 11.543576 | G28: =IFERROR(G13/G6*365,"") -> 26.388603 | H28: =H13/H6*365 -> 26 | I28: =I13/I6*365 -> 26 | J28: =J13/J6*365 -> 25 | K28: =K13/K6*365 -> 25 | L28: =L13/L6*365 -> 24 | M28: =M13/M6*365 -> 24 | N28: =N13/N6*365 -> 24 | O28: =O13/O6*365 -> 24
A29: Add: receivable days | B29: Days | D29: =D12/D5*365 -> 23.563356 | E29: =E12/E5*365 -> 23.92356 | F29: =F12/F5*365 -> 35.088179 | G29: =G12/G5*365 -> 11.843499 | H29: =H12/H5*365 -> 12 | I29: =I12/I5*365 -> 12 | J29: =J12/J5*365 -> 12 | K29: =K12/K5*365 -> 12 | ... O29: =O12/O5*365 -> 12
A30: Less: payable days | B30: Days | D30: =IFERROR(-D18/D6*365,"") -> -177.6595 | E30: =IFERROR(-E18/E6*365,"") -> -112.21027 | F30: =IFERROR(-F18/F6*365,"") -> -100.74394 | G30: =IFERROR(-G18/G6*365,"") -> -36.418935 | H30: =-H18/H6*365 -> -36 | I30: =-I18/I6*365 -> -37 | J30: =-J18/J6*365 -> -38 | K30: =-K18/K6*365 -> -38 | L30: =-L18/L6*365 -> -38 | M30: =-M18/M6*365 -> -38 | N30: =-N18/N6*365 -> -38 | O30: =-O18/O6*365 -> -38
A31: CASH CONVERSION CYCLE | B31: Days | D31: =IFERROR(D28+D29+D30,"") -> -132.3793 | E31: =IFERROR(E28+E29+E30,"") -> -77.141673 | F31: =IFERROR(F28+F29+F30,"") -> -54.112181 | G31: =IFERROR(G28+G29+G30,"") -> 1.8131682 | H31: =H28+H29+H30 -> 2 | I31: =I28+I29+I30 -> 1 | J31: =J28+J29+J30 -> -1 | K31: =K28+K29+K30 -> -1 | L31: =L28+L29+L30 -> -2 | M31: =M28+M29+M30 -> -2 | N31: =N28+N29+N30 -> -2 | O31: =O28+O29+O30 -> -2
A33: READ-THROUGH
A34: 1. FY26 is the structural break: inventories went from INR 176 Cr to INR 2,181 Cr as Blinkit took ownership of stock. That one-off is why the company's disclosed working capital outflow was INR 1,228 Cr for the year despite positive Adjusted EBITDA.
A35: 2. The cycle is still short in absolute terms because payables (36 days on COGS) fund most of the inventory (26 days). Lengthening brand terms as scale grows is the cheapest source of funding available to the business.
A36: 3. Receivables are structurally tiny (12 days) and consumers pay at checkout. The receivable book is brand advertising and Hyperpure trade credit, not consumer credit.
A37: ="FY2027E free cash flow (CFO − capex, CFS row 35) is "&TEXT(CFS!H35,"#,##0")&" Cr on reported EBITDA of "&TEXT(IS!H16,"#,##0")&" Cr." -> FY2027E free cash flow (CFO − capex, CFS row 35) is -12,116 Cr on reported EBITDA of -5,291 Cr.
A38: 5. FY25 'other current assets' as reported include INR 2,948 Cr of bank balances that are counted inside treasury on the BS tab and only the non-treasury portion (INR 3,693 Cr) is treated as working capital here to avoid double-counting cash.

Sheet Other Income Schedule 
A1: OTHER INCOME / TREASURY & INVESTMENT SCHEDULE — Eternal Limited (INR Cr) | P1: =Data_Sources!$D$4&" | "&Data_Sources!$E$4&" | "&Data_Sources!$F$4 -> Eternal Q4FY26 audited consolidated financial results | Statement of consolidated financial results, line II | https://b.zmtcdn.com/investor-relations/Eternal_Shareholders_Letter_Q4FY26_Results.pdf
A2: Line item | B2: Unit | D2: FY2023A | E2: FY2024A | F2: FY2025A | G2: FY2026A | H2: FY2027E | I2: FY2028E | J2: FY2029E | K2: FY2030E | L2: FY2031E | M2: FY2032E | N2: FY2033E | O2: FY2034E
A4: A. INVESTMENT BASE
A5: Opening cash & treasury investments | B5: INR Cr | D5: =IF(CFS!D31="","",CFS!D31) | E5: =IF(CFS!E31="","",CFS!E31) -> 11323 | F5: =IF(CFS!F31="","",CFS!F31) -> 12241 | G5: =IF(CFS!G31="","",CFS!G31) -> 16806 | H5: =IF(CFS!H31="","",CFS!H31) -> 17972 | I5: =IF(CFS!I31="","",CFS!I31) -> 5637.6315 | J5: =IF(CFS!J31="","",CFS!J31) -> -5378.6029 | K5: =IF(CFS!K31="","",CFS!K31) -> -13796.35 | ... O5: =IF(CFS!O31="","",CFS!O31) -> 6940.2003
A6: Closing cash & treasury investments | B6: INR Cr | D6: =CFS!D32 -> 11323 | E6: =CFS!E32 -> 12241 | F6: =CFS!F32 -> 16806 | G6: =CFS!G32 -> 17972 | H6: =CFS!H32 -> 5637.6315 | I6: =CFS!I32 -> -5378.6029 | J6: =CFS!J32 -> -13796.35 | K6: =CFS!K32 -> -20244.157 | ... O6: =CFS!O32 -> 31344.97
A7: Average balance | B7: INR Cr | D7: =IF(D5="",D6,AVERAGE(D5,D6)) -> 11323 | E7: =IF(E5="",E6,AVERAGE(E5,E6)) -> 11782 | F7: =IF(F5="",F6,AVERAGE(F5,F6)) -> 14523.5 | G7: =IF(G5="",G6,AVERAGE(G5,G6)) -> 17389 | H7: =IF(H5="",H6,AVERAGE(H5,H6)) -> 11804.816 | I7: =IF(I5="",I6,AVERAGE(I5,I6)) -> 129.51429 | J7: =IF(J5="",J6,AVERAGE(J5,J6)) -> -9587.4764 | K7: =IF(K5="",K6,AVERAGE(K5,K6)) -> -17020.254 | ... O7: =IF(O5="",O6,AVERAGE(O5,O6)) -> 19142.585
A9: B. INCOME EARNED
A10: Treasury yield on opening balance | B10: % | D10: =Assumptions!D90 -> 0 | E10: =Assumptions!E90 -> 0.074803497 | F10: =Assumptions!F90 -> 0.087983008 | G10: =Assumptions!G90 -> 0.083065572 | H10: =Assumptions!H90 -> 0.065 | I10: =Assumptions!I90 -> 0.065 | J10: =Assumptions!J90 -> 0.065 | K10: =Assumptions!K90 -> 0.065 | ... O10: =Assumptions!O90 -> 0.065
A12: OTHER INCOME — ACCRUAL BASIS (to P&L) | B12: INR Cr | D12: 682 | E12: 847 | F12: 1077 | G12: 1396 | H12: =H10*CFS!G32 -> 1168.18 | I12: =I10*CFS!H32 -> 366.44605 | J12: =J10*CFS!I32 -> -349.60919 | K12: =K10*CFS!J32 -> -896.76274 | L12: =L10*CFS!K32 -> -1315.8702 | M12: =M10*CFS!L32 -> -1265.4114 | N12: =N10*CFS!M32 -> -701.30171 | O12: =O10*CFS!N32 -> 451.11302
A13: of which: interest on deposits & bonds | B13: INR Cr | D13: =IFERROR(D12*0.75,"") -> 511.5 | E13: =IFERROR(E12*0.75,"") -> 635.25 | F13: =IFERROR(F12*0.75,"") -> 807.75 | G13: =IFERROR(G12*0.75,"") -> 1047 | H13: =IFERROR(H12*0.75,"") -> 876.135 | I13: =IFERROR(I12*0.75,"") -> 274.83454 | J13: =IFERROR(J12*0.75,"") -> -262.20689 | K13: =IFERROR(K12*0.75,"") -> -672.57206 | ... O13: =IFERROR(O12*0.75,"") -> 338.33477
A14: of which: fair value gains on investments | B14: INR Cr | D14: =IFERROR(D12-D13,"") -> 170.5 | E14: =IFERROR(E12-E13,"") -> 211.75 | F14: =IFERROR(F12-F13,"") -> 269.25 | G14: =IFERROR(G12-G13,"") -> 349 | H14: =IFERROR(H12-H13,"") -> 292.045 | I14: =IFERROR(I12-I13,"") -> 91.611512 | J14: =IFERROR(J12-J13,"") -> -87.402297 | K14: =IFERROR(K12-K13,"") -> -224.19069 | ... O14: =IFERROR(O12-O13,"") -> 112.77826
A16: C. CASH VS ACCRUAL
A17: Treasury income received (cash, to CFS) | B17: INR Cr | E17: 618 | F17: 820 | G17: 953 | H17: =H12 -> 1168.18 | I17: =I12 -> 366.44605 | J17: =J12 -> -349.60919 | K17: =K12 -> -896.76274 | L17: =L12 -> -1315.8702 | M17: =M12 -> -1265.4114 | N17: =N12 -> -701.30171 | O17: =O12 -> 451.11302
A18: Accrual less cash received | B18: INR Cr | D18: =IFERROR(D12-D17,"") -> 682 | E18: =IFERROR(E12-E17,"") -> 229 | F18: =IFERROR(F12-F17,"") -> 257 | G18: =IFERROR(G12-G17,"") -> 443 | H18: =IFERROR(H12-H17,"") -> 0 | I18: =IFERROR(I12-I17,"") -> 0 | J18: =IFERROR(J12-J17,"") -> 0 | K18: =IFERROR(K12-K17,"") -> 0 | ... O18: =IFERROR(O12-O17,"") -> 0
A19: Effective yield on average balance | B19: % | D19: =IFERROR(D12/D7,"") -> 0.060231387 | E19: =IFERROR(E12/E7,"") -> 0.071889323 | F19: =IFERROR(F12/F7,"") -> 0.074155679 | G19: =IFERROR(G12/G7,"") -> 0.080280637 | H19: =IFERROR(H12/H7,"") -> 0.098957919 | I19: =IFERROR(I12/I7,"") -> 2.829387 | J19: =IFERROR(J12/J7,"") -> 0.036465194 | K19: =IFERROR(K12/K7,"") -> 0.052687978 | ... O19: =IFERROR(O12/O7,"") -> 0.023565941
A21: D. CHECKS
A22: Check: accrual income vs IS other income (must be nil) | B22: INR Cr | D22: =IFERROR(ROUND(D12-IS!D23,6),"") -> 0 | E22: =IFERROR(ROUND(E12-IS!E23,6),"") -> 0 | F22: =IFERROR(ROUND(F12-IS!F23,6),"") -> 0 | G22: =IFERROR(ROUND(G12-IS!G23,6),"") -> 0 | H22: =IFERROR(ROUND(H12-IS!H23,6),"") -> 0 | I22: =IFERROR(ROUND(I12-IS!I23,6),"") -> 0 | J22: =IFERROR(ROUND(J12-IS!J23,6),"") -> 0 | K22: =IFERROR(ROUND(K12-IS!K23,6),"") -> 0 | ... O22: =IFERROR(ROUND(O12-IS!O23,6),"") -> 0
A23: Check: cash received vs CFS treasury line (must be nil) | B23: INR Cr | D23: =IFERROR(ROUND(D17-CFS!D20,6),"") -> 0 | E23: =IFERROR(ROUND(E17-CFS!E20,6),"") -> 0 | F23: =IFERROR(ROUND(F17-CFS!F20,6),"") -> 0 | G23: =IFERROR(ROUND(G17-CFS!G20,6),"") -> 0 | H23: =IFERROR(ROUND(H17-CFS!H20,6),"") -> 0 | I23: =IFERROR(ROUND(I17-CFS!I20,6),"") -> 0 | J23: =IFERROR(ROUND(J17-CFS!J20,6),"") -> 0 | K23: =IFERROR(ROUND(K17-CFS!K20,6),"") -> 0 | ... O23: =IFERROR(ROUND(O17-CFS!O20,6),"") -> 0

Sheet ESOP Schedule
A1: SHARE-BASED PAYMENT (ESOP) SCHEDULE — Eternal Limited (INR Cr) | O1: =Data_Sources!$D$8&" | "&Data_Sources!$E$8&" | "&Data_Sources!$F$8 -> Eternal Q4FY26 consolidated statement of cash flows | Adjustments to reconcile PBT | https://b.zmtcdn.com/investor-relations/Eternal_Shareholders_Letter_Q4FY26_Results.pdf
A2: Line item | B2: Unit | C2: FY2023A | D2: FY2024A | E2: FY2025A | F2: FY2026A | G2: FY2027E | H2: FY2028E | I2: FY2029E | J2: FY2030E | K2: FY2031E | L2: FY2032E | M2: FY2033E | N2: FY2034E
A4: A. SHARE-BASED PAYMENT CHARGE
A5: ESOP charge to P&L | B5: INR Cr | D5: 515 | E5: 798 | F5: 819 | G5: =Assumptions!H85 -> 850 | H5: =Assumptions!I85 -> 880 | I5: =Assumptions!J85 -> 900 | J5: =Assumptions!K85 -> 920 | K5: =Assumptions!L85 -> 940 | L5: =Assumptions!M85 -> 960 | M5: =Assumptions!N85 -> 980 | N5: =Assumptions!O85 -> 1000
A6: Growth | B6: % | D6: =IFERROR(D5/C5-1,"") | E6: =IFERROR(E5/D5-1,"") -> 0.54951456 | F6: =IFERROR(F5/E5-1,"") -> 0.026315789 | G6: =IFERROR(G5/F5-1,"") -> 0.037851038 | H6: =IFERROR(H5/G5-1,"") -> 0.035294118 | I6: =IFERROR(I5/H5-1,"") -> 0.022727273 | J6: =IFERROR(J5/I5-1,"") -> 0.022222222 | K6: =IFERROR(K5/J5-1,"") -> 0.02173913 | ... N6: =IFERROR(N5/M5-1,"") -> 0.020408163
A8: B. INTENSITY
A9: as % of employee benefits expense | B9: % | C9: =IF($C$5="","",C5/'Cost Schedule'!D8) | D9: =IFERROR(D5/'Cost Schedule'!E8,"") -> 0.31042797 | E9: =IFERROR(E5/'Cost Schedule'!F8,"") -> 0.31196247 | F9: =IFERROR(F5/'Cost Schedule'!G8,"") -> 0.23161765 | G9: =IFERROR(G5/'Cost Schedule'!H8,"") -> 0.10965855 | H9: =IFERROR(H5/'Cost Schedule'!I8,"") -> 0.087772546 | I9: =IFERROR(I5/'Cost Schedule'!J8,"") -> 0.071401452 | J9: =IFERROR(J5/'Cost Schedule'!K8,"") -> 0.059452435 | K9: =IFERROR(K5/'Cost Schedule'!L8,"") -> 0.050191285 | ... N9: =IFERROR(N5/'Cost Schedule'!O8,"") -> 0.033650752
A10: as % of revenue from operations | B10: % | C10: =IF($C$5="","",C5/IS!D6) | D10: =IFERROR(D5/IS!E6,"") -> 0.042512795 | E10: =IFERROR(E5/IS!F6,"") -> 0.039421034 | F10: =IFERROR(F5/IS!G6,"") -> 0.015065117 | G10: =IFERROR(G5/IS!H6,"") -> 0.0065110848 | H10: =IFERROR(H5/IS!I6,"") -> 0.0048493001 | I10: =IFERROR(I5/IS!J6,"") -> 0.0036517896 | J10: =IFERROR(J5/IS!K6,"") -> 0.0028581169 | K10: =IFERROR(K5/IS!L6,"") -> 0.0023105737 | ... N10: =IFERROR(N5/IS!O6,"") -> 0.0014126018
A11: as % of adjusted EBITDA | B11: % | C11: =IF($C$5="","",C5/IS!D48) | D11: =IFERROR(D5/IS!E48,"") -> 1.3844086 | E11: =IFERROR(E5/IS!F48,"") -> 0.73957368 | F11: =IFERROR(F5/IS!G48,"") -> 0.68881413 | G11: =IFERROR(G5/IS!H48,"") -> 0.33550712 | H11: =IFERROR(H5/IS!I48,"") -> 0.16230247 | I11: =IFERROR(I5/IS!J48,"") -> 0.085222925 | J11: =IFERROR(J5/IS!K48,"") -> 0.052567178 | K11: =IFERROR(K5/IS!L48,"") -> 0.036426859 | ... N11: =IFERROR(N5/IS!O48,"") -> 0.018214216
A13: C. CHECK
A14: Check: charge vs IS share-based payment line (must be nil) | B14: INR Cr | C14: =IFERROR(ROUND(C5+IS!D55,6),"") -> 0 | D14: =IFERROR(ROUND(D5+IS!E55,6),"") -> 0 | E14: =IFERROR(ROUND(E5+IS!F55,6),"") -> 0 | F14: =IFERROR(ROUND(F5+IS!G55,6),"") -> 0 | G14: =IFERROR(ROUND(G5+IS!H55,6),"") -> 0 | H14: =IFERROR(ROUND(H5+IS!I55,6),"") -> 0 | I14: =IFERROR(ROUND(I5+IS!J55,6),"") -> 0 | J14: =IFERROR(ROUND(J5+IS!K55,6),"") -> 0 | ... N14: =IFERROR(ROUND(N5+IS!O55,6),"") -> 0

Sheet BS
A1: BALANCE SHEET — condensed, consolidated (INR Cr) | Q1: Source (linked to Data_Sources)
A2: Line item | B2: Unit | D2: FY2023A | E2: FY2024A | F2: FY2025A | G2: FY2026A | H2: FY2027E | I2: FY2028E | J2: FY2029E | K2: FY2030E | L2: FY2031E | M2: FY2032E | N2: FY2033E | O2: FY2034E | P2: Source / Note
A4: ASSETS | Q4: =Data_Sources!$D$9&" | "&Data_Sources!$E$9&" | "&Data_Sources!$F$9 -> Eternal Q4FY26 audited consolidated balance sheet | Annexure E | https://b.zmtcdn.com/investor-relations/Eternal_Shareholders_Letter_Q4FY26_Results.pdf
A5: Non-current assets | P5: Forecast from FA_Schedule (PPE roll-forward)
A6: Property, plant & equipment + CWIP | B6: INR Cr | D6: =FA_Schedule!C9 -> 216 | E6: =FA_Schedule!D9 -> 305 | F6: =FA_Schedule!E9 -> 1016 | G6: =FA_Schedule!F9 -> 2169 | H6: =FA_Schedule!G9 -> 4238.3 | I6: =FA_Schedule!H9 -> 5941.81 | J6: =FA_Schedule!I9 -> 7389.267 | K6: =FA_Schedule!J9 -> 8657.4869 | ... O6: =FA_Schedule!N9 -> 12010.339 | P6: Forecast from FA_Schedule (ROU roll-forward)
A7: Right-of-use assets | B7: INR Cr | D7: =FA_Schedule!C24 -> 427 | E7: =FA_Schedule!D24 -> 690 | F7: =FA_Schedule!E24 -> 1918 | G7: =FA_Schedule!F24 -> 4294 | H7: =FA_Schedule!G24 -> 6860.909 | I7: =FA_Schedule!H24 -> 9365.0467 | J7: =FA_Schedule!I24 -> 11836.324 | K7: =FA_Schedule!J24 -> 14292.956 | ... O7: =FA_Schedule!N24 -> 22696.493 | P7: Forecast from FA_Schedule (intangibles roll-forward)
A8: Goodwill & other intangibles | B8: INR Cr | D8: =FA_Schedule!C31 -> 5708 | E8: =FA_Schedule!D31 -> 5471 | F8: =FA_Schedule!E31 -> 6649 | G8: =FA_Schedule!F31 -> 6348 | H8: =FA_Schedule!G31 -> 6030.6 | I8: =FA_Schedule!H31 -> 5729.07 | J8: =FA_Schedule!I31 -> 5442.6165 | K8: =FA_Schedule!J31 -> 5170.4857 | ... O8: =FA_Schedule!N31 -> 4211.3929 | P8: Forecast: prior year + net change in cash from the CFS bridge
A9: Other non-current assets (FY25A–26A: audited total assets less disclosed lines; forecast held flat) | B9: INR Cr | D9: =D31-D6-D7-D8-D16 -> -1404 | E9: =E31-E6-E7-E8-E16 -> 1202 | F9: =F18-F6-F7-F8-F16 -> 1399 | G9: =G18-G6-G7-G8-G16 -> 867 | H9: =$G$9 -> 867 | I9: =$G$9 -> 867 | J9: =$G$9 -> 867 | K9: =$G$9 -> 867 | L9: =$G$9 -> 867 | M9: =$G$9 -> 867 | N9: =$G$9 -> 867 | O9: =$G$9 -> 867 | P9: Forecast from WC_Schedule (inventory days on COGS)
A10: Total non-current assets | B10: INR Cr | D10: =SUM(D6:D9) -> 4947 | E10: =SUM(E6:E9) -> 7668 | F10: =SUM(F6:F9) -> 10982 | G10: =SUM(G6:G9) -> 13678 | H10: =SUM(H6:H9) -> 17996.809 | I10: =SUM(I6:I9) -> 21902.927 | J10: =SUM(J6:J9) -> 25535.208 | K10: =SUM(K6:K9) -> 28987.929 | ... O10: =SUM(O6:O9) -> 39785.225 | P10: Forecast from WC_Schedule (receivable days)
A11: Current assets | P11: Forecast: balancing item so the condensed balance sheet ties
A12: Inventories | B12: INR Cr | D12: =WC_Schedule!D13 -> 83 | E12: =WC_Schedule!E13 -> 88 | F12: =WC_Schedule!F13 -> 176 | G12: =WC_Schedule!G13 -> 2181 | H12: =WC_Schedule!H13 -> 5947.2718 | I12: =WC_Schedule!I13 -> 8266.5674 | J12: =WC_Schedule!J13 -> 10832.312 | K12: =WC_Schedule!K13 -> 14142.499 | ... O12: =WC_Schedule!O13 -> 29950.643 | P12: Check: audited total assets FY25 35,623 / FY26 40,736
A13: Trade receivables | B13: INR Cr | D13: =WC_Schedule!D12 -> 457 | E13: =WC_Schedule!E12 -> 794 | F13: =WC_Schedule!F12 -> 1946 | G13: =WC_Schedule!G12 -> 1764 | H13: =WC_Schedule!H12 -> 4291.9431 | I13: =WC_Schedule!I12 -> 5966.1201 | J13: =WC_Schedule!J12 -> 8102.6138 | K13: =WC_Schedule!K12 -> 10582.694 | ... O13: =WC_Schedule!O12 -> 23273.872
A14: Other current assets | B14: INR Cr | D14: =WC_Schedule!D14 -> 4789 | E14: =WC_Schedule!E14 -> 2565 | F14: =WC_Schedule!F14 -> 5713 | G14: =WC_Schedule!G14 -> 5141 | H14: =WC_Schedule!H14 -> 11096.461 | I14: =WC_Schedule!I14 -> 15424.906 | J14: =WC_Schedule!J14 -> 19716.36 | K14: =WC_Schedule!K14 -> 25751.221 | ... O14: =WC_Schedule!O14 -> 56633.088
A15: Cash, bank balances & treasury investments (company cash-bridge basis) | B15: INR Cr | D15: 11323 | E15: 12241 | F15: 16806 | G15: 17972 | H15: =G15+CFS!H30 -> 5637.6315 | I15: =H15+CFS!I30 -> -5378.6029 | J15: =I15+CFS!J30 -> -13796.35 | K15: =J15+CFS!K30 -> -20244.157 | L15: =K15+CFS!L30 -> -19467.867 | M15: =L15+CFS!M30 -> -10789.257 | N15: =M15+CFS!N30 -> 6940.2003 | O15: =N15+CFS!O30 -> 31344.97 | P15: Forecast: prior year + PAT + share-based payment credited to equity. No dividends or buybacks assumed.
A16: Total current assets | B16: INR Cr | D16: =SUM(D12:D15) -> 16652 | E16: =SUM(E12:E15) -> 15688 | F16: =SUM(F12:F15) -> 24641 | G16: =SUM(G12:G15) -> 27058 | H16: =SUM(H12:H15) -> 26973.308 | I16: =SUM(I12:I15) -> 24278.991 | J16: =SUM(J12:J15) -> 24854.936 | K16: =SUM(K12:K15) -> 30232.256 | ... O16: =SUM(O12:O15) -> 141202.57 | P16: Forecast from Lease_Schedule (closing lease liability)
A17: TOTAL ASSETS | B17: INR Cr | D17: =D10+D16 -> 21599 | E17: =E10+E16 -> 23356 | F17: =F10+F16 -> 35623 | G17: =G10+G16 -> 40736 | H17: =H10+H16 -> 44970.117 | I17: =I10+I16 -> 46181.918 | J17: =J10+J16 -> 50390.144 | K17: =K10+K16 -> 59220.186 | ... O17: =O10+O16 -> 180987.8 | P17: Forecast from WC_Schedule (payable days on COGS)
A18: Memo: audited total assets (input) | B18: INR Cr | D18: MANUAL – OPEN | E18: MANUAL – OPEN | F18: 35623 | G18: 40736 | P18: Forecast from WC_Schedule (other current liabilities)
A19: EQUITY & LIABILITIES | Q19: =Data_Sources!$D$9&" | "&Data_Sources!$E$9&" | "&Data_Sources!$F$9 -> Eternal Q4FY26 audited consolidated balance sheet | Annexure E | https://b.zmtcdn.com/investor-relations/Eternal_Shareholders_Letter_Q4FY26_Results.pdf
A20: Equity
A21: Total equity | B21: INR Cr | D21: 19453 | E21: 20406 | F21: 30310 | G21: 30973 | H21: =G21+IS!H29+Assumptions!H85 -> 24366.374 | I21: =H21+IS!I29+Assumptions!I85 -> 17018.69 | J21: =I21+IS!J29+Assumptions!J85 -> 10858.236 | K21: =J21+IS!K29+Assumptions!K85 -> 8575.8184 | L21: =K21+IS!L29+Assumptions!L85 -> 13194.497 | M21: =L21+IS!M29+Assumptions!M85 -> 26872.436 | N21: =M21+IS!N29+Assumptions!N85 -> 50707.055 | O21: =N21+IS!O29+Assumptions!O85 -> 81389.196 | P21: Must be zero. Forecast years balance by construction via the 'Other assets (net, balancing)' line.
A22: Non-current liabilities | Q22: =Data_Sources!$D$10&" | "&Data_Sources!$E$10&" | "&Data_Sources!$F$10 -> Eternal Q4FY26 audited consolidated balance sheet | Annexure E | https://b.zmtcdn.com/investor-relations/Eternal_Shareholders_Letter_Q4FY26_Results.pdf
A23: Lease liabilities — non-current | B23: INR Cr | D23: =Lease_Schedule!D14 -> 351 | E23: =Lease_Schedule!E14 -> 588 | F23: =Lease_Schedule!F14 -> 1654 | G23: =Lease_Schedule!G14 -> 3833 | H23: =Lease_Schedule!H14 -> 6391.7895 | I23: =Lease_Schedule!I14 -> 9145.3646 | J23: =Lease_Schedule!J14 -> 12031.831 | K23: =Lease_Schedule!K14 -> 14966.813 | ... O23: =Lease_Schedule!O14 -> 23233.963
A24: Other non-current liabilities & provisions | B24: INR Cr | D24: 389 | E24: 279 | F24: 333 | G24: 258 | H24: =G24 -> 258 | I24: =G24 -> 258 | J24: =G24 -> 258 | K24: =G24 -> 258 | L24: =G24 -> 258 | M24: =G24 -> 258 | N24: =G24 -> 258 | O24: =G24 -> 258
A25: Total non-current liabilities | B25: INR Cr | D25: =SUM(D23:D24) -> 740 | E25: =SUM(E23:E24) -> 867 | F25: =SUM(F23:F24) -> 1987 | G25: =SUM(G23:G24) -> 4091 | H25: =SUM(H23:H24) -> 6649.7895 | I25: =SUM(I23:I24) -> 9403.3646 | J25: =SUM(J23:J24) -> 12289.831 | K25: =SUM(K23:K24) -> 15224.813 | ... O25: =SUM(O23:O24) -> 23491.963
A26: Current liabilities | Q26: =Data_Sources!$D$10&" | "&Data_Sources!$E$10&" | "&Data_Sources!$F$10 -> Eternal Q4FY26 audited consolidated balance sheet | Annexure E | https://b.zmtcdn.com/investor-relations/Eternal_Shareholders_Letter_Q4FY26_Results.pdf
A27: Lease liabilities — current | B27: INR Cr | D27: =Lease_Schedule!D17 -> 115 | E27: =Lease_Schedule!E17 -> 161 | F27: =Lease_Schedule!F17 -> 391 | G27: =Lease_Schedule!G17 -> 759 | H27: =Lease_Schedule!H17 -> 1265.6844 | I27: =Lease_Schedule!I17 -> 1810.9397 | J27: =Lease_Schedule!J17 -> 2382.5097 | K27: =Lease_Schedule!K17 -> 2963.6867 | ... O27: =Lease_Schedule!O17 -> 4600.7247
A28: Trade payables | B28: INR Cr | D28: =WC_Schedule!D18 -> 679 | E28: =WC_Schedule!E18 -> 886 | F28: =WC_Schedule!F18 -> 1536 | G28: =WC_Schedule!G18 -> 3010 | H28: =WC_Schedule!H18 -> 8234.6841 | I28: =WC_Schedule!I18 -> 11763.961 | J28: =WC_Schedule!J18 -> 16465.114 | K28: =WC_Schedule!K18 -> 21496.598 | ... O28: =WC_Schedule!O18 -> 47421.852
A29: Other current liabilities & provisions | B29: INR Cr | D29: =WC_Schedule!D19 -> 612 | E29: =WC_Schedule!E19 -> 1036 | F29: =WC_Schedule!F19 -> 1399 | G29: =WC_Schedule!G19 -> 1888 | H29: =WC_Schedule!H19 -> 4438.5845 | I29: =WC_Schedule!I19 -> 6169.9626 | J29: =WC_Schedule!J19 -> 8379.4531 | K29: =WC_Schedule!K19 -> 10944.269 | ... O29: =WC_Schedule!O19 -> 24069.063
A30: Total current liabilities | B30: INR Cr | D30: =SUM(D27:D29) -> 1406 | E30: =SUM(E27:E29) -> 2083 | F30: =SUM(F27:F29) -> 3326 | G30: =SUM(G27:G29) -> 5657 | H30: =SUM(H27:H29) -> 13938.953 | I30: =SUM(I27:I29) -> 19744.864 | J30: =SUM(J27:J29) -> 27227.077 | K30: =SUM(K27:K29) -> 35404.554 | ... O30: =SUM(O27:O29) -> 76091.639
A31: TOTAL EQUITY & LIABILITIES | B31: INR Cr | D31: =D21+D25+D30 -> 21599 | E31: =E21+E25+E30 -> 23356 | F31: =F21+F25+F30 -> 35623 | G31: =G21+G25+G30 -> 40721 | H31: =H21+H25+H30 -> 44955.117 | I31: =I21+I25+I30 -> 46166.918 | J31: =J21+J25+J30 -> 50375.144 | K31: =K21+K25+K30 -> 59205.186 | ... O31: =O21+O25+O30 -> 180972.8
A33: Balance check: Total assets − Total equity & liabilities (must be 0) | B33: INR Cr | D33: =ROUND(D17-D31,2) -> 0 | E33: =ROUND(E17-E31,2) -> 0 | F33: =ROUND(F17-F31,2) -> 0 | G33: =ROUND(G17-G31,2) -> 15 | H33: =ROUND(H17-H31,2) -> 15 | I33: =ROUND(I17-I31,2) -> 15 | J33: =ROUND(J17-J31,2) -> 15 | K33: =ROUND(K17-K31,2) -> 15 | ... O33: =ROUND(O17-O31,2) -> 15
A34: Change in imbalance vs prior year (forecast integrity, must be 0) | B34: INR Cr | E34: =ROUND(E33-D33,2) -> 0 | F34: =ROUND(F33-E33,2) -> 0 | G34: =ROUND(G33-F33,2) -> 15 | H34: =ROUND(H33-G33,2) -> 0 | I34: =ROUND(I33-H33,2) -> 0 | J34: =ROUND(J33-I33,2) -> 0 | K34: =ROUND(K33-J33,2) -> 0 | L34: =ROUND(L33-K33,2) -> 0 | ... O34: =ROUND(O33-N33,2) -> 0
A35: MEMO
A36: Net working capital (ex-cash) | B36: INR Cr | D36: =(D12+D13+D14)-(D28+D29) -> 4038 | E36: =(E12+E13+E14)-(E28+E29) -> 1525 | F36: =(F12+F13+F14)-(F28+F29) -> 4900 | G36: =(G12+G13+G14)-(G28+G29) -> 4188 | H36: =(H12+H13+H14)-(H28+H29) -> 8662.4075 | I36: =(I12+I13+I14)-(I28+I29) -> 11723.67 | J36: =(J12+J13+J14)-(J28+J29) -> 13806.719 | K36: =(K12+K13+K14)-(K28+K29) -> 18035.547 | ... O36: =(O12+O13+O14)-(O28+O29) -> 38366.689
A37: Current ratio | B37: x | D37: =IFERROR(D16/D30,"") -> 11.843528 | E37: =IFERROR(E16/E30,"") -> 7.531445 | F37: =IFERROR(F16/F30,"") -> 7.4085989 | G37: =IFERROR(G16/G30,"") -> 4.7831006 | H37: =IFERROR(H16/H30,"") -> 1.9351029 | I37: =IFERROR(I16/I30,"") -> 1.2296358 | J37: =IFERROR(J16/J30,"") -> 0.91287567 | K37: =IFERROR(K16/K30,"") -> 0.85390869 | ... O37: =IFERROR(O16/O30,"") -> 1.855691
A38: Net cash / (debt) including lease liabilities | B38: INR Cr | D38: =D15-D23-D27 -> 10857 | E38: =E15-E23-E27 -> 11492 | F38: =F15-F23-F27 -> 14761 | G38: =G15-G23-G27 -> 13380 | H38: =H15-H23-H27 -> -2019.8424 | I38: =I15-I23-I27 -> -16334.907 | J38: =J15-J23-J27 -> -28210.691 | K38: =K15-K23-K27 -> -38174.657 | ... O38: =O15-O23-O27 -> 3510.2819

Sheet CFS
A1: CASH FLOW STATEMENT — Eternal Limited, consolidated (INR Cr). ANALYST BRIDGE, not the reported Ind AS statement: historical columns close to BS cash through a disclosed residual (row 27); forecast is fully derived. | Q1: Source (linked to Data_Sources)
A2: Line item | B2: Unit | D2: FY2023A | E2: FY2024A | F2: FY2025A | G2: FY2026A | H2: FY2027E | I2: FY2028E | J2: FY2029E | K2: FY2030E | L2: FY2031E | M2: FY2032E | N2: FY2033E | O2: FY2034E | P2: Source / Note
A4: A. CASH FLOW FROM OPERATING ACTIVITIES | B4: INR Cr | Q4: =Data_Sources!$D$17&" | "&Data_Sources!$E$17&" | "&Data_Sources!$F$17 -> Eternal Q4FY26 shareholders' letter | Annexure A — cash (burn) / surplus bridge | https://b.zmtcdn.com/investor-relations/Eternal_Shareholders_Letter_Q4FY26_Results.pdf
A5: Revenue from operations (reported, Ind AS) — memo | B5: INR Cr | D5: =IS!D6 -> 7079 | E5: =IS!E6 -> 12114 | F5: =IS!F6 -> 20243 | G5: =IS!G6 -> 54364 | H5: =IS!H6 -> 130546.6 | I5: =IS!I6 -> 181469.49 | J5: =IS!J6 -> 246454.5 | K5: =IS!K6 -> 321890.27 | ... O5: =IS!O6 -> 707913.6
A6: Profit before tax (PBT) | B6: INR Cr | D6: =IS!D26 -> -1014 | E6: =IS!E26 -> 291 | F6: =IS!F26 -> 697 | G6: =IS!G26 -> 615 | H6: =IS!H26 -> -7456.6258 | I6: =IS!I26 -> -8227.6845 | J6: =IS!J26 -> -7060.4536 | K6: =IS!K26 -> -3202.4177 | ... O6: =IS!O26 -> 39666.097
A7: Add: Depreciation & amortisation (non-cash) | B7: INR Cr | D7: =-IS!D19 -> 437 | E7: =-IS!E19 -> 526 | F7: =-IS!F19 -> 863 | G7: =-IS!G19 -> 1597 | H7: =-IS!H19 -> 2838.1476 | I7: =-IS!I19 -> 4122.4038 | J7: =-IS!J19 -> 5286.4737 | K7: =-IS!K19 -> 6369.0036 | ... O7: =-IS!O19 -> 9782.1131
A8: Add: Finance costs (reclassified to financing) | B8: INR Cr | D8: =-IS!D24 -> 49 | E8: =-IS!E24 -> 72 | F8: =-IS!F24 -> 154 | G8: =-IS!G24 -> 392 | H8: =-IS!H24 -> 495.51725 | I8: =-IS!I24 -> 826.30888 | J8: =-IS!J24 -> 1182.2817 | K8: =-IS!K24 -> 1555.4344 | ... O8: =-IS!O24 -> 2850.3063
A9: Less: Other income (reclassified to investing) | B9: INR Cr | D9: =-IS!D23 -> -682 | E9: =-IS!E23 -> -847 | F9: =-IS!F23 -> -1077 | G9: =-IS!G23 -> -1396 | H9: =-IS!H23 -> -1168.18 | I9: =-IS!I23 -> -366.44605 | J9: =-IS!J23 -> 349.60919 | K9: =-IS!K23 -> 896.76274 | ... O9: =-IS!O23 -> -451.11302
A10: Add: Share-based payment expense (non-cash) | B10: INR Cr | D10: =N('ESOP Schedule'!C5) -> 0 | E10: =N('ESOP Schedule'!D5) -> 515 | F10: =N('ESOP Schedule'!E5) -> 798 | G10: =N('ESOP Schedule'!F5) -> 819 | H10: =N('ESOP Schedule'!G5) -> 850 | I10: =N('ESOP Schedule'!H5) -> 880 | J10: =N('ESOP Schedule'!I5) -> 900 | K10: =N('ESOP Schedule'!J5) -> 920 | ... O10: =N('ESOP Schedule'!N5) -> 1000
A11: Operating profit before working capital changes | B11: INR Cr | D11: =SUM(D6:D10) -> -1210 | E11: =SUM(E6:E10) -> 557 | F11: =SUM(F6:F10) -> 1435 | G11: =SUM(G6:G10) -> 2027 | H11: =SUM(H6:H10) -> -4441.141 | I11: =SUM(I6:I10) -> -2765.4179 | J11: =SUM(J6:J10) -> 657.91101 | K11: =SUM(K6:K10) -> 6538.783 | ... O11: =SUM(O6:O10) -> 52847.403 | P11: Forecast from WC_Schedule row 24 (change in net working capital); FY26A per the company's disclosed cash bridge
A12: Memo: as % of reported revenue | B12: % | D12: =IFERROR(D11/D5,"") -> -0.1709281 | E12: =IFERROR(E11/E5,"") -> 0.045979858 | F12: =IFERROR(F11/F5,"") -> 0.070888702 | G12: =IFERROR(G11/G5,"") -> 0.037285704 | H12: =IFERROR(H11/H5,"") -> -0.034019583 | I12: =IFERROR(I11/I5,"") -> -0.015239024 | J12: =IFERROR(J11/J5,"") -> 0.0026695029 | K12: =IFERROR(K11/K5,"") -> 0.020313702 | ... O12: =IFERROR(O11/O5,"") -> 0.074652335
A13: Less: Tax paid | B13: INR Cr | D13: MANUAL – OPEN | E13: MANUAL – OPEN | F13: MANUAL – OPEN | G13: MANUAL – OPEN | H13: =IS!H27 -> 0 | I13: =IS!I27 -> 0 | J13: =IS!J27 -> 0 | K13: =IS!K27 -> 0 | L13: =IS!L27 -> 0 | M13: =IS!M27 -> 0 | N13: =IS!N27 -> -4474.9843 | O13: =IS!O27 -> -9983.9566
A14: Less: (Increase) / decrease in net working capital | B14: INR Cr | E14: 118 | F14: -1093 | G14: -1228 | H14: =-WC_Schedule!H24 -> -4474.4075 | I14: =-WC_Schedule!I24 -> -3061.2626 | J14: =-WC_Schedule!J24 -> -2083.0488 | K14: =-WC_Schedule!K24 -> -4228.8277 | L14: =-WC_Schedule!L24 -> -4052.4457 | M14: =-WC_Schedule!M24 -> -5099.9416 | N14: =-WC_Schedule!N24 -> -5832.9648 | O14: =-WC_Schedule!O24 -> -5345.7905
A15: Add / (less): Other operating items | B15: INR Cr | E15: 13 | F15: 276 | G15: -20 | H15: =Assumptions!H97 -> 0 | I15: =Assumptions!I97 -> 0 | J15: =Assumptions!J97 -> 0 | K15: =Assumptions!K97 -> 0 | L15: =Assumptions!L97 -> 0 | M15: =Assumptions!M97 -> 0 | N15: =Assumptions!N97 -> 0 | O15: =Assumptions!O97 -> 0
A16: NET CASH FROM OPERATING ACTIVITIES | B16: INR Cr | D16: =SUM(D11,D13:D15) -> -1210 | E16: =SUM(E11,E13:E15) -> 688 | F16: =SUM(F11,F13:F15) -> 618 | G16: =SUM(G11,G13:G15) -> 779 | H16: =SUM(H11,H13:H15) -> -8915.5485 | I16: =SUM(I11,I13:I15) -> -5826.6805 | J16: =SUM(J11,J13:J15) -> -1425.1378 | K16: =SUM(K11,K13:K15) -> 2309.9552 | ... O16: =SUM(O11,O13:O15) -> 37517.656
A18: B. CASH FLOW FROM INVESTING ACTIVITIES | B18: INR Cr | Q18: =Data_Sources!$D$17&" | "&Data_Sources!$E$17&" | "&Data_Sources!$F$17 -> Eternal Q4FY26 shareholders' letter | Annexure A — cash (burn) / surplus bridge | https://b.zmtcdn.com/investor-relations/Eternal_Shareholders_Letter_Q4FY26_Results.pdf
A19: Purchase of PPE & intangibles (capital expenditure) | B19: INR Cr | D19: =IFERROR(-FA_Schedule!C16,"") -> 0 | E19: =IFERROR(-FA_Schedule!D16,"") -> -202 | F19: =IFERROR(-FA_Schedule!E16,"") -> -931 | G19: =IFERROR(-FA_Schedule!F16,"") -> -1746 | H19: =IFERROR(-FA_Schedule!G16,"") -> -3200 | I19: =IFERROR(-FA_Schedule!H16,"") -> -3500 | J19: =IFERROR(-FA_Schedule!I16,"") -> -3800 | K19: =IFERROR(-FA_Schedule!J16,"") -> -4100 | ... O19: =IFERROR(-FA_Schedule!N16,"") -> -4800
A20: Treasury income received | B20: INR Cr | D20: ='Other Income Schedule '!D17 -> 0 | E20: ='Other Income Schedule '!E17 -> 618 | F20: ='Other Income Schedule '!F17 -> 820 | G20: ='Other Income Schedule '!G17 -> 953 | H20: ='Other Income Schedule '!H17 -> 1168.18 | I20: ='Other Income Schedule '!I17 -> 366.44605 | J20: ='Other Income Schedule '!J17 -> -349.60919 | K20: ='Other Income Schedule '!K17 -> -896.76274 | ... O20: ='Other Income Schedule '!O17 -> 451.11302
A21: NET CASH USED IN INVESTING ACTIVITIES | B21: INR Cr | D21: =SUM(D19:D20) -> 0 | E21: =SUM(E19:E20) -> 416 | F21: =SUM(F19:F20) -> -111 | G21: =SUM(G19:G20) -> -793 | H21: =SUM(H19:H20) -> -2031.82 | I21: =SUM(I19:I20) -> -3133.554 | J21: =SUM(J19:J20) -> -4149.6092 | K21: =SUM(K19:K20) -> -4996.7627 | ... O21: =SUM(O19:O20) -> -4348.887
A23: C. CASH FLOW FROM FINANCING ACTIVITIES | Q23: =Data_Sources!$D$17&" | "&Data_Sources!$E$17&" | "&Data_Sources!$F$17 -> Eternal Q4FY26 shareholders' letter | Annexure A — cash (burn) / surplus bridge | https://b.zmtcdn.com/investor-relations/Eternal_Shareholders_Letter_Q4FY26_Results.pdf
A24: Repayment of lease liabilities — principal | B24: INR Cr | D24: =IF(Lease_Schedule!D22="","n.a.",-Lease_Schedule!D22) -> n.a. | E24: =IF(Lease_Schedule!E22="","n.a.",-Lease_Schedule!E22) -> -185 | F24: =IF(Lease_Schedule!F22="","n.a.",-Lease_Schedule!F22) -> -209 | G24: =IF(Lease_Schedule!G22="","n.a.",-Lease_Schedule!G22) -> -471 | H24: =IF(Lease_Schedule!H22="","n.a.",-Lease_Schedule!H22) -> -891.48275 | I24: =IF(Lease_Schedule!I22="","n.a.",-Lease_Schedule!I22) -> -1229.6911 | J24: =IF(Lease_Schedule!J22="","n.a.",-Lease_Schedule!J22) -> -1660.7183 | K24: =IF(Lease_Schedule!K22="","n.a.",-Lease_Schedule!K22) -> -2205.5656 | ... O24: =IF(Lease_Schedule!O22="","n.a.",-Lease_Schedule!O22) -> -5913.6937
A25: Interest paid (lease interest + other finance costs) | B25: INR Cr | D25: =IFERROR(-Lease_Schedule!D25,"") -> -49 | E25: =IFERROR(-Lease_Schedule!E25,"") -> -72 | F25: =IFERROR(-Lease_Schedule!F25,"") -> -154 | G25: =IFERROR(-Lease_Schedule!G25,"") -> -392 | H25: =IFERROR(-Lease_Schedule!H25,"") -> -495.51725 | I25: =IFERROR(-Lease_Schedule!I25,"") -> -826.30888 | J25: =IFERROR(-Lease_Schedule!J25,"") -> -1182.2817 | K25: =IFERROR(-Lease_Schedule!K25,"") -> -1555.4344 | ... O25: =IFERROR(-Lease_Schedule!O25,"") -> -2850.3063
A26: Net bank borrowings / (repayment) | B26: INR Cr | D26: 0 | E26: 0 | F26: 0 | G26: 0 | H26: 0 | I26: 0 | J26: 0 | K26: 0 | L26: 0 | M26: 0 | N26: 0 | O26: 0
A27: Historical: balancing residual to reported closing cash (NOT a reported line – MANUAL – OPEN); forecast: equity issuance (nil) | B27: INR Cr | E27: =BS!E15-E31-(E16+E21+SUM(E24:E26)) -> 71 | F27: =BS!F15-F31-(F16+F21+SUM(F24:F26)) -> 4421 | G27: =BS!G15-G31-(G16+G21+SUM(G24:G26)) -> 2043 | H27: =0 -> 0 | I27: =0 -> 0 | J27: =0 -> 0 | K27: =0 -> 0 | L27: =0 -> 0 | M27: =0 -> 0 | N27: =0 -> 0 | O27: =0 -> 0
A28: NET CASH FROM FINANCING ACTIVITIES | B28: INR Cr | D28: =SUM(D24:D27) -> -49 | E28: =SUM(E24:E27) -> -186 | F28: =SUM(F24:F27) -> 4058 | G28: =SUM(G24:G27) -> 1180 | H28: =SUM(H24:H27) -> -1387 | I28: =SUM(I24:I27) -> -2056 | J28: =SUM(J24:J27) -> -2843 | K28: =SUM(K24:K27) -> -3761 | ... O28: =SUM(O24:O27) -> -8764
A30: NET INCREASE / (DECREASE) IN CASH | B30: INR Cr | D30: =D16+D21+D28 -> -1259 | E30: =E16+E21+E28 -> 918 | F30: =F16+F21+F28 -> 4565 | G30: =G16+G21+G28 -> 1166 | H30: =H16+H21+H28 -> -12334.369 | I30: =I16+I21+I28 -> -11016.234 | J30: =J16+J21+J28 -> -8417.747 | K30: =K16+K21+K28 -> -6447.8075 | ... O30: =O16+O21+O28 -> 24404.769
A31: Opening cash & treasury investments | B31: INR Cr | E31: =D32 -> 11323 | F31: =E32 -> 12241 | G31: =F32 -> 16806 | H31: =G32 -> 17972 | I31: =H32 -> 5637.6315 | J31: =I32 -> -5378.6029 | K31: =J32 -> -13796.35 | L31: =K32 -> -20244.157 | ... O31: =N32 -> 6940.2003
A32: CLOSING CASH & TREASURY INVESTMENTS | B32: INR Cr | D32: =BS!D15 -> 11323 | E32: =BS!E15 -> 12241 | F32: =BS!F15 -> 16806 | G32: =BS!G15 -> 17972 | H32: =H31+H30 -> 5637.6315 | I32: =I31+I30 -> -5378.6029 | J32: =J31+J30 -> -13796.35 | K32: =K31+K30 -> -20244.157 | L32: =L31+L30 -> -19467.867 | M32: =M31+M30 -> -10789.257 | N32: =N31+N30 -> 6940.2003 | O32: =O31+O30 -> 31344.97
A34: Memo: difference vs BS cash & treasury line | B34: INR Cr | D34: =IFERROR(ROUND(D32-BS!D15,6),"") -> 0 | E34: =IFERROR(ROUND(E32-BS!E15,6),"") -> 0 | F34: =IFERROR(ROUND(F32-BS!F15,6),"") -> 0 | G34: =IFERROR(ROUND(G32-BS!G15,6),"") -> 0 | H34: =IFERROR(ROUND(H32-BS!H15,6),"") -> 0 | I34: =IFERROR(ROUND(I32-BS!I15,6),"") -> 0 | J34: =IFERROR(ROUND(J32-BS!J15,6),"") -> 0 | K34: =IFERROR(ROUND(K32-BS!K15,6),"") -> 0 | ... O34: =IFERROR(ROUND(O32-BS!O15,6),"") -> 0
A35: Memo: free cash flow (CFO less capex) | B35: INR Cr | D35: =IFERROR(D16-FA_Schedule!C16,"") -> -1210 | E35: =IFERROR(E16-FA_Schedule!D16,"") -> 486 | F35: =IFERROR(F16-FA_Schedule!E16,"") -> -313 | G35: =IFERROR(G16-FA_Schedule!F16,"") -> -967 | H35: =IFERROR(H16-FA_Schedule!G16,"") -> -12115.549 | I35: =IFERROR(I16-FA_Schedule!H16,"") -> -9326.6805 | J35: =IFERROR(J16-FA_Schedule!I16,"") -> -5225.1378 | K35: =IFERROR(K16-FA_Schedule!J16,"") -> -1790.0448 | ... O35: =IFERROR(O16-FA_Schedule!N16,"") -> 32717.656

Sheet OpMetrics
A1: OPERATING METRICS — KPIs and unit economics by business | Q1: =Data_Sources!$D$31&" | "&Data_Sources!$E$31&" | "&Data_Sources!$F$31 -> Eternal Q4FY25 and Q4FY26 shareholders' letters | Annexure A — operating metrics (quarterly figures) | https://b.zmtcdn.com/investor-relations/Eternal_Shareholders_Letter_Q4FY26_Results.pdf
A2: Metric | B2: Unit | D2: FY2023A | E2: FY2024A | F2: FY2025A | G2: FY2026A | H2: FY2027E | I2: FY2028E | J2: FY2029E | K2: FY2030E | L2: FY2031E | M2: FY2032E | N2: FY2033E | O2: FY2034E | P2: Source / Note
A4: A. QUICK COMMERCE (BLINKIT)
A5: Dark stores (end of year) | B5: # | D5: ='Revenue Schedule'!C60 -> 377 | E5: ='Revenue Schedule'!D60 -> 526 | F5: ='Revenue Schedule'!E60 -> 1301 | G5: ='Revenue Schedule'!F60 -> 2243 | H5: ='Revenue Schedule'!G60 -> 3343 | I5: ='Revenue Schedule'!H60 -> 4543 | J5: ='Revenue Schedule'!I60 -> 5843 | K5: ='Revenue Schedule'!J60 -> 7243 | ... O5: ='Revenue Schedule'!N60 -> 13343 | P5: Q4FY25 / Q4FY26 letters: 1,301 → 2,243 stores
A6: Net new stores added | B6: # | E6: =E5-D5 -> 149 | F6: =F5-E5 -> 775 | G6: =G5-F5 -> 942 | H6: =H5-G5 -> 1100 | I6: =I5-H5 -> 1200 | J6: =J5-I5 -> 1300 | K6: =K5-J5 -> 1400 | L6: =L5-K5 -> 1450 | ... O6: =O5-N5 -> 1600
A8: NOV per store per day | B8: INR '000 | E8: ='Revenue Schedule'!D66 -> 672 | F8: ='Revenue Schedule'!E66 -> 766 | G8: ='Revenue Schedule'!F66 -> 756 | H8: ='Revenue Schedule'!G66 -> 1200 | I8: ='Revenue Schedule'!H66 -> 1200 | J8: ='Revenue Schedule'!I66 -> 1250 | K8: ='Revenue Schedule'!J66 -> 1300 | L8: ='Revenue Schedule'!K66 -> 1350 | ... O8: ='Revenue Schedule'!N66 -> 1450
A9: NOV per store per year | B9: INR Cr | E9: =E8*365/10000 -> 24.528 | F9: =F8*365/10000 -> 27.959 | G9: =G8*365/10000 -> 27.594 | H9: =H8*365/10000 -> 43.8 | I9: =I8*365/10000 -> 43.8 | J9: =J8*365/10000 -> 45.625 | K9: =K8*365/10000 -> 47.45 | L9: =L8*365/10000 -> 49.275 | ... O9: =O8*365/10000 -> 52.925
A10: Adjusted EBITDA per store (on closing stores) | B10: INR Cr | D10: =IS!D44/D5 -> -1.4907162 | E10: =IS!E44/E5 -> -0.73003802 | F10: =IS!F44/F5 -> -0.22444274 | G10: =IS!G44/G5 -> -0.12349532 | H10: =IS!H44/H5 -> 0.18296949 | I10: =IS!I44/I5 -> 0.57022914 | J10: =IS!J44/J5 -> 1.0137371 | K10: =IS!K44/K5 -> 1.5002468 | ... O10: =IS!O44/O5 -> 2.985108
A12: B. FOOD DELIVERY (ZOMATO)
A13: NOV | B13: INR Cr | D13: ='Revenue Schedule'!C42 -> 22501 | E13: ='Revenue Schedule'!D42 -> 27478 | F13: ='Revenue Schedule'!E42 -> 32862 | G13: ='Revenue Schedule'!F42 -> 37993 | H13: ='Revenue Schedule'!G42 -> 44994.96 | I13: ='Revenue Schedule'!H42 -> 53302.2 | J13: ='Revenue Schedule'!I42 -> 63118.71 | K13: ='Revenue Schedule'!J42 -> 74745.92 | ... O13: ='Revenue Schedule'!N42 -> 142112.88
A14: Take rate (adjusted revenue % of NOV) | B14: % | D14: ='Revenue Schedule'!C52 -> 0.27318786 | E14: ='Revenue Schedule'!D52 -> 0.28357231 | F14: ='Revenue Schedule'!E52 -> 0.28659242 | G14: ='Revenue Schedule'!F52 -> 0.30789882 | H14: ='Revenue Schedule'!G52 -> 0.315 | I14: ='Revenue Schedule'!H52 -> 0.32 | J14: ='Revenue Schedule'!I52 -> 0.325 | K14: ='Revenue Schedule'!J52 -> 0.33 | ... O14: ='Revenue Schedule'!N52 -> 0.33
A15: Adjusted EBITDA margin (% of NOV) | B15: % | D15: =Assumptions!D49 -> 0 | E15: =Assumptions!E49 -> 0 | F15: =Assumptions!F49 -> 0 | G15: =Assumptions!G49 -> 0.053088727 | H15: =Assumptions!H49 -> 0.056 | I15: =Assumptions!I49 -> 0.058 | J15: =Assumptions!J49 -> 0.06 | K15: =Assumptions!K49 -> 0.06 | ... O15: =Assumptions!O49 -> 0.06
A17: C. GROUP
A18: B2C NOV | B18: INR Cr | D18: ='Revenue Schedule'!C16 -> 28191 | E18: ='Revenue Schedule'!D16 -> 41206 | F18: ='Revenue Schedule'!E16 -> 61852 | G18: ='Revenue Schedule'!F16 -> 95960 | H18: ='Revenue Schedule'!G16 -> 180486.96 | I18: ='Revenue Schedule'!H16 -> 243901.3 | J18: ='Revenue Schedule'!I16 -> 323671.65 | K18: ='Revenue Schedule'!J16 -> 415920.28 | ... O18: ='Revenue Schedule'!N16 -> 880924.33
A19: B2C NOV (US$ bn; INR Cr × 10 ÷ FX in Assumptions!B159 ÷ 1,000) | B19: US$ bn | D19: =D18*10/Assumptions!$B$159/1000 -> 3.0642391 | E19: =E18*10/Assumptions!$B$159/1000 -> 4.478913 | F19: =F18*10/Assumptions!$B$159/1000 -> 6.7230435 | G19: =G18*10/Assumptions!$B$159/1000 -> 10.430435 | H19: =H18/92/1000 -> 1.9618148 | I19: =I18/92/1000 -> 2.651101 | J19: =J18/92/1000 -> 3.5181701 | K19: =K18/92/1000 -> 4.5208727 | L19: =L18/92/1000 -> 5.6390316 | M19: =M18/92/1000 -> 6.8867623 | N19: =N18/92/1000 -> 8.2771762 | O19: =O18/92/1000 -> 9.5752645 | P19: ="FY26A B2C NOV US$ "&TEXT(G19,"0.00")&" bn; Q4FY26 letter (Data_Sources row 18) cites the $10bn milestone and a $20bn ambition within two years." -> FY26A B2C NOV US$ 10.43 bn; Q4FY26 letter (Data_Sources row 18) cites the $10bn milestone and a $20bn ambition within two years.
A20: Quick commerce share of B2C NOV | B20: % | D20: ='Revenue Schedule'!C56/D18 -> 0.20183747 | E20: ='Revenue Schedule'!D56/E18 -> 0.25489006 | F20: ='Revenue Schedule'!E56/F18 -> 0.36168596 | G20: ='Revenue Schedule'!F56/G18 -> 0.50612755 | H20: ='Revenue Schedule'!G56/H18 -> 0.67779633 | I20: ='Revenue Schedule'!H56/I18 -> 0.70808726 | J20: ='Revenue Schedule'!I56/J18 -> 0.73200919 | K20: ='Revenue Schedule'!J56/K18 -> 0.74645398 | ... O20: ='Revenue Schedule'!N56/O18 -> 0.75357014
A21: Adjusted EBITDA as % of B2C NOV | B21: % | D21: =IS!D48/D18 -> -0.027774822 | E21: =IS!E48/E18 -> 0.0090278115 | F21: =IS!F48/F18 -> 0.017444868 | G21: =IS!G48/G18 -> 0.012390579 | H21: =IS!H48/H18 -> 0.014036905 | I21: =IS!I48/I18 -> 0.022230203 | J21: =IS!J48/J18 -> 0.03262732 | K21: =IS!K48/K18 -> 0.042078772 | ... O21: =IS!O48/O18 -> 0.062323368
A22: Adjusted revenue per employee-equivalent cost rupee | B22: x | D22: ='Revenue Schedule'!C27/'Cost Schedule'!D8 -> 5.9337884 | E22: ='Revenue Schedule'!D27/'Cost Schedule'!E8 -> 8.164557 | F22: ='Revenue Schedule'!E27/'Cost Schedule'!F8 -> 8.4429242 | G22: ='Revenue Schedule'!F27/'Cost Schedule'!G8 -> 15.809672 | H22: ='Revenue Schedule'!G27/'Cost Schedule'!H8 -> 17.21438 | I22: ='Revenue Schedule'!H27/'Cost Schedule'!I8 -> 18.489278 | J22: ='Revenue Schedule'!I27/'Cost Schedule'!J8 -> 19.96331 | K22: ='Revenue Schedule'!J27/'Cost Schedule'!K8 -> 21.231304 | ... O22: ='Revenue Schedule'!N27/'Cost Schedule'!O8 -> 24.296125
A25: D. BLINKIT STORE-LEVEL UNIT ECONOMICS AND COHORT PAYBACK
A26: Added the review. The model prices Blinkit off group-average EBITDA per store, which blends mature and immature vintages. A single dark store is the unit of capital allocation here if it does not pay back, store growth destroys value however good the group average looks.
A28: Capex per net new dark store | B28: INR Cr | C28: =Assumptions!K111 -> 2.5
A29: Right-of-use asset / lease liability per new store | B29: INR Cr | C29: =Assumptions!B125 -> 3.2632696
A30: Total invested capital per new store | B30: INR Cr | C30: =C28+C29 -> 5.7632696
A32: Mature NOV per store per day (FY2034E steady state) | B32: INR '000 | C32: =Assumptions!O20 -> 1450
A33: Mature NOV per store per year | B33: INR Cr | C33: =C32*365/10000 -> 52.925
A35: Steady-state Adjusted EBITDA margin (% of NOV) | B35: % | C35: =Assumptions!O50 -> 0.06
A36: Mature Adjusted EBITDA per store per year | B36: INR Cr | C36: =C33*C35 -> 3.1755
A38: Returns at maturity
A39: Simple payback on store capex only | B39: years | C39: =C28/C36 -> 0.78727759
A40: Simple payback on total invested capital (capex plus lease) | B40: years | C40: =C30/C36 -> 1.8149172
A41: Pre-tax cash return on invested capital at maturity | B41: % | C41: =C36/C30 -> 0.55098932
A42: Post-tax return at the terminal effective tax rate | B42: % | C42: =C41*(1-Assumptions!O91) -> 0.41230531
A44: Spread over WACC | B44: pp | C44: =C42-DCF!B3 -> 0.26516784
A46: Maturity ramp for a single store cohort
C47: Year 1 | D47: Year 2 | E47: Year 3 | F47: Year 4+
A48: % of mature throughput achieved | B48: % | C48: =Assumptions!B163 -> 0.5 | D48: =Assumptions!C163 -> 0.75 | E48: =Assumptions!D163 -> 0.9 | F48: =Assumptions!E163 -> 1
A49: Adjusted EBITDA per store | B49: INR Cr | C49: =$C$36*C48 -> 1.58775 | D49: =$C$36*D48 -> 2.381625 | E49: =$C$36*E48 -> 2.85795 | F49: =$C$36*F48 -> 3.1755
A50: Cumulative Adjusted EBITDA per store | B50: INR Cr | C50: =C49 -> 1.58775 | D50: =C50+D49 -> 3.969375 | E50: =D50+E49 -> 6.827325 | F50: =E50+F49 -> 10.002825
A51: Cumulative as % of invested capital per store | B51: % | C51: =C50/$C$30 -> 0.27549466 | D51: =D50/$C$30 -> 0.68873665 | E51: =E50/$C$30 -> 1.184627 | F51: =F50/$C$30 -> 1.7356163
A53: Cash-on-cash payback including the ramp | B53: years | C53: =IF(C50>=$C$30,$C$30/C49,IF(D50>=$C$30,1+($C$30-C50)/D49,IF(E50>=$C$30,2+($C$30-D50)/E49,IF(F50>=$C$30,3+($C$30-E50)/F49,"beyond year 4")))) -> 2.6276858
A54: Stores that must be added FY2027E-FY2034E to hit the model's FY2034E count | B54: # | C54: =SUM(Assumptions!H18:O18) -> 11100
A55: Cumulative store capex implied (undiscounted) | B55: INR Cr | C55: =C54*C28 -> 27750
A57: READ-THROUGH ON STORE ECONOMICS
A58: ="6. A mature store returns "&TEXT(C42,"0%")&" post-tax on "&TEXT(C30,"0.0")&" Cr of invested capital and pays back in "&TEXT(C53,"0.0")&" years including the ramp. That is the whole bull case in one line: the rollout is self-funding long before the model's terminal year." -> 6. A mature store returns 41% post-tax on 5.8 Cr of invested capital and pays back in 2.6 years including the ramp. That is the whole bull case in one line: the rollout is self-funding long before the model's terminal year.
A59: ="7. It is also the bear case: a "&TEXT(C42,"0%")&" post-tax return on "&TEXT(C30,"0.00")&" Cr invested with a "&TEXT(C53,"0.0")&"-year payback is implausibly high for physical retail." -> 7. It is also the bear case: a 41% post-tax return on 5.76 Cr invested with a 2.6-year payback is implausibly high for physical retail.
A60: 8. Test to run: at what steady-state margin does a store still clear WACC? Roughly 0.5% of NOV. So the investment case does not depend on Blinkit hitting 6.0% — it depends on whether the store count can be built at all. That reframes the risk from margin risk to execution and competition risk.
A61: 9. Caveat on this block: it assumes a mature store, terminal-year drivers and no cannibalisation between stores as density increases. The group-average EBITDA per store on row 9 is the blended reality and will always sit below these numbers while the store base is growing.
A62: READ-THROUGH
A63: 1. Quick commerce overtook food delivery as the largest B2C business during FY26 and is ~51% of B2C NOV; by FY30E the model has it at over 60%. The equity story is now a quick-commerce story with a cash-generative food delivery business attached.
A64: ="2. Store productivity is the swing factor. NOV per store per day moved "&TEXT('Revenue Schedule'!E66,"#,##0")&"k (FY25A) to "&TEXT('Revenue Schedule'!F66,"#,##0")&"k (FY26A)." -> 2. Store productivity is the swing factor. NOV per store per day moved 766k (FY25A) to 756k (FY26A).
A65: 3. Blinkit's monthly transacting customers doubled to 27.2 mn and have now passed food delivery's 25.4 mn. Cross-sell between the two apps is the cheapest customer acquisition channel in Indian consumer internet.
A66: 4. Food delivery take rate expanded from 28.7% to 30.8% of NOV — platform fees and ad monetisation, not commission increases. This is what funds the 5-6% NOV margin guidance.
A67: 5. Delivery partner count (409k, Blinkit alone) is the operational constraint and the regulatory risk: any gig-worker social security mandate lands directly on delivery cost per order.

Sheet Ratios
A1: RATIOS & KPI DASHBOARD | P1: =Data_Sources!$D$3&" | "&Data_Sources!$E$3&" | "&Data_Sources!$F$3 -> Eternal Q4FY26 audited consolidated financial results | Statement of consolidated financial results, line I | https://b.zmtcdn.com/investor-relations/Eternal_Shareholders_Letter_Q4FY26_Results.pdf
A2: Metric | B2: Unit | D2: FY2023A | E2: FY2024A | F2: FY2025A | G2: FY2026A | H2: FY2027E | I2: FY2028E | J2: FY2029E | K2: FY2030E | L2: FY2031E | M2: FY2032E | N2: FY2033E | O2: FY2034E
A4: GROWTH
A5: B2C NOV growth | B5: % | E5: =IFERROR('Revenue Schedule'!D16/'Revenue Schedule'!C16-1,"") -> 0.46167216 | F5: =IFERROR('Revenue Schedule'!E16/'Revenue Schedule'!D16-1,"") -> 0.50104354 | G5: =IFERROR('Revenue Schedule'!F16/'Revenue Schedule'!E16-1,"") -> 0.55144539 | H5: =IFERROR('Revenue Schedule'!G16/'Revenue Schedule'!F16-1,"") -> 0.88085619 | I5: =IFERROR('Revenue Schedule'!H16/'Revenue Schedule'!G16-1,"") -> 0.35135134 | J5: =IFERROR('Revenue Schedule'!I16/'Revenue Schedule'!H16-1,"") -> 0.32706 | K5: =IFERROR('Revenue Schedule'!J16/'Revenue Schedule'!I16-1,"") -> 0.28500683 | L5: =IFERROR('Revenue Schedule'!K16/'Revenue Schedule'!J16-1,"") -> 0.24733255 | ... O5: =IFERROR('Revenue Schedule'!N16/'Revenue Schedule'!M16-1,"") -> 0.15682743
A6: Adjusted revenue growth | B6: % | E6: ='Revenue Schedule'!D27/'Revenue Schedule'!C27-1 -> 0.55815024 | F6: ='Revenue Schedule'!E27/'Revenue Schedule'!D27-1 -> 0.5944629 | G6: ='Revenue Schedule'!F27/'Revenue Schedule'!E27-1 -> 1.5884614 | H6: ='Revenue Schedule'!G27/'Revenue Schedule'!F27-1 -> 1.3868915 | I6: ='Revenue Schedule'!H27/'Revenue Schedule'!G27-1 -> 0.38923634 | J6: ='Revenue Schedule'!I27/'Revenue Schedule'!H27-1 -> 0.35745082 | K6: ='Revenue Schedule'!J27/'Revenue Schedule'!I27-1 -> 0.30565016 | L6: ='Revenue Schedule'!K27/'Revenue Schedule'!J27-1 -> 0.26352868 | ... O6: ='Revenue Schedule'!N27/'Revenue Schedule'!M27-1 -> 0.16296999
A7: Adjusted EBITDA growth | B7: % | E7: - | F7: =IS!F48/IS!E48-1 -> 1.9005376 | G7: =IS!G48/IS!F48-1 -> 0.10194625 | H7: =IS!H48/IS!G48-1 -> 1.1307639 | I7: =IS!I48/IS!H48-1 -> 1.140131 | J7: =IS!J48/IS!I48-1 -> 0.94772906 | K7: =IS!K48/IS!J48-1 -> 0.65724641 | L7: =IS!L48/IS!K48-1 -> 0.47445989 | M7: =IS!M48/IS!L48-1 -> 0.3218677 | ... O7: =IS!O48/IS!N48-1 -> 0.24284576
A9: MARGINS & RETURNS
A10: Adjusted EBITDA margin (% of adj. revenue) | B10: % | D10: =IS!D48/'Revenue Schedule'!C27 -> -0.090072472 | E10: =IS!E48/'Revenue Schedule'!D27 -> 0.027464009 | F10: =IS!F48/'Revenue Schedule'!E27 -> 0.049960643 | G10: =IS!G48/'Revenue Schedule'!F27 -> 0.021268984 | H10: =IS!H48/'Revenue Schedule'!G27 -> 0.018986696 | I10: =IS!I48/'Revenue Schedule'!H27 -> 0.029249174 | J10: =IS!J48/'Revenue Schedule'!I27 -> 0.041967978 | K10: =IS!K48/'Revenue Schedule'!J27 -> 0.053269462 | ... O10: =IS!O48/'Revenue Schedule'!N27 -> 0.076040905
A11: Adjusted EBITDA as % of B2C NOV | B11: % | D11: =IFERROR(IS!D48/'Revenue Schedule'!C16,"") -> -0.027774822 | E11: =IFERROR(IS!E48/'Revenue Schedule'!D16,"") -> 0.0090278115 | F11: =IFERROR(IS!F48/'Revenue Schedule'!E16,"") -> 0.017444868 | G11: =IFERROR(IS!G48/'Revenue Schedule'!F16,"") -> 0.012390579 | H11: =IFERROR(IS!H48/'Revenue Schedule'!G16,"") -> 0.014036905 | I11: =IFERROR(IS!I48/'Revenue Schedule'!H16,"") -> 0.022230203 | J11: =IFERROR(IS!J48/'Revenue Schedule'!I16,"") -> 0.03262732 | K11: =IFERROR(IS!K48/'Revenue Schedule'!J16,"") -> 0.042078772 | ... O11: =IFERROR(IS!O48/'Revenue Schedule'!N16,"") -> 0.062323368
A12: PAT margin (% of adj. revenue) | B12: % | D12: =IS!D29/'Revenue Schedule'!C27 -> -0.11158403 | E12: =IS!E29/'Revenue Schedule'!D27 -> 0.025913621 | F12: =IS!F29/'Revenue Schedule'!E27 -> 0.024401537 | G12: =IS!G29/'Revenue Schedule'!F27 -> 0.0065470547 | H12: =IS!H29/'Revenue Schedule'!G27 -> -0.055882338 | I12: =IS!I29/'Revenue Schedule'!H27 -> -0.044384743 | J12: =IS!J29/'Revenue Schedule'!I27 -> -0.028058508 | K12: =IS!K29/'Revenue Schedule'!J27 -> -0.0097472729 | ... O12: =IS!O29/'Revenue Schedule'!N27 -> 0.04111052
A13: Return on equity (PAT / average equity) | B13: % | E13: =IS!E29/AVERAGE(BS!D21:'BS'!E21) -> 0.017612083 | F13: =IS!F29/AVERAGE(BS!E21:'BS'!F21) -> 0.020782396 | G13: =IS!G29/AVERAGE(BS!F21:'BS'!G21) -> 0.011944585 | H13: =IS!H29/AVERAGE(BS!G21:'BS'!H21) -> -0.26948718 | I13: =IS!I29/AVERAGE(BS!H21:'BS'!I21) -> -0.39761613 | J13: =IS!J29/AVERAGE(BS!I21:'BS'!J21) -> -0.50654464 | K13: =IS!K29/AVERAGE(BS!J21:'BS'!K21) -> -0.32956764 | L13: =IS!L29/AVERAGE(BS!K21:'BS'!L21) -> 0.33795367 | ... O13: =IS!O29/AVERAGE(BS!N21:'BS'!O21) -> 0.44940171
